Workbook
Name \A: #REF!
Name \D: #REF!
Name \E: #REF!
Name \G: '[1]Company Related Premises'!#REF!
Name \H: '[1]Company Related Premises'!#REF!
Name \L: '[1]Company Related Premises'!#REF!
Name \M: '[1]Company Related Premises'!#REF!
Name \N: #REF!
Name \O: #REF!
Name \P: #REF!
Name \Q: #REF!
Name \R: #REF!
Name \S: #REF!
Name \T: #REF!
Name \U: #REF!
Name \V: #REF!
Name \W: #REF!
Name \X: #REF!
Name \xy: #REF!
Name \Y: #REF!
Name \Z: #REF!
Name __PR1: [2]Sheet!#REF!
Name __SR1: #REF!
Name __SR2: #REF!
Name _PR1: [2]Sheet!#REF!
Name _SR1: #REF!
Name _SR2: #REF!
Name aa: #REF!
Name aaa: #REF!
Name abcd: #REF!
Name All: #REF!
Name ANLAGE_III: [3]Anlagevermögen!$A$1:$Z$29
Name data84: '[4]Purchase Order'!$E$40
Name dflt3: '[4]Customize Your Purchase Order'!$F$24
Name dflt4: '[4]Customize Your Purchase Order'!$E$25
Name DRPAUSE: #REF!
Name DSCTEMP: [5]DSCTEMP!$A$1:$B$65536
Name FTBSch: [2]Sheet!#REF!
Name hh: [2]Sheet!#REF!
Name is: '[6]Company Related Premises'!#REF!
Name jngiüorajg: #REF!
Name ll: #REF!
Name new: #REF!
Name PeriodsInYear: #REF!
Name PrintArea: #REF!
Name qqqqqqqqqqqqqqqqqqqqq: #REF!
Name RANDO: #REF!
Name RANDU: #REF!
Name re: [7]Sheet!#REF!
Name Report: #REF!
Name Sale: #REF!
Name SalSch: #REF!
Name Seite1: #REF!
Name Seite2: #REF!
Name Seite3: #REF!
Name Spec: #REF!
Name SR: #REF!
Name SRC: #REF!
Name tes: [2]Sheet!#REF!
Name Test: [2]Sheet!#REF!

Sheet Company information
B2: COMPANY NAME (KHMER) | D2: វីអ៊ីស៊ិន (ខេមបូឌា) អ៊ិនដាសស្ទ្រី ឯ.ក | F2: AUDIT TIMELINE | H2: ពីថ្ងៃទី១ ខែមីនា ឆ្នាំ២០២៦ ដល់ថ្ងៃទី៣១ ខែមីនា ឆ្នាំ២០២៦
B3: COMPANY NAME (ENGLISH) | D3: Viiition (Cambodia)
B4: VAT NUMBER | D4: L001-901905215 | F4: MOC NUMBER | H4: ១៥៩៧៥៥៤៨MOC
B5: BUSINESS ACTIVITY | D5: កម្មន្តសាលសម្លៀកបំពាក់ (លើកលែងជាសម្លៀកបំពាក់ស្រាប់ឬកាត់) ( ) រោងចក្រកាត់ដេរសម្លៀកបំពាក់ | F5: MOC DATE OF ISSUE | H5: ១១-០៣-២០២៦
B6: ADDRESS NAME | D6: ផ្ទះលេខ ​ ផ្លូវ ​ ភូមិស្រង់ ឃុំស្រង់ ស្រុកគងពិសី ខេត្តកំពង់ស្ពឺ | F6: PATENT ISSUE DATE | H6: ២៣-០៣-២០២៦ | I6: PATENT AMOUNT | K6: ៥,០០០,០០០ ៛
B7: REQUEST PERIOD | D7: ខែមេសា ឆ្នាំ២០២៣ ដល់ខែវិច្ឆិកា ឆ្នាំ២០២៤ | F7: VAT CERTIFICATE ISSUE DATE | H7: ១៩-០៣-២០២៦
B8: AUDITOR NAME | D8: លោក ជា ហុកស័រ | E8: កញ្ញា ប៉ែន សុជាតា | F8: REQUEST DATE | H8: ស្នើសុំបង្វិលសងអាករលើតម្លៃបន្ថែមតាមអនឡាញចុះថ្ងៃទី២២ ខែមីនា ឆ្នាំ២០២៦
D9: ជា ហុកស័រ | E9: ប៉ែន សុជាតា | F9: AMOUNT OF REQUEST | H9: 879446544
B10: PHONE NUMBER | D10: 011777957
B11: BANK ACCOUNT NUMBER TO REFUND | D11: 38800502883099
B12: BANK NAME: | D12: ធនាគារ អេស៊ីលីដាACLEDA Bank Plc.
B13: PERSON TO CONTACT | D13: លោក លាង មេង
B14: POSITION | D14: គណនេយ្យករ

Sheet Annex I-IM State Charge
A1: តារាងឧបសម្ព័ន្ធ I
A2: បញ្ជាក់អំពីអាករលើធាតុចូលដែលមិនអាចស្នើសុំជាឥណទាន
A3: ( ការនាំចូលជាបន្ទុករបស់រដ្ឋ )
A4: ក្រុមហ៊ុន៖ | B4: ='Company information'!D2 | G4: សវនករពន្ធដារ៖ | H4: ='Company information'!D8
A5: លេខ អតប៖ | B5: ='Company information'!D4 | H5: ='Company information'!E8
A6: ='Company information'!E8 | G6: ទឹកប្រាក់ស្នើសុំបង្វិលសងចំនួន៖ | H6: ='Company information'!H9
A7: ល.រ | B7: បរិយាយ | C7: ប្រតិវេទន៍គយនាំចូល/វិក្កយបត្រ | E7: បង្កាន់ដៃទទួលប្រាក់ | G7: ប្រាក់អាករ (រៀល) | H7: ផ្សេងៗ
C8: លេខ | D8: ចុះថ្ងៃទី ខែ ឆ្នាំ | E8: លេខ | F8: ថ្ងៃ ខែ ឆ្នាំ
A9: 1 | C9: I821 | D9: 43857 | G9: 5671447
A10: 2 | C10: I820 | D10: 43857 | G10: 3115425
A11: 3 | C11: I608 | D11: 43850 | G11: 10824695
A12: 4 | C12: I609 | D12: 43843 | G12: 5811817
A13: 5 | C13: I459 | D13: 43845 | G13: 7391034
A14: 6 | B14: COMPUTER | C14: I292 | D14: 44207 | G14: 216700
A15: 7 | B15: AWNING ADAPTER METAL PRODUCTS PAPER SLIPSHEET PLASTIC ACCESSORIE A LIGHT BULB | C15: I291 | D15: 44207 | G15: 31606500
A16: 8 | B16: BATTERY COPPER PRODUCTS LED COPPER WIRE LAMPE LIGHT BULB METAL PRODUCTS PLASTIC ACCESSORIE A PLASTIC TUBE PRINTED CIRUIT BOARD ASSEMBLY SCREW SOLAR PANEL WIRE | C16: I242 | D16: 44204 | G16: 15832100
A17: 9 | B17: METAL PRODUCTS WOOD PRODUCTS | C17: I235 | D17: 44204 | G17: 5990300
A18: 10 | C18: I236 | D18: 44204 | G18: 13990100
A19: 11 | C19: I237 | D19: 44204 | G19: 6094100
A20: 12 | C20: I688 | D20: 44215 | G20: 120512600
A21: 13 | C21: I1016 | D21: 44222 | G21: 5723300
A22: 14 | C22: I961 | D22: 44221 | G22: 31514400
A23: 15 | C23: I1010 | D23: 44222 | G23: 82195100
A24: 16 | C24: I1183 | D24: 44224 | G24: 649700
A25: 17 | C25: I468 | D25: 44209 | G25: 18227300
A26: 18 | C26: I544 | D26: 44211 | G26: 55579000
A27: 19 | C27: I466 | D27: 44209 | G27: 688200
A28: 20 | C28: I707 | D28: 44215 | G28: 45324500
A29: 21 | C29: I240 | D29: 44204 | G29: 65935300
A30: 22 | B30: Import Raw Material | C30: I15369 | D30: 44562 | G30: 73348100
A31: 23 | B31: Import Raw Material | C31: I15321 | D31: 44562 | G31: 113862800
A32: 24 | B32: Import Raw Material | C32: I15323 | D32: 44562 | G32: 72377500
A33: 25 | B33: PLASTIC INJECTTION PRODUCTS,PRINTED CIRCUIT BOARD ASSEMBLY ,LIGHT BULB ... | C33: I1157 | D33: 44952 | G33: 39785000
A34: 26 | B34: PAPER BOARD ,COLOR BOX | C34: I1168 | D34: 44952 | G34: 4580700
A35: 27 | B35: IRON SHEET FRAME,PRINTED CIRCUIT BOARD ASSEMBLY ... | C35: I1166 | D35: 44952 | G35: 8832200
A36: 28 | B36: PRINTED CIRCUIT BOARD ASSEMBLY ,PLASTIC SPRAYING POWER (9),IRON WIRE (10)... | C36: I1162 | D36: 44952 | G36: 15314800
A37: 29 | B37: MOLD (INJECTION),IRON TUBE FRAME ,STRECH FILM | C37: I792 | D37: 44945 | G37: 8562800
A38: 30 | B38: IRON SHEET FRAME | C38: I791 | D38: 44945 | G38: 6542700
A39: 31 | B39: PLASTIC TUBE ,SOLAR PANELS (7),PLASTIC (BLOWN, INJECTION )PRODUCTS... | C39: I772 | D39: 44944 | G39: 10671300
A40: 32 | B40: SCREW (11),PRINTED CIRCUIT BOARD ASSEMBLY ,PLASTIC SPRAYING POWER (9)... | C40: I716 | D40: 44944 | G40: 13793200
A41: 33 | B41: STRECH FILM (10),SCREW (9),PLASTIC RESIN... Import Raw Material | C41: I705 | D41: 44944 | G41: 14164700
... A43: 35 | B43: IRON SHEET FRAME ,PLASTIC BLOWN PRODUCT | C43: I237 | D43: 44932 | G43: 4241700
A44: 36 | C44: I1914 | D44: 43886 | G44: 2542249
A45: 37 | C45: I1912 | D45: 43886 | G45: 40811364
A46: 38 | C46: I1856 | D46: 43885 | G46: 1616717
A47: 39 | C47: I1855 | D47: 43885 | G47: 23694486
A48: 40 | C48: I1858 | D48: 43885 | G48: 870431
A49: 41 | C49: I1857 | D49: 43885 | G49: 77071914
A50: 42 | C50: I1256 | D50: 43869 | G50: 53446350
A51: 43 | C51: I1257 | D51: 43868 | G51: 431947
A52: 44 | C52: I1255 | D52: 43867 | G52: 15842239
A53: 45 | C53: I1254 | D53: 43867 | G53: 22883094
A54: 46 | C54: I1260 | D54: 43867 | G54: 1796639
A55: 47 | C55: I1258 | D55: 43867 | G55: 62589725
A56: 48 | B56: CRUSHING MACHINE | C56: I2492 | D56: 44252 | G56: 917700
A57: 49 | B57: LIGHT STRING EQUIPMENT LAMP HOLDER DISCHARGE BARREL MOLD STORAGE STACKED LAMINATE ADAPTER BATTERY COLOR CARD COPPER PRODUCTS DOUBLE SIDED TAPE FUSE LED COPPER WIRE LAMPE LIGHT BEAD + LIGHT BULB METAL | C57: I2491 | D57: 44252 | G57: 92976900
A58: 50 | B58: MOLD STORAGE CAGE TESTING INSTRUMENT SOLDERING STATION ADAPTER BATTERY COPPER PRODUCTS DOUBLE SIDED TAPE ROCKER SWITCH WELDING WIRE FASTENER FUSE LED LIGHT LINE LIGHT BULB METAL ACCESSORIE PLASTIC ACC | C58: I2461 | D58: 44252 | G58: 85361300
A59: 51 | B59: LED COPPER WIRE LAMPE LIGHT BULB METAL PRODUCTS PLASTIC ACCESSORIE A PP1100RESIN | C59: I2200 | D59: 44249 | G59: 25264400
A60: 52 | B60: METAL RACK METAL PRODUCTS | C60: I1409 | D60: 44231 | G60: 4711200
A61: 53 | B61: METAL PRODUCTS PRINTED CIRCUIT BOARD ASSEMBLY PLASTIC MATERIAL (PP1100 RESIN) | C61: I1408 | D61: 44231 | G61: 11404100
A62: 54 | B62: LIGHT STRING EQUIPMENT PLASTIC PALLET TOOL FOR HAND BATTERY FASTENER LIGHT BULB METAL MATERIAL PLASTIC ACCESSORIE A POWER CORD H PRINTED CIRCUIT BOARD ASSEMBLY REMOTE CONTROL PLASTIC TUBE LED LIGHT LI | C62: I1407 | D62: 44231 | G62: 49032900
A63: 55 | B63: AWNING TESTING INSTRUMENT ADAPTER BATTERY FASTENER COPPER PRODUCTS DOUBLE SIDED TAPE ELECTRONIC COMPONENTS (ROCKER SWITCH) FUSE LED LIGHT LINE LIGHT BEAD + LIGHT BULB METAL ACCESSORIE METAL PRODUCTS P | C63: I1406 | D63: 44231 | G63: 83663000
A64: 56 | C64: I1649 | D64: 44236 | G64: 46414700
A65: 57 | C65: I2459 | D65: 44252 | G65: 20057300
A66: 58 | C66: I2463 | D66: 44252 | G66: 84083200
A67: 59 | C67: I2458 | D67: 44252 | G67: 12593900
A68: 60 | C68: I2460 | D68: 44252 | G68: 80975600
A69: 61 | C69: I2462 | D69: 44252 | G69: 51175300
A70: 62 | C70: I2367 | D70: 44251 | G70: 2403800
A71: 63 | C71: I2285 | D71: 44250 | G71: 38219500
A72: 64 | C72: I2286 | D72: 44250 | G72: 15758800
A73: 65 | C73: I2270 | D73: 44249 | G73: 19781100
A74: 66 | C74: I2275 | D74: 44249 | G74: 10143600
A75: 67 | C75: I2273 | D75: 44249 | G75: 23789300
... A81: 73 | C81: I1361 | D81: 44230 | G81: 1174500
A82: 74 | B82: Import Raw material | C82: I1797 | D82: 44596 | G82: 114059000
A83: 75 | B83: Import raw material | C83: I1578 | D83: 44596 | G83: 139731000
A84: 76 | B84: Import Raw material | C84: I1582 | D84: 44596 | G84: 32847400
A85: 77 | B85: Import Raw material | C85: I1559 | D85: 44596 | G85: 125660100
A86: 78 | B86: Import Raw Mterial | C86: I1553 | D86: 44596 | G86: 119180000
A87: 79 | B87: Import Raw Material | C87: I1565 | D87: 44596 | G87: 53707400
A88: 80 | B88: Import Raw Material | C88: I1547 | D88: 44593 | G88: 62472600
A89: 81 | B89: Import Raw Material | C89: I2446 | D89: 44979 | G89: 41872300
A90: 82 | B90: Import Raw Material | C90: I2451 | D90: 44979 | G90: 23469500
A91: 83 | B91: Import Raw Material | C91: I2453 | D91: 44979 | G91: 15671200
A92: 84 | B92: Import Raw Material | C92: I2445 | D92: 44979 | G92: 7878500
A93: 85 | B93: Import Raw Material | C93: I1453 | D93: 44959 | G93: 27931100
A94: 86 | C94: I2189 | D94: 43894 | G94: 5822386
A95: 87 | C95: I2934 | D95: 43910 | G95: 4827321
A96: 88 | B96: ការនាំចូលទំនិញមកពីក្រៅប្រទេស | C96: I3738 | D96: 44280 | G96: 48134400
A97: 89 | B97: ការនាំចូលទំនិញមកពីក្រៅប្រទេស | C97: I3741 | D97: 44280 | G97: 35664600
A98: 90 | B98: ការនាំចូលទំនិញមកពីក្រៅប្រទេស | C98: I3740 | D98: 44280 | G98: 91140700
A99: 91 | B99: ការនាំចូលទំនិញមកពីក្រៅប្រទេស | C99: I3739 | D99: 44280 | G99: 27280900
A100: 92 | B100: ការនាំចូលទំនិញមកពីក្រៅប្រទេស | C100: I3736 | D100: 44280 | G100: 51144700
A101: 93 | B101: ការនាំចូលទំនិញមកពីក្រៅប្រទេស | C101: I3745 | D101: 44280 | G101: 56154000
A102: 94 | B102: ការនាំចូលទំនិញមកពីក្រៅប្រទេស | C102: I3513 | D102: 44277 | G102: 26280300
A103: 95 | B103: ការនាំចូលទំនិញមកពីក្រៅប្រទេស | C103: I3255 | D103: 44271 | G103: 37498300
A104: 96 | B104: ការនាំចូលទំនិញមកពីក្រៅប្រទេស | C104: I3256 | D104: 44271 | G104: 17755100
A105: 97 | B105: ការនាំចូលទំនិញមកពីក្រៅប្រទេស | C105: I2672 | D105: 44258 | G105: 32917800
A106: 98 | B106: ការនាំចូលទំនិញមកពីក្រៅប្រទេស | C106: I2674 | D106: 44258 | G106: 66614300
...

Sheet Annex II-IM Non-State Charge
A1: តារាងឧបសម្ព័ន្ធ II
A2: តារាងផ្ទៀងផ្ទាត់បញ្ជាក់អំពីអាករលើធាតុចូលដែលអាចស្នើសុំជាឥណទាន
A3: ( ការនាំចូល ឬ អាករគិតជំនួស(Reverse Charge))
A4: ក្រុមហ៊ុន៖ | B4: ='Company information'!D2 | G4: សវនករពន្ធដារ៖ | H4: ='Company information'!D8
A5: លេខ អតប៖ | B5: ='Company information'!D4 | H5: ='Company information'!E8
A6: ='Company information'!E8 | G6: ទឹកប្រាក់ស្នើសុំបង្វិលសងចំនួន៖ | H6: ='Company information'!H9
A7: ល.រ | B7: បរិយាយ | C7: ប្រតិវេទន៍គយនាំចូល/ វិក្កយបត្រ | E7: បង្កាន់ដៃទទួលប្រាក់ | G7: ប្រាក់អាករ (រៀល) | H7: លទ្ធផលផ្ទៀងផ្ទាត់ជាមួយទិន្នន័យពីអគ្គនាយកដ្ឋានគយ/ ឬ អាករគិតជំនួស(Reverse Charge) | I7: ទឹកប្រាក់អនុញ្ញាត
C8: លេខ | D8: ចុះថ្ងៃទី ខែ ឆ្នាំ | E8: លេខ | F8: ថ្ងៃ ខែ ឆ្នាំ | J8: ខ្វះ
A10: I. ការនាំចូល
A11: 1 | C11: I2933 | D11: 43910 | G11: 86294 | I11: 85000 | J11: =G11-I11 | K11: test
A12: 2 | B12: Stretch Film | C12: I3963 | D12: 44287 | G12: 4225100 | I12: 1549751 | J12: =G12-I12
A13: 3 | B13: COB Light board | C13: I5395 | D13: 44337 | G13: 229500 | I13: 0 | J13: =G13-I13
A14: 4 | B14: Lamp holder | C14: I5399 | D14: 44337 | G14: 495400 | I14: 0 | J14: =G14-I14
A15: 5 | B15: ELECTRODE SLICE | C15: I8833 | D15: 44743 | G15: 3300 | I15: 0 | J15: =G15-I15
A16: 6 | B16: Industrial glasses | C16: I8938. | D16: 44414 | G16: 44200 | I16: 0 | J16: =G16-I16
A17: 7 | B17: Industrial glover | C17: I8938 | D17: 44414 | G17: 16300 | I17: 0 | J17: =G17-I17
A18: 8 | B18: Iron stand | C18: I9185 | D18: 44420 | G18: 258400 | I18: 0 | J18: =G18-I18
A19: 9 | B19: Iron tube | C19: I9187 | D19: 44420 | G19: 3710600 | I19: 0 | J19: =G19-I19
A20: 10 | B20: IRON STAND | C20: I10359. | D20: 44446 | G20: 518400 | I20: 0 | J20: =G20-I20
A21: 11 | B21: Import Raw Material | C21: I10761 | D21: 44455 | G21: 65700 | I21: 0 | J21: =G21-I21
A22: 12 | C22: I9794 | D22: 44110 | G22: 1047700 | I22: 0 | J22: =G22-I22
A23: 13 | C23: I12103 | D23: 43810 | G23: 248568 | I23: 0 | J23: =G23-I23
A24: II. អាករលើតម្លៃបន្ថែមតាមវិធីគិតអាករជំនួស(Reverse Charge)
A25: 1 | B25: Online serivce | C25: 01-02-2024 | D25: 19108.4 | G25: 19108.4 | H25: អនុញ្ញាត (បានប្រកាស) | I25: =G25 | J25: =G25-I25
A26: 2 | B26: Online service | C26: 01-02-2024 | D26: 19042.9 | G26: 19042.9 | H26: អនុញ្ញាត (បានប្រកាស) | I26: =G26 | J26: =G26-I26
A27: 3 | B27: Software License | C27: 26-02-2024 | D27: 203450 | G27: 203450 | H27: អនុញ្ញាត (បានប្រកាស) | I27: =G27 | J27: =G27-I27
A28: 4 | B28: Online Service | C28: 01-03-2024 | D28: 18911.9 | G28: 18911.9 | H28: អនុញ្ញាត (បានប្រកាស) | I28: =G28 | J28: =G28-I28
A29: 5 | B29: Online Service | C29: 01-05-2024 | D29: 19155.2 | G29: 19155.2 | H29: អនុញ្ញាត (បានប្រកាស) | I29: =G29 | J29: =G29-I29
A30: 6 | B30: Online Service | C30: 01-06-2024 | D30: 19234.8 | G30: 19234.8 | H30: អនុញ្ញាត (បានប្រកាស) | I30: =G30 | J30: =G30-I30
A31: 7 | B31: Online Service | C31: 01-07-2024 | D31: 19225.4 | G31: 19225.4 | H31: អនុញ្ញាត (បានប្រកាស) | I31: =G31 | J31: =G31-I31
A32: 8 | B32: Online Services | C32: 01-08-2024 | D32: 18986.8 | G32: 18986.8 | H32: អនុញ្ញាត (បានប្រកាស) | I32: =G32 | J32: =G32-I32
A33: 9 | B33: Online Services | C33: 28-09-2024 | D33: 19005.5 | G33: 19005.5 | H33: អនុញ្ញាត (បានប្រកាស) | I33: =G33 | J33: =G33-I33
A34: 10 | B34: Online Services | C34: 01-09-2024 | D34: 19005.5 | G34: 19005.5 | H34: អនុញ្ញាត (បានប្រកាស) | I34: =G34 | J34: =G34-I34
A35: 11 | B35: Online Services | C35: 28-10-2024 | D35: 19014.8 | G35: 19014.8 | H35: អនុញ្ញាត (បានប្រកាស) | I35: =G35 | J35: =G35-I35
A36: 12 | B36: Online Service | C36: 28-11-2024 | D36: 18851 | G36: 18851 | H36: អនុញ្ញាត (បានប្រកាស) | I36: =G36 | J36: =G36-I36
A37: 13 | B37: Online Services | C37: 28-12-2024 | D37: 18837 | G37: 18837 | H37: អនុញ្ញាត (បានប្រកាស) | I37: =G37 | J37: =G37-I37
A38: សរុបអាករលើការនាំចូល ឬ អាករលើតម្លៃបន្ថែមតាមវិធីគិតអាករជំនួស(Reverse Charge) | G38: =SUM(G11:G37) | H38: សរុបទឺកប្រាក់អនុញ្ញាត | I38: =SUM(I11:I37) | J38: =SUM(J11:J37)
A40: សេចក្តីធានាអះអាងរបស់មន្ត្រីសវនករទទួលបន្ទុក៖ លទ្ធផលផ្ទៀងផ្ទាត់ឥណទានអាករ ចំពោះការនាំចូល ឬ/និង អាករលើតម្លៃបន្ថែមតាមវិធីគិតអាករជំនួស(Reverse Charge)ខាងលើពិតជាត្រឹមត្រូវតាមរបាយការណ៍លម្អិតដែលបានទាញទិន្នន័យពីអគ្គនាយកដ្ឋានគយ/ប្រព័ន្ធE-Filing ពិតប្រាកដមែន។
E43: រាជធានីភ្នំពេញ.ថ្ងៃទី ខែ ឆ្នាំ
E44: មន្ត្រីសវនកម្ម
E46: ='Company information'!D9 | I46: ='Company information'!E9

Sheet AnnexIII-Local Pur
A1: តារាងឧបសម្ព័ន្ធ III
A2: តារាងផ្ទៀងផ្ទាត់បញ្ជាក់អំពីអាករលើធាតុចូលដែលអាចស្នើសុំជាឥណទាន
A3: (ការទិញក្នុងស្រុក)
A4: ក្រុមហ៊ុន៖ | B4: ='Company information'!D2 | I4: សវនករពន្ធដារ៖ | K4: ='Company information'!D8
A5: លេខ អតប៖ | B5: ='Company information'!D4 | K5: ='Company information'!E8 | N5: FOR REPORT | V5: សម្គាល់ផ្សេងៗ | X5: បញ្ចូលទិន្នន័យ
A6: ='Company information'!E8 | I6: ទឹកប្រាក់ស្នើសុំបង្វិលសងចំនួន៖ | J6: ='Company information'!H9
A7: ល.រ | B7: បរិយាយ | C7: អ្នកផ្គត់ផ្គង់ | D7: លេខ អតប | E7: វិក្កយបត្រ | G7: ទឹកប្រាក់អាករ | J7: ស្ថានភាព | K7: ស្ថានភាពអ្នកប្រើប្រាស់ | L7: មតិអ្នកប្រើប្រាស់ | M7: ផ្សេង (សម្គាល់) | Q7: PURCHASE | R7: SUPPLIER | S7: VAR INVOICE T/F | T7: VAR. DATE T/F | U7: VAR. SUPPLIER & PUCHASER | V7: តេស្តទឹកប្រាក់លម្អៀង | W7: សម្កាល់ | X7: កាលបរិច្ឆេទ | Y7: លេខវិក្កយបត្រ ឬប្រតិវេទគយ | Z7: លេខលិខិតជូនដំណឹងឥណទាន | AA7: អ្នកទិញ | AD7: តម្លៃសរុបលើវិក្កយបត្រ | AE7: តម្លៃ​​មិន​រួមអតប និងមិនជាប់​អតប​ | AG7: អាករលើតម្លៃបន្ថែមអត្រា ០% | AH7: អាករលើតម្លៃបន្ថែម | AJ7: អាករលើតម្លៃបន្ថែម(បន្ទុករដ្ឋ) | AK7: អតប កាត់ទុកដោយរតនាគារជាតិ | AL7: អាករបំភ្លឺសាធារណៈ | AM7: អាករពិសេសលើទំនិញមួយចំនួន | AN7: អាករពិសេសលើសេវាមួយចំនួន | AO7: អាករលើការស្នាក់នៅ | AP7: អត្រាប្រាក់រំដោះពន្ធលើប្រាក់ចំណូល | AQ7: កំណត់សម្គាល់ | AR7: បរិយាយ | AS7: ស្ថានភាពប្រកាសពន្ធ
E8: លេខ | F8: ថ្ងៃ ខែ ឆ្នាំ | G8: ជាដុល្លារអាមេរិក | H8: អត្រា | I8: ជារៀល | N8: បានប្រកាស | O8: នៅខ្វះ | P8: ស្ថានភាពត្រួតពិនិត្យ | AA8: ប្រភេទ | AB8: លេខសម្គាល់ចុះបញ្ជីពន្ធដា | AC8: ឈ្មោះ | AE8: តម្លៃមិនរួមអតប | AF8: ការលក់មិនជាប់អតប | AH8: ការលក់ក្នុងស្រុក | AI8: អតបលើការនាំចេញ
A9: 1 | C9: អ៊ីជីអេហ្វ ឡូជីស្ទីក ខូ អិលធីឌី | D9: L001-901501877 | E9: 2001007 | F9: 43861 | G9: 279450 | I9: 279450 | J9: =IF(AND(S9=TRUE, T9=TRUE, U9=TRUE), IF(W9<-0.05, "អនុញ្ញាត (អ្នកផ្គត់ផ្គង់ប្រកាសខ្វះ)", "បានប្រកាស (អនុញ្ញាត)"), IF(AND(S9=FALSE, T9=FALSE, U9=FALSE), "ព្យួរទុក (មិនមានទិន្នន័យ)", "ប្រកាសខុស (ព្យួរទុក)")) | N9: =IF(W9<0,AH9,I9) | O9: =I9-M9 | Q9: 2001007 | R9: 2001007 | S9: =Q9=R9 | T9: =AND(MONTH(F9)=MONTH(X9), YEAR(F9)=YEAR(X9)) | U9: =AND(AB9<>"", 'Company information'!D$4<>"", RIGHT(SUBSTITUTE(AB9,"-",""),9)=RIGHT(SUBSTITUTE('Company information'!D$4,"-",""),9)) | V9: =AH9-I9 | X9: 43861 | Y9: 2001007 | AA9: បុគ្គលជាប់អាករ | AB9: L001-901905215 | AC9: វីអ៊ីស៊ិន (ខេមបូឌា) អ៊ិនដាសស្ទ្រី ឯ.ក | AD9: 3073950 | AE9: 2794500 | AF9: 0 | AG9: 123 | AH9: 279450 | AI9: 0 | AJ9: 0 | AK9: 0 | AL9: 0 | AM9: 0 | AN9: 0 | AO9: 0 | AP9: 0 | AS9: បានប្រកាសពន្ធ
A10: 2 | C10: អិនខេ ត្រេឌីង (ខេមបូឌា) ឯ.ក | D10: K009-901700707 | E10: NK00006 | F10: 43844 | G10: 406000 | I10: 406000 | J10: =IF(AND(S10=TRUE, T10=TRUE, U10=TRUE), IF(W10<-0.05, "អនុញ្ញាត (អ្នកផ្គត់ផ្គង់ប្រកាសខ្វះ)", "បានប្រកាស (អនុញ្ញាត)"), IF(AND(S10=FALSE, T10=FALSE, U10=FALSE), "ព្យួរទុក (មិនមានទិន្នន័យ)", "ប្រកាសខុស (ព្យួរទុក)")) | N10: =IF(W10<0,AH10,I10) | O10: =I10-M10 | Q10: NK00006 | R10: NK-00006 | S10: =Q10=R10 | T10: =AND(MONTH(F10)=MONTH(X10), YEAR(F10)=YEAR(X10)) | U10: =AND(AB10<>"", 'Company information'!D$4<>"", RIGHT(SUBSTITUTE(AB10,"-",""),9)=RIGHT(SUBSTITUTE('Company information'!D$4,"-",""),9)) | V10: =AH10-I10 | X10: 43844 | Y10: NK-00006 | AA10: បុគ្គលជាប់អាករ | AB10: L001-901905215 | AC10: វីអ៊ីស៊ិន (ខេមបូឌា) អ៊ិនដាសស្ទ្រី ឯ.ក | AD10: 4455000 | AE10: 4050000 | AF10: 0 | AG10: 0 | AH10: 405000 | AI10: 0 | AJ10: 0 | AK10: 0 | AL10: 0 | AM10: 0 | AN10: 0 | AO10: 0 | AP10: 0 | AS10: បានប្រកាសពន្ធ
A11: 3 | C11: ថេកអេស៊ីស៊ី ផេភើរ សឺវីស ខនសាល់ធេន ឯ.ក | D11: K004-901801112 | E11: 000013 | F11: 44105 | G11: 162800 | I11: 162800 | J11: =IF(AND(S11=TRUE, T11=TRUE, U11=TRUE), IF(W11<-0.05, "អនុញ្ញាត (អ្នកផ្គត់ផ្គង់ប្រកាសខ្វះ)", "បានប្រកាស (អនុញ្ញាត)"), IF(AND(S11=FALSE, T11=FALSE, U11=FALSE), "ព្យួរទុក (មិនមានទិន្នន័យ)", "ប្រកាសខុស (ព្យួរទុក)")) | N11: =IF(W11<0,AH11,I11) | O11: =I11-M11 | Q11: 000013 | R11: 000013 | S11: =Q11=R11 | T11: =AND(MONTH(F11)=MONTH(X11), YEAR(F11)=YEAR(X11)) | U11: =AND(AB11<>"", 'Company information'!D$4<>"", RIGHT(SUBSTITUTE(AB11,"-",""),9)=RIGHT(SUBSTITUTE('Company information'!D$4,"-",""),9)) | V11: =AH11-I11 | X11: 43840 | Y11: 000013 | AA11: បុគ្គលជាប់អាករ | AB11: L001-901905215 | AC11: វីអ៊ីស៊ិន (ខេមបូឌា) អ៊ិនដាសស្ទ្រី ឯ.ក | AD11: 1790800 | AE11: 1628000 | AF11: 0 | AG11: 0 | AH11: 162800 | AI11: 0 | AJ11: 0 | AK11: 0 | AL11: 0 | AM11: 0 | AN11: 0 | AO11: 0 | AP11: 0 | AS11: បានប្រកាសពន្ធ
A12: 4 | C12: ប្យួរ៉ូ វេរីតាស (ខេមបូឌា) លីមីធីត | D12: L001-107024462 | E12: 59006679 | F12: 43861 | G12: 67073 | I12: 67073 | J12: =IF(AND(S12=TRUE, T12=TRUE, U12=TRUE), IF(W12<-0.05, "អនុញ្ញាត (អ្នកផ្គត់ផ្គង់ប្រកាសខ្វះ)", "បានប្រកាស (អនុញ្ញាត)"), IF(AND(S12=FALSE, T12=FALSE, U12=FALSE), "ព្យួរទុក (មិនមានទិន្នន័យ)", "ប្រកាសខុស (ព្យួរទុក)")) | N12: =IF(W12<0,AH12,I12) | O12: =I12-M12 | Q12: 59006679 | R12: 59006679 | S12: =Q12=R12 | T12: =AND(MONTH(F12)=MONTH(X12), YEAR(F12)=YEAR(X12)) | U12: =AND(AB12<>"", 'Company information'!D$4<>"", RIGHT(SUBSTITUTE(AB12,"-",""),9)=RIGHT(SUBSTITUTE('Company information'!D$4,"-",""),9)) | V12: =AH12-I12 | X12: 43861 | Y12: 59006679 | AA12: បុគ្គលជាប់អាករ | AB12: L001-901905215 | AC12: វីអ៊ីស៊ិន (ខេមបូឌា) អ៊ិនដាសស្ទ្រី ឯ.ក | AD12: 737797 | AE12: 670725 | AF12: 0 | AG12: 0 | AH12: 67072 | AI12: 0 | AJ12: 0 | AK12: 0 | AL12: 0 | AM12: 0 | AN12: 0 | AO12: 0 | AP12: 0 | AS12: បានប្រកាសពន្ធ
A13: 5 | C13: ប្យួរ៉ូ វេរីតាស (ខេមបូឌា) លីមីធីត | D13: L001-107024462 | E13: 59006668 | F13: 43861 | G13: 102845 | I13: 102845 | J13: =IF(AND(S13=TRUE, T13=TRUE, U13=TRUE), IF(W13<-0.05, "អនុញ្ញាត (អ្នកផ្គត់ផ្គង់ប្រកាសខ្វះ)", "បានប្រកាស (អនុញ្ញាត)"), IF(AND(S13=FALSE, T13=FALSE, U13=FALSE), "ព្យួរទុក (មិនមានទិន្នន័យ)", "ប្រកាសខុស (ព្យួរទុក)")) | N13: =IF(W13<0,AH13,I13) | O13: =I13-M13 | Q13: 59006668 | R13: 59006668 | S13: =Q13=R13 | T13: =AND(MONTH(F13)=MONTH(X13), YEAR(F13)=YEAR(X13)) | U13: =AND(AB13<>"", 'Company information'!D$4<>"", RIGHT(SUBSTITUTE(AB13,"-",""),9)=RIGHT(SUBSTITUTE('Company information'!D$4,"-",""),9)) | V13: =AH13-I13 | X13: 43861 | Y13: 59006668 | AA13: បុគ្គលជាប់អាករ | AB13: L001-901905215 | AC13: វីអ៊ីស៊ិន (ខេមបូឌា) អ៊ិនដាសស្ទ្រី ឯ.ក | AD13: 1131289 | AE13: 1028445 | AF13: 0 | AG13: 0 | AH13: 102844 | AI13: 0 | AJ13: 0 | AK13: 0 | AL13: 0 | AM13: 0 | AN13: 0 | AO13: 0 | AP13: 0 | AS13: បានប្រកាសពន្ធ
A14: 6 | C14: ប្យួរ៉ូ វេរីតាស (ខេមបូឌា) លីមីធីត | D14: L001-107024462 | E14: 59006650 | F14: 43860 | G14: 134145 | I14: 134145 | J14: =IF(AND(S14=TRUE, T14=TRUE, U14=TRUE), IF(W14<-0.05, "អនុញ្ញាត (អ្នកផ្គត់ផ្គង់ប្រកាសខ្វះ)", "បានប្រកាស (អនុញ្ញាត)"), IF(AND(S14=FALSE, T14=FALSE, U14=FALSE), "ព្យួរទុក (មិនមានទិន្នន័យ)", "ប្រកាសខុស (ព្យួរទុក)")) | N14: =IF(W14<0,AH14,I14) | O14: =I14-M14 | Q14: 59006650 | R14: 59006650 | S14: =Q14=R14 | T14: =AND(MONTH(F14)=MONTH(X14), YEAR(F14)=YEAR(X14)) | U14: =AND(AB14<>"", 'Company information'!D$4<>"", RIGHT(SUBSTITUTE(AB14,"-",""),9)=RIGHT(SUBSTITUTE('Company information'!D$4,"-",""),9)) | V14: =AH14-I14 | X14: 43860 | Y14: 59006650 | AA14: បុគ្គលជាប់អាករ | AB14: L001-901905215 | AC14: វីអ៊ីស៊ិន (ខេមបូឌា) អ៊ិនដាសស្ទ្រី ឯ.ក | AD14: 1475595 | AE14: 1341450 | AF14: 0 | AG14: 0 | AH14: 134145 | AI14: 0 | AJ14: 0 | AK14: 0 | AL14: 0 | AM14: 0 | AN14: 0 | AO14: 0 | AP14: 0 | AS14: បានប្រកាសពន្ធ
A15: 7 | C15: ប្យួរ៉ូ វេរីតាស (ខេមបូឌា) លីមីធីត | D15: L001-107024462 | E15: 59006649 | F15: 43860 | G15: 67073 | I15: 67073 | J15: =IF(AND(S15=TRUE, T15=TRUE, U15=TRUE), IF(W15<-0.05, "អនុញ្ញាត (អ្នកផ្គត់ផ្គង់ប្រកាសខ្វះ)", "បានប្រកាស (អនុញ្ញាត)"), IF(AND(S15=FALSE, T15=FALSE, U15=FALSE), "ព្យួរទុក (មិនមានទិន្នន័យ)", "ប្រកាសខុស (ព្យួរទុក)")) | N15: =IF(W15<0,AH15,I15) | O15: =I15-M15 | Q15: 59006649 | R15: 59006649 | S15: =Q15=R15 | T15: =AND(MONTH(F15)=MONTH(X15), YEAR(F15)=YEAR(X15)) | U15: =AND(AB15<>"", 'Company information'!D$4<>"", RIGHT(SUBSTITUTE(AB15,"-",""),9)=RIGHT(SUBSTITUTE('Company information'!D$4,"-",""),9)) | V15: =AH15-I15 | X15: 43860 | Y15: 59006649 | Z15: 123 | AA15: បុគ្គលជាប់អាករ | AB15: L001-901905215 | AC15: វីអ៊ីស៊ិន (ខេមបូឌា) អ៊ិនដាសស្ទ្រី ឯ.ក | AD15: 737797 | AE15: 670725 | AF15: 0 | AG15: 0 | AH15: 67072 | AI15: 0 | AJ15: 0 | AK15: 0 | AL15: 0 | AM15: 0 | AN15: 0 | AO15: 0 | AP15: 0 | AS15: បានប្រកាសពន្ធ
A16: 8 | C16: ប្យួរ៉ូ វេរីតាស (ខេមបូឌា) លីមីធីត | D16: L001-107024462 | E16: 59006619 | F16: 43850 | G16: 399590 | I16: 399590 | J16: =IF(AND(S16=TRUE, T16=TRUE, U16=TRUE), IF(W16<-0.05, "អនុញ្ញាត (អ្នកផ្គត់ផ្គង់ប្រកាសខ្វះ)", "បានប្រកាស (អនុញ្ញាត)"), IF(AND(S16=FALSE, T16=FALSE, U16=FALSE), "ព្យួរទុក (មិនមានទិន្នន័យ)", "ប្រកាសខុស (ព្យួរទុក)")) | N16: =IF(W16<0,AH16,I16) | O16: =I16-M16 | Q16: 59006619 | R16: 59006619 | S16: =Q16=R16 | T16: =AND(MONTH(F16)=MONTH(X16), YEAR(F16)=YEAR(X16)) | U16: =AND(AB16<>"", 'Company information'!D$4<>"", RIGHT(SUBSTITUTE(AB16,"-",""),9)=RIGHT(SUBSTITUTE('Company information'!D$4,"-",""),9)) | V16: =AH16-I16 | X16: 43850 | Y16: 59006619 | AA16: បុគ្គលជាប់អាករ | AB16: L001-901905215 | AC16: វីអ៊ីស៊ិន (ខេមបូឌា) អ៊ិនដាសស្ទ្រី ឯ.ក | AD16: 4395484 | AE16: 3995895 | AF16: 0 | AG16: 0 | AH16: 399589 | AI16: 0 | AJ16: 0 | AK16: 0 | AL16: 0 | AM16: 0 | AN16: 0 | AO16: 0 | AP16: 0 | AS16: បានប្រកាសពន្ធ
A17: 9 | C17: ប្យួរ៉ូ វេរីតាស (ខេមបូឌា) លីមីធីត | D17: L001-107024462 | E17: 59006612 | F17: 43848 | G17: 67073 | I17: 67073 | J17: =IF(AND(S17=TRUE, T17=TRUE, U17=TRUE), IF(W17<-0.05, "អនុញ្ញាត (អ្នកផ្គត់ផ្គង់ប្រកាសខ្វះ)", "បានប្រកាស (អនុញ្ញាត)"), IF(AND(S17=FALSE, T17=FALSE, U17=FALSE), "ព្យួរទុក (មិនមានទិន្នន័យ)", "ប្រកាសខុស (ព្យួរទុក)")) | N17: =IF(W17<0,AH17,I17) | O17: =I17-M17 | Q17: 59006612 | R17: 59006612 | S17: =Q17=R17 | T17: =AND(MONTH(F17)=MONTH(X17), YEAR(F17)=YEAR(X17)) | U17: =AND(AB17<>"", 'Company information'!D$4<>"", RIGHT(SUBSTITUTE(AB17,"-",""),9)=RIGHT(SUBSTITUTE('Company information'!D$4,"-",""),9)) | V17: =AH17-I17 | X17: 43848 | Y17: 59006612 | AA17: បុគ្គលជាប់អាករ | AB17: L001-901905215 | AC17: វីអ៊ីស៊ិន (ខេមបូឌា) អ៊ិនដាសស្ទ្រី ឯ.ក | AD17: 737797 | AE17: 670725 | AF17: 0 | AG17: 0 | AH17: 67072 | AI17: 0 | AJ17: 0 | AK17: 0 | AL17: 0 | AM17: 0 | AN17: 0 | AO17: 0 | AP17: 0 | AS17: បានប្រកាសពន្ធ
A18: 10 | C18: ប្យួរ៉ូ វេរីតាស (ខេមបូឌា) លីមីធីត | D18: L001-107024462 | E18: 59006582 | F18: 43847 | G18: 134145 | I18: 134145 | J18: =IF(AND(S18=TRUE, T18=TRUE, U18=TRUE), IF(W18<-0.05, "អនុញ្ញាត (អ្នកផ្គត់ផ្គង់ប្រកាសខ្វះ)", "បានប្រកាស (អនុញ្ញាត)"), IF(AND(S18=FALSE, T18=FALSE, U18=FALSE), "ព្យួរទុក (មិនមានទិន្នន័យ)", "ប្រកាសខុស (ព្យួរទុក)")) | N18: =IF(W18<0,AH18,I18) | O18: =I18-M18 | Q18: 59006582 | R18: 59006582 | S18: =Q18=R18 | T18: =AND(MONTH(F18)=MONTH(X18), YEAR(F18)=YEAR(X18)) | U18: =AND(AB18<>"", 'Company information'!D$4<>"", RIGHT(SUBSTITUTE(AB18,"-",""),9)=RIGHT(SUBSTITUTE('Company information'!D$4,"-",""),9)) | V18: =AH18-I18 | X18: 43847 | Y18: 59006582 | AA18: បុគ្គលជាប់អាករ | AB18: L001-901905215 | AC18: វីអ៊ីស៊ិន (ខេមបូឌា) អ៊ិនដាសស្ទ្រី ឯ.ក | AD18: 1475595 | AE18: 1341450 | AF18: 0 | AG18: 0 | AH18: 134145 | AI18: 0 | AJ18: 0 | AK18: 0 | AL18: 0 | AM18: 0 | AN18: 0 | AO18: 0 | AP18: 0 | AS18: បានប្រកាសពន្ធ
A19: 11 | C19: ប្យួរ៉ូ វេរីតាស (ខេមបូឌា) លីមីធីត | D19: L001-107024462 | E19: 59006581 | F19: 43847 | G19: 134145 | I19: 134145 | J19: =IF(AND(S19=TRUE, T19=TRUE, U19=TRUE), IF(W19<-0.05, "អនុញ្ញាត (អ្នកផ្គត់ផ្គង់ប្រកាសខ្វះ)", "បានប្រកាស (អនុញ្ញាត)"), IF(AND(S19=FALSE, T19=FALSE, U19=FALSE), "ព្យួរទុក (មិនមានទិន្នន័យ)", "ប្រកាសខុស (ព្យួរទុក)")) | N19: =IF(W19<0,AH19,I19) | O19: =I19-M19 | Q19: 59006581 | R19: 59006581 | S19: =Q19=R19 | T19: =AND(MONTH(F19)=MONTH(X19), YEAR(F19)=YEAR(X19)) | U19: =AND(AB19<>"", 'Company information'!D$4<>"", RIGHT(SUBSTITUTE(AB19,"-",""),9)=RIGHT(SUBSTITUTE('Company information'!D$4,"-",""),9)) | V19: =AH19-I19 | X19: 43847 | Y19: 59006581 | AA19: បុគ្គលជាប់អាករ | AB19: L001-901905215 | AC19: វីអ៊ីស៊ិន (ខេមបូឌា) អ៊ិនដាសស្ទ្រី ឯ.ក | AD19: 1475595 | AE19: 1341450 | AF19: 0 | AG19: 0 | AH19: 134145 | AI19: 0 | AJ19: 0 | AK19: 0 | AL19: 0 | AM19: 0 | AN19: 0 | AO19: 0 | AP19: 0 | AS19: បានប្រកាសពន្ធ
A20: 12 | C20: ប្យួរ៉ូ វេរីតាស (ខេមបូឌា) លីមីធីត | D20: L001-107024462 | E20: 59006580 | F20: 43847 | G20: 67073 | I20: 67073 | J20: =IF(AND(S20=TRUE, T20=TRUE, U20=TRUE), IF(W20<-0.05, "អនុញ្ញាត (អ្នកផ្គត់ផ្គង់ប្រកាសខ្វះ)", "បានប្រកាស (អនុញ្ញាត)"), IF(AND(S20=FALSE, T20=FALSE, U20=FALSE), "ព្យួរទុក (មិនមានទិន្នន័យ)", "ប្រកាសខុស (ព្យួរទុក)")) | N20: =IF(W20<0,AH20,I20) | O20: =I20-M20 | Q20: 59006580 | R20: 59006580 | S20: =Q20=R20 | T20: =AND(MONTH(F20)=MONTH(X20), YEAR(F20)=YEAR(X20)) | U20: =AND(AB20<>"", 'Company information'!D$4<>"", RIGHT(SUBSTITUTE(AB20,"-",""),9)=RIGHT(SUBSTITUTE('Company information'!D$4,"-",""),9)) | V20: =AH20-I20 | X20: 43847 | Y20: 59006580 | AA20: បុគ្គលជាប់អាករ | AB20: L001-901905215 | AC20: វីអ៊ីស៊ិន (ខេមបូឌា) អ៊ិនដាសស្ទ្រី ឯ.ក | AD20: 737797 | AE20: 670725 | AF20: 0 | AG20: 0 | AH20: 67072 | AI20: 0 | AJ20: 0 | AK20: 0 | AL20: 0 | AM20: 0 | AN20: 0 | AO20: 0 | AP20: 0 | AS20: បានប្រកាសពន្ធ
A21: 13 | C21: ប្យួរ៉ូ វេរីតាស (ខេមបូឌា) លីមីធីត | D21: L001-107024462 | E21: 59006451 | F21: 43846 | G21: 67073 | I21: 67073 | J21: =IF(AND(S21=TRUE, T21=TRUE, U21=TRUE), IF(W21<-0.05, "អនុញ្ញាត (អ្នកផ្គត់ផ្គង់ប្រកាសខ្វះ)", "បានប្រកាស (អនុញ្ញាត)"), IF(AND(S21=FALSE, T21=FALSE, U21=FALSE), "ព្យួរទុក (មិនមានទិន្នន័យ)", "ប្រកាសខុស (ព្យួរទុក)")) | N21: =IF(W21<0,AH21,I21) | O21: =I21-M21 | Q21: 59006451 | R21: 59006451 | S21: =Q21=R21 | T21: =AND(MONTH(F21)=MONTH(X21), YEAR(F21)=YEAR(X21)) | U21: =AND(AB21<>"", 'Company information'!D$4<>"", RIGHT(SUBSTITUTE(AB21,"-",""),9)=RIGHT(SUBSTITUTE('Company information'!D$4,"-",""),9)) | V21: =AH21-I21 | X21: 43843 | Y21: 59006451 | AA21: បុគ្គលជាប់អាករ | AB21: L001-901700229 | AC21: ឈី មីង ស៊ីន ហ្វេកធើរី ឯ.ក | AD21: 18333 | AE21: 16666 | AF21: 0 | AG21: 0 | AH21: 1667 | AI21: 0 | AJ21: 0 | AK21: 0 | AL21: 0 | AM21: 0 | AN21: 0 | AO21: 0 | AP21: 0 | AS21: បានប្រកាសពន្ធ
A22: 14 | C22: ប្យួរ៉ូ វេរីតាស (ខេមបូឌា) លីមីធីត | D22: L001-107024462 | E22: 59006450 | F22: 43843 | G22: 229673 | I22: 229673 | J22: =IF(AND(S22=TRUE, T22=TRUE, U22=TRUE), IF(W22<-0.05, "អនុញ្ញាត (អ្នកផ្គត់ផ្គង់ប្រកាសខ្វះ)", "បានប្រកាស (អនុញ្ញាត)"), IF(AND(S22=FALSE, T22=FALSE, U22=FALSE), "ព្យួរទុក (មិនមានទិន្នន័យ)", "ប្រកាសខុស (ព្យួរទុក)")) | N22: =IF(W22<0,AH22,I22) | O22: =I22-M22 | Q22: 59006450 | R22: 59006450 | S22: =Q22=R22 | T22: =AND(MONTH(F22)=MONTH(X22), YEAR(F22)=YEAR(X22)) | U22: =AND(AB22<>"", 'Company information'!D$4<>"", RIGHT(SUBSTITUTE(AB22,"-",""),9)=RIGHT(SUBSTITUTE('Company information'!D$4,"-",""),9)) | V22: =AH22-I22 | X22: 43843 | Y22: 59006450 | Z22: 123 | AA22: បុគ្គលជាប់អាករ | AB22: L001-901905215 | AC22: វីអ៊ីស៊ិន (ខេមបូឌា) អ៊ិនដាសស្ទ្រី ឯ.ក | AD22: 2526397 | AE22: 2296725 | AF22: 0 | AG22: 0 | AH22: 229672 | AI22: 0 | AJ22: 0 | AK22: 0 | AL22: 0 | AM22: 0 | AN22: 0 | AO22: 0 | AP22: 0 | AS22: បានប្រកាសពន្ធ
A23: 15 | C23: ប្យួរ៉ូ វេរីតាស (ខេមបូឌា) លីមីធីត | D23: L001-107024462 | E23: 59006449 | F23: 43843 | G23: 229673 | I23: 229673 | J23: =IF(AND(S23=TRUE, T23=TRUE, U23=TRUE), IF(W23<-0.05, "អនុញ្ញាត (អ្នកផ្គត់ផ្គង់ប្រកាសខ្វះ)", "បានប្រកាស (អនុញ្ញាត)"), IF(AND(S23=FALSE, T23=FALSE, U23=FALSE), "ព្យួរទុក (មិនមានទិន្នន័យ)", "ប្រកាសខុស (ព្យួរទុក)")) | N23: =IF(W23<0,AH23,I23) | O23: =I23-M23 | Q23: 59006449 | R23: 59006449 | S23: =Q23=R23 | T23: =AND(MONTH(F23)=MONTH(X23), YEAR(F23)=YEAR(X23)) | U23: =AND(AB23<>"", 'Company information'!D$4<>"", RIGHT(SUBSTITUTE(AB23,"-",""),9)=RIGHT(SUBSTITUTE('Company information'!D$4,"-",""),9)) | V23: =AH23-I23 | X23: 43843 | Y23: 59006449 | AA23: បុគ្គលជាប់អាករ | AB23: L001-901905215 | AC23: វីអ៊ីស៊ិន (ខេមបូឌា) អ៊ិនដាសស្ទ្រី ឯ.ក | AD23: 2526397 | AE23: 2296725 | AF23: 0 | AG23: 0 | AH23: 229672 | AI23: 0 | AJ23: 0 | AK23: 0 | AL23: 0 | AM23: 0 | AN23: 0 | AO23: 0 | AP23: 0 | AS23: បានប្រកាសពន្ធ
A24: 16 | C24: ប្យួរ៉ូ វេរីតាស (ខេមបូឌា) លីមីធីត | D24: L001-107024462 | E24: 59006446 | F24: 44105 | G24: 67073 | I24: 67073 | J24: =IF(AND(S24=TRUE, T24=TRUE, U24=TRUE), IF(W24<-0.05, "អនុញ្ញាត (អ្នកផ្គត់ផ្គង់ប្រកាសខ្វះ)", "បានប្រកាស (អនុញ្ញាត)"), IF(AND(S24=FALSE, T24=FALSE, U24=FALSE), "ព្យួរទុក (មិនមានទិន្នន័យ)", "ប្រកាសខុស (ព្យួរទុក)")) | N24: =IF(W24<0,AH24,I24) | O24: =I24-M24 | Q24: 59006446 | R24: 59006446 | S24: =Q24=R24 | T24: =AND(MONTH(F24)=MONTH(X24), YEAR(F24)=YEAR(X24)) | U24: =AND(AB24<>"", 'Company information'!D$4<>"", RIGHT(SUBSTITUTE(AB24,"-",""),9)=RIGHT(SUBSTITUTE('Company information'!D$4,"-",""),9)) | V24: =AH24-I24 | X24: 43840 | Y24: 59006446 | AA24: បុគ្គលជាប់អាករ | AB24: L001-901905215 | AC24: វីអ៊ីស៊ិន (ខេមបូឌា) អ៊ិនដាសស្ទ្រី ឯ.ក | AD24: 737797 | AE24: 670725 | AF24: 0 | AG24: 0 | AH24: 67072 | AI24: 0 | AJ24: 0 | AK24: 0 | AL24: 0 | AM24: 0 | AN24: 0 | AO24: 0 | AP24: 0 | AS24: បានប្រកាសពន្ធ
A25: 17 | C25: ប្យួរ៉ូ វេរីតាស (ខេមបូឌា) លីមីធីត | D25: L001-107024462 | E25: 59006444 | F25: 44105 | G25: 256095 | I25: 256095 | J25: =IF(AND(S25=TRUE, T25=TRUE, U25=TRUE), IF(W25<-0.05, "អនុញ្ញាត (អ្នកផ្គត់ផ្គង់ប្រកាសខ្វះ)", "បានប្រកាស (អនុញ្ញាត)"), IF(AND(S25=FALSE, T25=FALSE, U25=FALSE), "ព្យួរទុក (មិនមានទិន្នន័យ)", "ប្រកាសខុស (ព្យួរទុក)")) | N25: =IF(W25<0,AH25,I25) | O25: =I25-M25 | Q25: 59006444 | R25: 59006444 | S25: =Q25=R25 | T25: =AND(MONTH(F25)=MONTH(X25), YEAR(F25)=YEAR(X25)) | U25: =AND(AB25<>"", 'Company information'!D$4<>"", RIGHT(SUBSTITUTE(AB25,"-",""),9)=RIGHT(SUBSTITUTE('Company information'!D$4,"-",""),9)) | V25: =AH25-I25 | X25: 43840 | Y25: 59006444 | AA25: បុគ្គលជាប់អាករ | AB25: L001-901905215 | AC25: វីអ៊ីស៊ិន (ខេមបូឌា) អ៊ិនដាសស្ទ្រី ឯ.ក | AD25: 2817045 | AE25: 2560950 | AF25: 0 | AG25: 0 | AH25: 256095 | AI25: 0 | AJ25: 0 | AK25: 0 | AL25: 0 | AM25: 0 | AN25: 0 | AO25: 0 | AP25: 0 | AS25: បានប្រកាសពន្ធ
A26: 18 | C26: ប្យួរ៉ូ វេរីតាស (ខេមបូឌា) លីមីធីត | D26: L001-107024462 | E26: 59006440 | F26: 44105 | G26: 134145 | I26: 134145 | J26: =IF(AND(S26=TRUE, T26=TRUE, U26=TRUE), IF(W26<-0.05, "អនុញ្ញាត (អ្នកផ្គត់ផ្គង់ប្រកាសខ្វះ)", "បានប្រកាស (អនុញ្ញាត)"), IF(AND(S26=FALSE, T26=FALSE, U26=FALSE), "ព្យួរទុក (មិនមានទិន្នន័យ)", "ប្រកាសខុស (ព្យួរទុក)")) | N26: =IF(W26<0,AH26,I26) | O26: =I26-M26 | Q26: 59006440 | R26: 59006440 | S26: =Q26=R26 | T26: =AND(MONTH(F26)=MONTH(X26), YEAR(F26)=YEAR(X26)) | U26: =AND(AB26<>"", 'Company information'!D$4<>"", RIGHT(SUBSTITUTE(AB26,"-",""),9)=RIGHT(SUBSTITUTE('Company information'!D$4,"-",""),9)) | V26: =AH26-I26 | X26: 43840 | Y26: 59006440 | AA26: បុគ្គលជាប់អាករ | AB26: L001-901905215 | AC26: វីអ៊ីស៊ិន (ខេមបូឌា) អ៊ិនដាសស្ទ្រី ឯ.ក | AD26: 1475595 | AE26: 1341450 | AF26: 0 | AG26: 0 | AH26: 134145 | AI26: 0 | AJ26: 0 | AK26: 0 | AL26: 0 | AM26: 0 | AN26: 0 | AO26: 0 | AP26: 0 | AS26: បានប្រកាសពន្ធ
A27: 19 | C27: ប្យួរ៉ូ វេរីតាស (ខេមបូឌា) លីមីធីត | D27: L001-107024462 | E27: 59006403 | F27: 44044 | G27: 189023 | I27: 189023 | J27: =IF(AND(S27=TRUE, T27=TRUE, U27=TRUE), IF(W27<-0.05, "អនុញ្ញាត (អ្នកផ្គត់ផ្គង់ប្រកាសខ្វះ)", "បានប្រកាស (អនុញ្ញាត)"), IF(AND(S27=FALSE, T27=FALSE, U27=FALSE), "ព្យួរទុក (មិនមានទិន្នន័យ)", "ប្រកាសខុស (ព្យួរទុក)")) | N27: =IF(W27<0,AH27,I27) | O27: =I27-M27 | Q27: 59006403 | R27: 59006403 | S27: =Q27=R27 | T27: =AND(MONTH(F27)=MONTH(X27), YEAR(F27)=YEAR(X27)) | U27: =AND(AB27<>"", 'Company information'!D$4<>"", RIGHT(SUBSTITUTE(AB27,"-",""),9)=RIGHT(SUBSTITUTE('Company information'!D$4,"-",""),9)) | V27: =AH27-I27 | X27: 43838 | Y27: 59006403 | AA27: បុគ្គលជាប់អាករ | AB27: L001-901905215 | AC27: វីអ៊ីស៊ិន (ខេមបូឌា) អ៊ិនដាសស្ទ្រី ឯ.ក | AD27: 2079247 | AE27: 1890225 | AF27: 0 | AG27: 0 | AH27: 189022 | AI27: 0 | AJ27: 0 | AK27: 0 | AL27: 0 | AM27: 0 | AN27: 0 | AO27: 0 | AP27: 0 | AS27: បានប្រកាសពន្ធ
A28: 20 | C28: ប្យួរ៉ូ វេរីតាស (ខេមបូឌា) លីមីធីត | D28: L001-107024462 | E28: 59006359 | F28: 43983 | G28: 229673 | I28: 229673 | J28: =IF(AND(S28=TRUE, T28=TRUE, U28=TRUE), IF(W28<-0.05, "អនុញ្ញាត (អ្នកផ្គត់ផ្គង់ប្រកាសខ្វះ)", "បានប្រកាស (អនុញ្ញាត)"), IF(AND(S28=FALSE, T28=FALSE, U28=FALSE), "ព្យួរទុក (មិនមានទិន្នន័យ)", "ប្រកាសខុស (ព្យួរទុក)")) | N28: =IF(W28<0,AH28,I28) | O28: =I28-M28 | Q28: 59006359 | R28: 59006359 | S28: =Q28=R28 | T28: =AND(MONTH(F28)=MONTH(X28), YEAR(F28)=YEAR(X28)) | U28: =AND(AB28<>"", 'Company information'!D$4<>"", RIGHT(SUBSTITUTE(AB28,"-",""),9)=RIGHT(SUBSTITUTE('Company information'!D$4,"-",""),9)) | V28: =AH28-I28 | X28: 43836 | Y28: 59006359 | AA28: បុគ្គលជាប់អាករ | AB28: L001-901905215 | AC28: វីអ៊ីស៊ិន (ខេមបូឌា) អ៊ិនដាសស្ទ្រី ឯ.ក | AD28: 2526397 | AE28: 2296725 | AF28: 0 | AG28: 0 | AH28: 229672 | AI28: 0 | AJ28: 0 | AK28: 0 | AL28: 0 | AM28: 0 | AN28: 0 | AO28: 0 | AP28: 0 | AS28: បានប្រកាសពន្ធ
A29: 21 | C29: អ៊ិចស្ពែឌីធ័រ ខេមបូឌា អិលធីឌី | D29: L001-100045898 | E29: TI0169609 | F29: 43860 | G29: 145395 | I29: 145395 | J29: =IF(AND(S29=TRUE, T29=TRUE, U29=TRUE), IF(W29<-0.05, "អនុញ្ញាត (អ្នកផ្គត់ផ្គង់ប្រកាសខ្វះ)", "បានប្រកាស (អនុញ្ញាត)"), IF(AND(S29=FALSE, T29=FALSE, U29=FALSE), "ព្យួរទុក (មិនមានទិន្នន័យ)", "ប្រកាសខុស (ព្យួរទុក)")) | N29: =IF(W29<0,AH29,I29) | O29: =I29-M29 | Q29: TI0169609 | R29: TI-0169609 | S29: =Q29=R29 | T29: =AND(MONTH(F29)=MONTH(X29), YEAR(F29)=YEAR(X29)) | U29: =AND(AB29<>"", 'Company information'!D$4<>"", RIGHT(SUBSTITUTE(AB29,"-",""),9)=RIGHT(SUBSTITUTE('Company information'!D$4,"-",""),9)) | V29: =AH29-I29 | X29: 43860 | Y29: TI-0169609 | AA29: បុគ្គលជាប់អាករ | AB29: L001-901905215 | AC29: វីអ៊ីស៊ិន (ខេមបូឌា) អ៊ិនដាសស្ទ្រី ឯ.ក | AD29: 1599345 | AE29: 1453950 | AF29: 0 | AG29: 0 | AH29: 145395 | AI29: 0 | AJ29: 0 | AK29: 0 | AL29: 0 | AM29: 0 | AN29: 0 | AO29: 0 | AP29: 0 | AS29: បានប្រកាសពន្ធ
A30: 22 | C30: អ៊ិចស្ពែឌីធ័រ ខេមបូឌា អិលធីឌី | D30: L001-100045898 | E30: TI0169607 | F30: 43860 | G30: 145395 | I30: 145395 | J30: =IF(AND(S30=TRUE, T30=TRUE, U30=TRUE), IF(W30<-0.05, "អនុញ្ញាត (អ្នកផ្គត់ផ្គង់ប្រកាសខ្វះ)", "បានប្រកាស (អនុញ្ញាត)"), IF(AND(S30=FALSE, T30=FALSE, U30=FALSE), "ព្យួរទុក (មិនមានទិន្នន័យ)", "ប្រកាសខុស (ព្យួរទុក)")) | N30: =IF(W30<0,AH30,I30) | O30: =I30-M30 | Q30: TI0169607 | R30: TI-0169607 | S30: =Q30=R30 | T30: =AND(MONTH(F30)=MONTH(X30), YEAR(F30)=YEAR(X30)) | U30: =AND(AB30<>"", 'Company information'!D$4<>"", RIGHT(SUBSTITUTE(AB30,"-",""),9)=RIGHT(SUBSTITUTE('Company information'!D$4,"-",""),9)) | V30: =AH30-I30 | X30: 43860 | Y30: TI-0169607 | AA30: បុគ្គលជាប់អាករ | AB30: L001-901905215 | AC30: វីអ៊ីស៊ិន (ខេមបូឌា) អ៊ិនដាសស្ទ្រី ឯ.ក | AD30: 1599345 | AE30: 1453950 | AF30: 0 | AG30: 0 | AH30: 145395 | AI30: 0 | AJ30: 0 | AK30: 0 | AL30: 0 | AM30: 0 | AN30: 0 | AO30: 0 | AP30: 0 | AS30: បានប្រកាសពន្ធ
A31: 23 | C31: អ៊ិចស្ពែឌីធ័រ ខេមបូឌា អិលធីឌី | D31: L001-100045898 | E31: TI0169605 | F31: 43860 | G31: 145395 | I31: 145395 | J31: =IF(AND(S31=TRUE, T31=TRUE, U31=TRUE), IF(W31<-0.05, "អនុញ្ញាត (អ្នកផ្គត់ផ្គង់ប្រកាសខ្វះ)", "បានប្រកាស (អនុញ្ញាត)"), IF(AND(S31=FALSE, T31=FALSE, U31=FALSE), "ព្យួរទុក (មិនមានទិន្នន័យ)", "ប្រកាសខុស (ព្យួរទុក)")) | N31: =IF(W31<0,AH31,I31) | O31: =I31-M31 | Q31: TI0169605 | R31: TI-0169605 | S31: =Q31=R31 | T31: =AND(MONTH(F31)=MONTH(X31), YEAR(F31)=YEAR(X31)) | U31: =AND(AB31<>"", 'Company information'!D$4<>"", RIGHT(SUBSTITUTE(AB31,"-",""),9)=RIGHT(SUBSTITUTE('Company information'!D$4,"-",""),9)) | V31: =AH31-I31 | X31: 43860 | Y31: TI-0169605 | AA31: បុគ្គលជាប់អាករ | AB31: L001-901905215 | AC31: វីអ៊ីស៊ិន (ខេមបូឌា) អ៊ិនដាសស្ទ្រី ឯ.ក | AD31: 1599345 | AE31: 1453950 | AF31: 0 | AG31: 0 | AH31: 145395 | AI31: 0 | AJ31: 0 | AK31: 0 | AL31: 0 | AM31: 0 | AN31: 0 | AO31: 0 | AP31: 0 | AS31: បានប្រកាសពន្ធ
A32: 24 | C32: អ៊ិចស្ពែឌីធ័រ ខេមបូឌា អិលធីឌី | D32: L001-100045898 | E32: TI0168468 | F32: 43847 | G32: 52366 | I32: 52366 | J32: =IF(AND(S32=TRUE, T32=TRUE, U32=TRUE), IF(W32<-0.05, "អនុញ្ញាត (អ្នកផ្គត់ផ្គង់ប្រកាសខ្វះ)", "បានប្រកាស (អនុញ្ញាត)"), IF(AND(S32=FALSE, T32=FALSE, U32=FALSE), "ព្យួរទុក (មិនមានទិន្នន័យ)", "ប្រកាសខុស (ព្យួរទុក)")) | N32: =IF(W32<0,AH32,I32) | O32: =I32-M32 | Q32: TI0168468 | R32: TI-0168468 | S32: =Q32=R32 | T32: =AND(MONTH(F32)=MONTH(X32), YEAR(F32)=YEAR(X32)) | U32: =AND(AB32<>"", 'Company information'!D$4<>"", RIGHT(SUBSTITUTE(AB32,"-",""),9)=RIGHT(SUBSTITUTE('Company information'!D$4,"-",""),9)) | V32: =AH32-I32 | X32: 43847 | Y32: TI-0168468 | AA32: បុគ្គលជាប់អាករ | AB32: L001-901905215 | AC32: វីអ៊ីស៊ិន (ខេមបូឌា) អ៊ិនដាសស្ទ្រី ឯ.ក | AD32: 576743 | AE32: 524312 | AF32: 0 | AG32: 0 | AH32: 52431 | AI32: 0 | AJ32: 0 | AK32: 0 | AL32: 0 | AM32: 0 | AN32: 0 | AO32: 0 | AP32: 0 | AS32: បានប្រកាសពន្ធ
A33: 25 | C33: អ៊ិចស្ពែឌីធ័រ ខេមបូឌា អិលធីឌី | D33: L001-100045898 | E33: TI0168455 | F33: 43847 | G33: 48460 | I33: 48460 | J33: =IF(AND(S33=TRUE, T33=TRUE, U33=TRUE), IF(W33<-0.05, "អនុញ្ញាត (អ្នកផ្គត់ផ្គង់ប្រកាសខ្វះ)", "បានប្រកាស (អនុញ្ញាត)"), IF(AND(S33=FALSE, T33=FALSE, U33=FALSE), "ព្យួរទុក (មិនមានទិន្នន័យ)", "ប្រកាសខុស (ព្យួរទុក)")) | N33: =IF(W33<0,AH33,I33) | O33: =I33-M33 | Q33: TI0168455 | R33: TI-0168455 | S33: =Q33=R33 | T33: =AND(MONTH(F33)=MONTH(X33), YEAR(F33)=YEAR(X33)) | U33: =AND(AB33<>"", 'Company information'!D$4<>"", RIGHT(SUBSTITUTE(AB33,"-",""),9)=RIGHT(SUBSTITUTE('Company information'!D$4,"-",""),9)) | V33: =AH33-I33 | X33: 43847 | Y33: TI-0168455 | AA33: បុគ្គលជាប់អាករ | AB33: L001-901905215 | AC33: វីអ៊ីស៊ិន (ខេមបូឌា) អ៊ិនដាសស្ទ្រី ឯ.ក | AD33: 533922 | AE33: 485384 | AF33: 0 | AG33: 0 | AH33: 48538 | AI33: 0 | AJ33: 0 | AK33: 0 | AL33: 0 | AM33: 0 | AN33: 0 | AO33: 0 | AP33: 0 | AS33: បានប្រកាសពន្ធ
A34: 26 | C34: អ៊ិចស្ពែឌីធ័រ ខេមបូឌា អិលធីឌី | D34: L001-100045898 | E34: TI0168454 | F34: 43847 | G34: 51052 | I34: 51052 | J34: =IF(AND(S34=TRUE, T34=TRUE, U34=TRUE), IF(W34<-0.05, "អនុញ្ញាត (អ្នកផ្គត់ផ្គង់ប្រកាសខ្វះ)", "បានប្រកាស (អនុញ្ញាត)"), IF(AND(S34=FALSE, T34=FALSE, U34=FALSE), "ព្យួរទុក (មិនមានទិន្នន័យ)", "ប្រកាសខុស (ព្យួរទុក)")) | N34: =IF(W34<0,AH34,I34) | O34: =I34-M34 | Q34: TI0168454 | R34: TI-0168454 | S34: =Q34=R34 | T34: =AND(MONTH(F34)=MONTH(X34), YEAR(F34)=YEAR(X34)) | U34: =AND(AB34<>"", 'Company information'!D$4<>"", RIGHT(SUBSTITUTE(AB34,"-",""),9)=RIGHT(SUBSTITUTE('Company information'!D$4,"-",""),9)) | V34: =AH34-I34 | X34: 43847 | Y34: TI-0168454 | AA34: បុគ្គលជាប់អាករ | AB34: L001-901905215 | AC34: វីអ៊ីស៊ិន (ខេមបូឌា) អ៊ិនដាសស្ទ្រី ឯ.ក | AD34: 562469 | AE34: 511335 | AF34: 0 | AG34: 0 | AH34: 51134 | AI34: 0 | AJ34: 0 | AK34: 0 | AL34: 0 | AM34: 0 | AN34: 0 | AO34: 0 | AP34: 0 | AS34: បានប្រកាសពន្ធ
... A39: 31 | C39: អ៊ិចស្ពែឌីធ័រ ខេមបូឌា អិលធីឌី | D39: L001-100045898 | E39: TI0168448 | F39: 43847 | G39: 52366 | I39: 52366 | J39: =IF(AND(S39=TRUE, T39=TRUE, U39=TRUE), IF(W39<-0.05, "អនុញ្ញាត (អ្នកផ្គត់ផ្គង់ប្រកាសខ្វះ)", "បានប្រកាស (អនុញ្ញាត)"), IF(AND(S39=FALSE, T39=FALSE, U39=FALSE), "ព្យួរទុក (មិនមានទិន្នន័យ)", "ប្រកាសខុស (ព្យួរទុក)")) | N39: =IF(W39<0,AH39,I39) | O39: =I39-M39 | Q39: TI0168448 | R39: TI-0168448 | S39: =Q39=R39 | T39: =AND(MONTH(F39)=MONTH(X39), YEAR(F39)=YEAR(X39)) | U39: =AND(AB39<>"", 'Company information'!D$4<>"", RIGHT(SUBSTITUTE(AB39,"-",""),9)=RIGHT(SUBSTITUTE('Company information'!D$4,"-",""),9)) | V39: =AH39-I39 | X39: 43847 | Y39: TI-0168448 | AA39: បុគ្គលជាប់អាករ | AB39: L001-901905215 | AC39: វីអ៊ីស៊ិន (ខេមបូឌា) អ៊ិនដាសស្ទ្រី ឯ.ក | AD39: 576743 | AE39: 524312 | AF39: 0 | AG39: 0 | AH39: 52431 | AI39: 0 | AJ39: 0 | AK39: 0 | AL39: 0 | AM39: 0 | AN39: 0 | AO39: 0 | AP39: 0 | AS39: បានប្រកាសពន្ធ
A40: 32 | C40: កំពង់ផែស្វយ័តក្រុងព្រះសីហនុ | D40: L001-100044638 | E40: 008584 | F40: 43845 | G40: 7290 | I40: 7290 | J40: =IF(AND(S40=TRUE, T40=TRUE, U40=TRUE), IF(W40<-0.05, "អនុញ្ញាត (អ្នកផ្គត់ផ្គង់ប្រកាសខ្វះ)", "បានប្រកាស (អនុញ្ញាត)"), IF(AND(S40=FALSE, T40=FALSE, U40=FALSE), "ព្យួរទុក (មិនមានទិន្នន័យ)", "ប្រកាសខុស (ព្យួរទុក)")) | N40: =IF(W40<0,AH40,I40) | O40: =I40-M40 | Q40: 008584 | S40: =Q40=R40 | T40: =AND(MONTH(F40)=MONTH(X40), YEAR(F40)=YEAR(X40)) | U40: =AND(AB40<>"", 'Company information'!D$4<>"", RIGHT(SUBSTITUTE(AB40,"-",""),9)=RIGHT(SUBSTITUTE('Company information'!D$4,"-",""),9)) | V40: =AH40-I40
A41: 33 | C41: កំពង់ផែស្វយ័តក្រុងព្រះសីហនុ | D41: L001-100044638 | E41: 007430 | F41: 43843 | G41: 64395 | I41: 64395 | J41: =IF(AND(S41=TRUE, T41=TRUE, U41=TRUE), IF(W41<-0.05, "អនុញ្ញាត (អ្នកផ្គត់ផ្គង់ប្រកាសខ្វះ)", "បានប្រកាស (អនុញ្ញាត)"), IF(AND(S41=FALSE, T41=FALSE, U41=FALSE), "ព្យួរទុក (មិនមានទិន្នន័យ)", "ប្រកាសខុស (ព្យួរទុក)")) | N41: =IF(W41<0,AH41,I41) | O41: =I41-M41 | Q41: 007430 | S41: =Q41=R41 | T41: =AND(MONTH(F41)=MONTH(X41), YEAR(F41)=YEAR(X41)) | U41: =AND(AB41<>"", 'Company information'!D$4<>"", RIGHT(SUBSTITUTE(AB41,"-",""),9)=RIGHT(SUBSTITUTE('Company information'!D$4,"-",""),9)) | V41: =AH41-I41
A42: 34 | C42: កំពង់ផែស្វយ័តក្រុងព្រះសីហនុ | D42: L001-100044638 | E42: 006642 | F42: 44136 | G42: 23085 | I42: 23085 | J42: =IF(AND(S42=TRUE, T42=TRUE, U42=TRUE), IF(W42<-0.05, "អនុញ្ញាត (អ្នកផ្គត់ផ្គង់ប្រកាសខ្វះ)", "បានប្រកាស (អនុញ្ញាត)"), IF(AND(S42=FALSE, T42=FALSE, U42=FALSE), "ព្យួរទុក (មិនមានទិន្នន័យ)", "ប្រកាសខុស (ព្យួរទុក)")) | N42: =IF(W42<0,AH42,I42) | O42: =I42-M42 | Q42: 006642 | S42: =Q42=R42 | T42: =AND(MONTH(F42)=MONTH(X42), YEAR(F42)=YEAR(X42)) | U42: =AND(AB42<>"", 'Company information'!D$4<>"", RIGHT(SUBSTITUTE(AB42,"-",""),9)=RIGHT(SUBSTITUTE('Company information'!D$4,"-",""),9)) | V42: =AH42-I42
A43: 35 | C43: អឹមេហ្ស៊ីង ឡូជីស្ទីក & សឹបផ្លាយ ឆេន (ខេមបូឌា) ឯ.ក | D43: K009-901703255 | E43: 200116 | F43: 43852 | G43: 540645 | I43: 540645 | J43: =IF(AND(S43=TRUE, T43=TRUE, U43=TRUE), IF(W43<-0.05, "អនុញ្ញាត (អ្នកផ្គត់ផ្គង់ប្រកាសខ្វះ)", "បានប្រកាស (អនុញ្ញាត)"), IF(AND(S43=FALSE, T43=FALSE, U43=FALSE), "ព្យួរទុក (មិនមានទិន្នន័យ)", "ប្រកាសខុស (ព្យួរទុក)")) | N43: =IF(W43<0,AH43,I43) | O43: =I43-M43 | Q43: 200116 | R43: 200116 | S43: =Q43=R43 | T43: =AND(MONTH(F43)=MONTH(X43), YEAR(F43)=YEAR(X43)) | U43: =AND(AB43<>"", 'Company information'!D$4<>"", RIGHT(SUBSTITUTE(AB43,"-",""),9)=RIGHT(SUBSTITUTE('Company information'!D$4,"-",""),9)) | V43: =AH43-I43 | X43: 43852 | Y43: 200116 | AA43: បុគ្គលជាប់អាករ | AB43: L001-901905215 | AC43: វីអ៊ីស៊ិន (ខេមបូឌា) អ៊ិនដាសស្ទ្រី ឯ.ក | AD43: 5947095 | AE43: 5406450 | AF43: 0 | AG43: 0 | AH43: 540645 | AI43: 0 | AJ43: 0 | AK43: 0 | AL43: 0 | AM43: 0 | AN43: 0 | AO43: 0 | AP43: 0 | AS43: បានប្រកាសពន្ធ
A44: 36 | C44: វ៉ាយ.ស៊ី ផេកខេជីង ឯ.ក | D44: L001-901700417 | E44: TI0008 | F44: 43851 | G44: 11694624 | I44: 11694624 | J44: =IF(AND(S44=TRUE, T44=TRUE, U44=TRUE), IF(W44<-0.05, "អនុញ្ញាត (អ្នកផ្គត់ផ្គង់ប្រកាសខ្វះ)", "បានប្រកាស (អនុញ្ញាត)"), IF(AND(S44=FALSE, T44=FALSE, U44=FALSE), "ព្យួរទុក (មិនមានទិន្នន័យ)", "ប្រកាសខុស (ព្យួរទុក)")) | N44: =IF(W44<0,AH44,I44) | O44: =I44-M44 | Q44: TI0008 | R44: TI0008 | S44: =Q44=R44 | T44: =AND(MONTH(F44)=MONTH(X44), YEAR(F44)=YEAR(X44)) | U44: =AND(AB44<>"", 'Company information'!D$4<>"", RIGHT(SUBSTITUTE(AB44,"-",""),9)=RIGHT(SUBSTITUTE('Company information'!D$4,"-",""),9)) | V44: =AH44-I44 | X44: 43851 | Y44: TI0008 | AA44: បុគ្គលជាប់អាករ | AB44: L001-901905215 | AC44: វីអ៊ីស៊ិន (ខេមបូឌា) អ៊ិនដាសស្ទ្រី ឯ.ក | AD44: 128166162 | AE44: 116514693 | AF44: 0 | AG44: 0 | AH44: 11651469 | AI44: 0 | AJ44: 0 | AK44: 0 | AL44: 0 | AM44: 0 | AN44: 0 | AO44: 0 | AP44: 0 | AS44: បានប្រកាសពន្ធ
A45: 37 | C45: វី សូ ខូ អិលធីឌី | D45: K006-901500578 | E45: TI000038 | F45: 43844 | G45: 264225 | I45: 264225 | J45: =IF(AND(S45=TRUE, T45=TRUE, U45=TRUE), IF(W45<-0.05, "អនុញ្ញាត (អ្នកផ្គត់ផ្គង់ប្រកាសខ្វះ)", "បានប្រកាស (អនុញ្ញាត)"), IF(AND(S45=FALSE, T45=FALSE, U45=FALSE), "ព្យួរទុក (មិនមានទិន្នន័យ)", "ប្រកាសខុស (ព្យួរទុក)")) | N45: =IF(W45<0,AH45,I45) | O45: =I45-M45 | Q45: TI000038 | R45: TI000038 | S45: =Q45=R45 | T45: =AND(MONTH(F45)=MONTH(X45), YEAR(F45)=YEAR(X45)) | U45: =AND(AB45<>"", 'Company information'!D$4<>"", RIGHT(SUBSTITUTE(AB45,"-",""),9)=RIGHT(SUBSTITUTE('Company information'!D$4,"-",""),9)) | V45: =AH45-I45 | X45: 43844 | Y45: TI000038 | AA45: បុគ្គលជាប់អាករ | AB45: L001-901905215 | AC45: វីអ៊ីស៊ិន (ខេមបូឌា) អ៊ិនដាសស្ទ្រី ឯ.ក | AD45: 2906475 | AE45: 2642250 | AF45: 0 | AG45: 0 | AH45: 264225 | AI45: 0 | AJ45: 0 | AK45: 0 | AL45: 0 | AM45: 0 | AN45: 0 | AO45: 0 | AP45: 0 | AS45: បានប្រកាសពន្ធ
A46: 38 | C46: សូស៊ីយេតេ កុងសេស្យូនែរ ដឺ ឡាអេរ៉ូព័រ | D46: L001-100047300 | E46: 2000005566 | F46: 43851 | G46: 27312 | I46: 27312 | J46: =IF(AND(S46=TRUE, T46=TRUE, U46=TRUE), IF(W46<-0.05, "អនុញ្ញាត (អ្នកផ្គត់ផ្គង់ប្រកាសខ្វះ)", "បានប្រកាស (អនុញ្ញាត)"), IF(AND(S46=FALSE, T46=FALSE, U46=FALSE), "ព្យួរទុក (មិនមានទិន្នន័យ)", "ប្រកាសខុស (ព្យួរទុក)")) | N46: =IF(W46<0,AH46,I46) | O46: =I46-M46 | Q46: 2000005566 | S46: =Q46=R46 | T46: =AND(MONTH(F46)=MONTH(X46), YEAR(F46)=YEAR(X46)) | U46: =AND(AB46<>"", 'Company information'!D$4<>"", RIGHT(SUBSTITUTE(AB46,"-",""),9)=RIGHT(SUBSTITUTE('Company information'!D$4,"-",""),9)) | V46: =AH46-I46
A47: 39 | C47: សូស៊ីយេតេ កុងសេស្យូនែរ ដឺ ឡាអេរ៉ូព័រ | D47: L001-100047300 | E47: 2000004264 | F47: 43846 | G47: 29878 | I47: 29878 | J47: =IF(AND(S47=TRUE, T47=TRUE, U47=TRUE), IF(W47<-0.05, "អនុញ្ញាត (អ្នកផ្គត់ផ្គង់ប្រកាសខ្វះ)", "បានប្រកាស (អនុញ្ញាត)"), IF(AND(S47=FALSE, T47=FALSE, U47=FALSE), "ព្យួរទុក (មិនមានទិន្នន័យ)", "ប្រកាសខុស (ព្យួរទុក)")) | N47: =IF(W47<0,AH47,I47) | O47: =I47-M47 | Q47: 2000004264 | S47: =Q47=R47 | T47: =AND(MONTH(F47)=MONTH(X47), YEAR(F47)=YEAR(X47)) | U47: =AND(AB47<>"", 'Company information'!D$4<>"", RIGHT(SUBSTITUTE(AB47,"-",""),9)=RIGHT(SUBSTITUTE('Company information'!D$4,"-",""),9)) | V47: =AH47-I47
A48: 40 | C48: សូស៊ីយេតេ កុងសេស្យូនែរ ដឺ ឡាអេរ៉ូព័រ | D48: L001-100047300 | E48: 2000003336 | F48: 43844 | G48: 34989 | I48: 34989 | J48: =IF(AND(S48=TRUE, T48=TRUE, U48=TRUE), IF(W48<-0.05, "អនុញ្ញាត (អ្នកផ្គត់ផ្គង់ប្រកាសខ្វះ)", "បានប្រកាស (អនុញ្ញាត)"), IF(AND(S48=FALSE, T48=FALSE, U48=FALSE), "ព្យួរទុក (មិនមានទិន្នន័យ)", "ប្រកាសខុស (ព្យួរទុក)")) | N48: =IF(W48<0,AH48,I48) | O48: =I48-M48 | Q48: 2000003336 | S48: =Q48=R48 | T48: =AND(MONTH(F48)=MONTH(X48), YEAR(F48)=YEAR(X48)) | U48: =AND(AB48<>"", 'Company information'!D$4<>"", RIGHT(SUBSTITUTE(AB48,"-",""),9)=RIGHT(SUBSTITUTE('Company information'!D$4,"-",""),9)) | V48: =AH48-I48
A49: 41 | C49: សូស៊ីយេតេ កុងសេស្យូនែរ ដឺ ឡាអេរ៉ូព័រ | D49: L001-100047300 | E49: 2000002791 | F49: 44136 | G49: 7130 | I49: 7130 | J49: =IF(AND(S49=TRUE, T49=TRUE, U49=TRUE), IF(W49<-0.05, "អនុញ្ញាត (អ្នកផ្គត់ផ្គង់ប្រកាសខ្វះ)", "បានប្រកាស (អនុញ្ញាត)"), IF(AND(S49=FALSE, T49=FALSE, U49=FALSE), "ព្យួរទុក (មិនមានទិន្នន័យ)", "ប្រកាសខុស (ព្យួរទុក)")) | N49: =IF(W49<0,AH49,I49) | O49: =I49-M49 | Q49: 2000002791 | S49: =Q49=R49 | T49: =AND(MONTH(F49)=MONTH(X49), YEAR(F49)=YEAR(X49)) | U49: =AND(AB49<>"", 'Company information'!D$4<>"", RIGHT(SUBSTITUTE(AB49,"-",""),9)=RIGHT(SUBSTITUTE('Company information'!D$4,"-",""),9)) | V49: =AH49-I49
A50: 42 | C50: ស្ត្រេតស៍ អ៊ិនធើណេសិនណល ភីធីអ៊ី អិលធីឌី | D50: L001-100045162 | E50: 2000649 | F50: 44044 | G50: 83333 | I50: 83333 | J50: =IF(AND(S50=TRUE, T50=TRUE, U50=TRUE), IF(W50<-0.05, "អនុញ្ញាត (អ្នកផ្គត់ផ្គង់ប្រកាសខ្វះ)", "បានប្រកាស (អនុញ្ញាត)"), IF(AND(S50=FALSE, T50=FALSE, U50=FALSE), "ព្យួរទុក (មិនមានទិន្នន័យ)", "ប្រកាសខុស (ព្យួរទុក)")) | N50: =IF(W50<0,AH50,I50) | O50: =I50-M50 | Q50: 2000649 | R50: 2000649 | S50: =Q50=R50 | T50: =AND(MONTH(F50)=MONTH(X50), YEAR(F50)=YEAR(X50)) | U50: =AND(AB50<>"", 'Company information'!D$4<>"", RIGHT(SUBSTITUTE(AB50,"-",""),9)=RIGHT(SUBSTITUTE('Company information'!D$4,"-",""),9)) | V50: =AH50-I50 | X50: 43838 | Y50: 2000649 | AA50: បុគ្គលជាប់អាករ | AB50: L001-901905215 | AC50: វីអ៊ីស៊ិន (ខេមបូឌា) អ៊ិនដាសស្ទ្រី ឯ.ក | AD50: 913275 | AE50: 830250 | AF50: 0 | AG50: 0 | AH50: 83025 | AI50: 0 | AJ50: 0 | AK50: 0 | AL50: 0 | AM50: 0 | AN50: 0 | AO50: 0 | AP50: 0 | AS50: បានប្រកាសពន្ធ
A51: 43 | C51: ស្ត្រេតស៍ អ៊ិនធើណេសិនណល ភីធីអ៊ី អិលធីឌី | D51: L001-100045162 | E51: 2000128 | F51: 43831 | G51: 111788 | I51: 111788 | J51: =IF(AND(S51=TRUE, T51=TRUE, U51=TRUE), IF(W51<-0.05, "អនុញ្ញាត (អ្នកផ្គត់ផ្គង់ប្រកាសខ្វះ)", "បានប្រកាស (អនុញ្ញាត)"), IF(AND(S51=FALSE, T51=FALSE, U51=FALSE), "ព្យួរទុក (មិនមានទិន្នន័យ)", "ប្រកាសខុស (ព្យួរទុក)")) | N51: =IF(W51<0,AH51,I51) | O51: =I51-M51 | Q51: 2000128 | R51: 2000128 | S51: =Q51=R51 | T51: =AND(MONTH(F51)=MONTH(X51), YEAR(F51)=YEAR(X51)) | U51: =AND(AB51<>"", 'Company information'!D$4<>"", RIGHT(SUBSTITUTE(AB51,"-",""),9)=RIGHT(SUBSTITUTE('Company information'!D$4,"-",""),9)) | V51: =AH51-I51 | X51: 43831 | Y51: 2000128 | AA51: បុគ្គលជាប់អាករ | AB51: L001-901905215 | AC51: វីអ៊ីស៊ិន (ខេមបូឌា) អ៊ិនដាសស្ទ្រី ឯ.ក | AD51: 1225125 | AE51: 1113750 | AF51: 0 | AG51: 0 | AH51: 111375 | AI51: 0 | AJ51: 0 | AK51: 0 | AL51: 0 | AM51: 0 | AN51: 0 | AO51: 0 | AP51: 0 | AS51: បានប្រកាសពន្ធ
A52: 44 | C52: ខេមវីល គ្លូប៊ល ឯ.ក | D52: L001-901637190 | E52: INV200149 | F52: 43861 | G52: 138210 | I52: 138210 | J52: =IF(AND(S52=TRUE, T52=TRUE, U52=TRUE), IF(W52<-0.05, "អនុញ្ញាត (អ្នកផ្គត់ផ្គង់ប្រកាសខ្វះ)", "បានប្រកាស (អនុញ្ញាត)"), IF(AND(S52=FALSE, T52=FALSE, U52=FALSE), "ព្យួរទុក (មិនមានទិន្នន័យ)", "ប្រកាសខុស (ព្យួរទុក)")) | N52: =IF(W52<0,AH52,I52) | O52: =I52-M52 | Q52: INV200149 | R52: INV200149 | S52: =Q52=R52 | T52: =AND(MONTH(F52)=MONTH(X52), YEAR(F52)=YEAR(X52)) | U52: =AND(AB52<>"", 'Company information'!D$4<>"", RIGHT(SUBSTITUTE(AB52,"-",""),9)=RIGHT(SUBSTITUTE('Company information'!D$4,"-",""),9)) | V52: =AH52-I52 | X52: 43861 | Y52: INV200149 | AA52: បុគ្គលជាប់អាករ | AB52: L001-901905215 | AC52: វីអ៊ីស៊ិន (ខេមបូឌា) អ៊ិនដាសស្ទ្រី ឯ.ក | AD52: 1514700 | AE52: 1377000 | AF52: 0 | AG52: 0 | AH52: 137700 | AI52: 0 | AJ52: 0 | AK52: 0 | AL52: 0 | AM52: 0 | AN52: 0 | AO52: 0 | AP52: 0 | AS52: បានប្រកាសពន្ធ
A53: 45 | C53: ខេមវីល គ្លូប៊ល ឯ.ក | D53: L001-901637190 | E53: INV200148 | F53: 43861 | G53: 105690 | I53: 105690 | J53: =IF(AND(S53=TRUE, T53=TRUE, U53=TRUE), IF(W53<-0.05, "អនុញ្ញាត (អ្នកផ្គត់ផ្គង់ប្រកាសខ្វះ)", "បានប្រកាស (អនុញ្ញាត)"), IF(AND(S53=FALSE, T53=FALSE, U53=FALSE), "ព្យួរទុក (មិនមានទិន្នន័យ)", "ប្រកាសខុស (ព្យួរទុក)")) | N53: =IF(W53<0,AH53,I53) | O53: =I53-M53 | Q53: INV200148 | R53: INV200148 | S53: =Q53=R53 | T53: =AND(MONTH(F53)=MONTH(X53), YEAR(F53)=YEAR(X53)) | U53: =AND(AB53<>"", 'Company information'!D$4<>"", RIGHT(SUBSTITUTE(AB53,"-",""),9)=RIGHT(SUBSTITUTE('Company information'!D$4,"-",""),9)) | V53: =AH53-I53 | X53: 43861 | Y53: INV200148 | AA53: បុគ្គលជាប់អាករ | AB53: L001-901905215 | AC53: វីអ៊ីស៊ិន (ខេមបូឌា) អ៊ិនដាសស្ទ្រី ឯ.ក | AD53: 1158300 | AE53: 1053000 | AF53: 0 | AG53: 0 | AH53: 105300 | AI53: 0 | AJ53: 0 | AK53: 0 | AL53: 0 | AM53: 0 | AN53: 0 | AO53: 0 | AP53: 0 | AS53: បានប្រកាសពន្ធ
A54: 46 | C54: ខេមវីល គ្លូប៊ល ឯ.ក | D54: L001-901637190 | E54: INV200126 | F54: 43859 | G54: 166665 | I54: 166665 | J54: =IF(AND(S54=TRUE, T54=TRUE, U54=TRUE), IF(W54<-0.05, "អនុញ្ញាត (អ្នកផ្គត់ផ្គង់ប្រកាសខ្វះ)", "បានប្រកាស (អនុញ្ញាត)"), IF(AND(S54=FALSE, T54=FALSE, U54=FALSE), "ព្យួរទុក (មិនមានទិន្នន័យ)", "ប្រកាសខុស (ព្យួរទុក)")) | N54: =IF(W54<0,AH54,I54) | O54: =I54-M54 | Q54: INV200126 | R54: INV200126 | S54: =Q54=R54 | T54: =AND(MONTH(F54)=MONTH(X54), YEAR(F54)=YEAR(X54)) | U54: =AND(AB54<>"", 'Company information'!D$4<>"", RIGHT(SUBSTITUTE(AB54,"-",""),9)=RIGHT(SUBSTITUTE('Company information'!D$4,"-",""),9)) | V54: =AH54-I54 | X54: 43858 | Y54: INV200126 | AA54: បុគ្គលជាប់អាករ | AB54: L001-901905215 | AC54: វីអ៊ីស៊ិន (ខេមបូឌា) អ៊ិនដាសស្ទ្រី ឯ.ក | AD54: 1826550 | AE54: 1660500 | AF54: 0 | AG54: 0 | AH54: 166050 | AI54: 0 | AJ54: 0 | AK54: 0 | AL54: 0 | AM54: 0 | AN54: 0 | AO54: 0 | AP54: 0 | AS54: បានប្រកាសពន្ធ
A55: 47 | C55: ខេមវីល គ្លូប៊ល ឯ.ក | D55: L001-901637190 | E55: INV200125 | F55: 43859 | G55: 235770 | I55: 235770 | J55: =IF(AND(S55=TRUE, T55=TRUE, U55=TRUE), IF(W55<-0.05, "អនុញ្ញាត (អ្នកផ្គត់ផ្គង់ប្រកាសខ្វះ)", "បានប្រកាស (អនុញ្ញាត)"), IF(AND(S55=FALSE, T55=FALSE, U55=FALSE), "ព្យួរទុក (មិនមានទិន្នន័យ)", "ប្រកាសខុស (ព្យួរទុក)")) | N55: =IF(W55<0,AH55,I55) | O55: =I55-M55 | Q55: INV200125 | R55: INV200125 | S55: =Q55=R55 | T55: =AND(MONTH(F55)=MONTH(X55), YEAR(F55)=YEAR(X55)) | U55: =AND(AB55<>"", 'Company information'!D$4<>"", RIGHT(SUBSTITUTE(AB55,"-",""),9)=RIGHT(SUBSTITUTE('Company information'!D$4,"-",""),9)) | V55: =AH55-I55 | X55: 43858 | Y55: INV200125 | AA55: បុគ្គលជាប់អាករ | AB55: L001-901905215 | AC55: វីអ៊ីស៊ិន (ខេមបូឌា) អ៊ិនដាសស្ទ្រី ឯ.ក | AD55: 2583900 | AE55: 2349000 | AF55: 0 | AG55: 0 | AH55: 234900 | AI55: 0 | AJ55: 0 | AK55: 0 | AL55: 0 | AM55: 0 | AN55: 0 | AO55: 0 | AP55: 0 | AS55: បានប្រកាសពន្ធ
A56: 48 | C56: ខេមវីល គ្លូប៊ល ឯ.ក | D56: L001-901637190 | E56: INV200124 | F56: 43859 | G56: 235770 | I56: 235770 | J56: =IF(AND(S56=TRUE, T56=TRUE, U56=TRUE), IF(W56<-0.05, "អនុញ្ញាត (អ្នកផ្គត់ផ្គង់ប្រកាសខ្វះ)", "បានប្រកាស (អនុញ្ញាត)"), IF(AND(S56=FALSE, T56=FALSE, U56=FALSE), "ព្យួរទុក (មិនមានទិន្នន័យ)", "ប្រកាសខុស (ព្យួរទុក)")) | N56: =IF(W56<0,AH56,I56) | O56: =I56-M56 | Q56: INV200124 | R56: INV200124 | S56: =Q56=R56 | T56: =AND(MONTH(F56)=MONTH(X56), YEAR(F56)=YEAR(X56)) | U56: =AND(AB56<>"", 'Company information'!D$4<>"", RIGHT(SUBSTITUTE(AB56,"-",""),9)=RIGHT(SUBSTITUTE('Company information'!D$4,"-",""),9)) | V56: =AH56-I56 | X56: 43858 | Y56: INV200124 | AA56: បុគ្គលជាប់អាករ | AB56: L001-901905215 | AC56: វីអ៊ីស៊ិន (ខេមបូឌា) អ៊ិនដាសស្ទ្រី ឯ.ក | AD56: 2583900 | AE56: 2349000 | AF56: 0 | AG56: 0 | AH56: 234900 | AI56: 0 | AJ56: 0 | AK56: 0 | AL56: 0 | AM56: 0 | AN56: 0 | AO56: 0 | AP56: 0 | AS56: បានប្រកាសពន្ធ
A57: 49 | C57: ខេមវីល គ្លូប៊ល ឯ.ក | D57: L001-901637190 | E57: INV200123 | F57: 43859 | G57: 235770 | I57: 235770 | J57: =IF(AND(S57=TRUE, T57=TRUE, U57=TRUE), IF(W57<-0.05, "អនុញ្ញាត (អ្នកផ្គត់ផ្គង់ប្រកាសខ្វះ)", "បានប្រកាស (អនុញ្ញាត)"), IF(AND(S57=FALSE, T57=FALSE, U57=FALSE), "ព្យួរទុក (មិនមានទិន្នន័យ)", "ប្រកាសខុស (ព្យួរទុក)")) | N57: =IF(W57<0,AH57,I57) | O57: =I57-M57 | Q57: INV200123 | R57: INV200123 | S57: =Q57=R57 | T57: =AND(MONTH(F57)=MONTH(X57), YEAR(F57)=YEAR(X57)) | U57: =AND(AB57<>"", 'Company information'!D$4<>"", RIGHT(SUBSTITUTE(AB57,"-",""),9)=RIGHT(SUBSTITUTE('Company information'!D$4,"-",""),9)) | V57: =AH57-I57 | X57: 43858 | Y57: INV200123 | AA57: បុគ្គលជាប់អាករ | AB57: L001-901905215 | AC57: វីអ៊ីស៊ិន (ខេមបូឌា) អ៊ិនដាសស្ទ្រី ឯ.ក | AD57: 2583900 | AE57: 2349000 | AF57: 0 | AG57: 0 | AH57: 234900 | AI57: 0 | AJ57: 0 | AK57: 0 | AL57: 0 | AM57: 0 | AN57: 0 | AO57: 0 | AP57: 0 | AS57: បានប្រកាសពន្ធ
A58: 50 | C58: ខេមវីល គ្លូប៊ល ឯ.ក | D58: L001-901637190 | E58: INV200096 | F58: 43857 | G58: 93495 | I58: 93495 | J58: =IF(AND(S58=TRUE, T58=TRUE, U58=TRUE), IF(W58<-0.05, "អនុញ្ញាត (អ្នកផ្គត់ផ្គង់ប្រកាសខ្វះ)", "បានប្រកាស (អនុញ្ញាត)"), IF(AND(S58=FALSE, T58=FALSE, U58=FALSE), "ព្យួរទុក (មិនមានទិន្នន័យ)", "ប្រកាសខុស (ព្យួរទុក)")) | N58: =IF(W58<0,AH58,I58) | O58: =I58-M58 | Q58: INV200096 | R58: INV200096 | S58: =Q58=R58 | T58: =AND(MONTH(F58)=MONTH(X58), YEAR(F58)=YEAR(X58)) | U58: =AND(AB58<>"", 'Company information'!D$4<>"", RIGHT(SUBSTITUTE(AB58,"-",""),9)=RIGHT(SUBSTITUTE('Company information'!D$4,"-",""),9)) | V58: =AH58-I58 | X58: 43857 | Y58: INV200096 | AA58: បុគ្គលជាប់អាករ | AB58: L001-901905215 | AC58: វីអ៊ីស៊ិន (ខេមបូឌា) អ៊ិនដាសស្ទ្រី ឯ.ក | AD58: 1024650 | AE58: 931500 | AF58: 0 | AG58: 0 | AH58: 93150 | AI58: 0 | AJ58: 0 | AK58: 0 | AL58: 0 | AM58: 0 | AN58: 0 | AO58: 0 | AP58: 0 | AS58: បានប្រកាសពន្ធ
A59: 51 | C59: ខេមវីល គ្លូប៊ល ឯ.ក | D59: L001-901637190 | E59: INV200095 | F59: 43857 | G59: 223575 | I59: 223575 | J59: =IF(AND(S59=TRUE, T59=TRUE, U59=TRUE), IF(W59<-0.05, "អនុញ្ញាត (អ្នកផ្គត់ផ្គង់ប្រកាសខ្វះ)", "បានប្រកាស (អនុញ្ញាត)"), IF(AND(S59=FALSE, T59=FALSE, U59=FALSE), "ព្យួរទុក (មិនមានទិន្នន័យ)", "ប្រកាសខុស (ព្យួរទុក)")) | N59: =IF(W59<0,AH59,I59) | O59: =I59-M59 | Q59: INV200095 | R59: INV200095 | S59: =Q59=R59 | T59: =AND(MONTH(F59)=MONTH(X59), YEAR(F59)=YEAR(X59)) | U59: =AND(AB59<>"", 'Company information'!D$4<>"", RIGHT(SUBSTITUTE(AB59,"-",""),9)=RIGHT(SUBSTITUTE('Company information'!D$4,"-",""),9)) | V59: =AH59-I59 | X59: 43857 | Y59: INV200095 | AA59: បុគ្គលជាប់អាករ | AB59: L001-901905215 | AC59: វីអ៊ីស៊ិន (ខេមបូឌា) អ៊ិនដាសស្ទ្រី ឯ.ក | AD59: 2450250 | AE59: 2227500 | AF59: 0 | AG59: 0 | AH59: 222750 | AI59: 0 | AJ59: 0 | AK59: 0 | AL59: 0 | AM59: 0 | AN59: 0 | AO59: 0 | AP59: 0 | AS59: បានប្រកាសពន្ធ
A60: 52 | C60: ខេមវីល គ្លូប៊ល ឯ.ក | D60: L001-901637190 | E60: INV200094 | F60: 43857 | G60: 138210 | I60: 138210 | J60: =IF(AND(S60=TRUE, T60=TRUE, U60=TRUE), IF(W60<-0.05, "អនុញ្ញាត (អ្នកផ្គត់ផ្គង់ប្រកាសខ្វះ)", "បានប្រកាស (អនុញ្ញាត)"), IF(AND(S60=FALSE, T60=FALSE, U60=FALSE), "ព្យួរទុក (មិនមានទិន្នន័យ)", "ប្រកាសខុស (ព្យួរទុក)")) | N60: =IF(W60<0,AH60,I60) | O60: =I60-M60 | Q60: INV200094 | R60: INV200094 | S60: =Q60=R60 | T60: =AND(MONTH(F60)=MONTH(X60), YEAR(F60)=YEAR(X60)) | U60: =AND(AB60<>"", 'Company information'!D$4<>"", RIGHT(SUBSTITUTE(AB60,"-",""),9)=RIGHT(SUBSTITUTE('Company information'!D$4,"-",""),9)) | V60: =AH60-I60 | X60: 43857 | Y60: INV200094 | AA60: បុគ្គលជាប់អាករ | AB60: L001-901905215 | AC60: វីអ៊ីស៊ិន (ខេមបូឌា) អ៊ិនដាសស្ទ្រី ឯ.ក | AD60: 1514700 | AE60: 1377000 | AF60: 0 | AG60: 0 | AH60: 137700 | AI60: 0 | AJ60: 0 | AK60: 0 | AL60: 0 | AM60: 0 | AN60: 0 | AO60: 0 | AP60: 0 | AS60: បានប្រកាសពន្ធ
A61: 53 | C61: ខេមវីល គ្លូប៊ល ឯ.ក | D61: L001-901637190 | E61: INV200093 | F61: 43857 | G61: 138210 | I61: 138210 | J61: =IF(AND(S61=TRUE, T61=TRUE, U61=TRUE), IF(W61<-0.05, "អនុញ្ញាត (អ្នកផ្គត់ផ្គង់ប្រកាសខ្វះ)", "បានប្រកាស (អនុញ្ញាត)"), IF(AND(S61=FALSE, T61=FALSE, U61=FALSE), "ព្យួរទុក (មិនមានទិន្នន័យ)", "ប្រកាសខុស (ព្យួរទុក)")) | N61: =IF(W61<0,AH61,I61) | O61: =I61-M61 | Q61: INV200093 | R61: INV200093 | S61: =Q61=R61 | T61: =AND(MONTH(F61)=MONTH(X61), YEAR(F61)=YEAR(X61)) | U61: =AND(AB61<>"", 'Company information'!D$4<>"", RIGHT(SUBSTITUTE(AB61,"-",""),9)=RIGHT(SUBSTITUTE('Company information'!D$4,"-",""),9)) | V61: =AH61-I61 | X61: 43857 | Y61: INV200093 | AA61: បុគ្គលជាប់អាករ | AB61: L001-901905215 | AC61: វីអ៊ីស៊ិន (ខេមបូឌា) អ៊ិនដាសស្ទ្រី ឯ.ក | AD61: 1514700 | AE61: 1377000 | AF61: 0 | AG61: 0 | AH61: 137700 | AI61: 0 | AJ61: 0 | AK61: 0 | AL61: 0 | AM61: 0 | AN61: 0 | AO61: 0 | AP61: 0 | AS61: បានប្រកាសពន្ធ
A62: 54 | C62: យីងកឺ ខេម ឯ.ក | D62: K003-901900367 | E62: YK21-003 | F62: 44287 | G62: 239318 | I62: 239318 | J62: =IF(AND(S62=TRUE, T62=TRUE, U62=TRUE), IF(W62<-0.05, "អនុញ្ញាត (អ្នកផ្គត់ផ្គង់ប្រកាសខ្វះ)", "បានប្រកាស (អនុញ្ញាត)"), IF(AND(S62=FALSE, T62=FALSE, U62=FALSE), "ព្យួរទុក (មិនមានទិន្នន័យ)", "ប្រកាសខុស (ព្យួរទុក)")) | N62: =IF(W62<0,AH62,I62) | O62: =I62-M62 | Q62: YK21-003 | R62: YK21-003 | S62: =Q62=R62 | T62: =AND(MONTH(F62)=MONTH(X62), YEAR(F62)=YEAR(X62)) | U62: =AND(AB62<>"", 'Company information'!D$4<>"", RIGHT(SUBSTITUTE(AB62,"-",""),9)=RIGHT(SUBSTITUTE('Company information'!D$4,"-",""),9)) | V62: =AH62-I62 | X62: 44200 | Y62: YK21-003 | AA62: បុគ្គលជាប់អាករ | AB62: L001-901905215 | AC62: វីអ៊ីស៊ិន (ខេមបូឌា) អ៊ិនដាសស្ទ្រី ឯ.ក | AD62: 2632500 | AE62: 2393182 | AF62: 0 | AG62: 0 | AH62: 239318 | AI62: 0 | AJ62: 0 | AK62: 0 | AL62: 0 | AM62: 0 | AN62: 0 | AO62: 0 | AP62: 0 | AS62: បានប្រកាសពន្ធ
A63: 55 | C63: សូស៊ីយេតេ កុងសេស្យូនែរ ដឺ ឡាអេរ៉ូព័រ | D63: L001-100047300 | E63: 2000-064199 | F63: 44197 | G63: 129346 | I63: 129346 | J63: =IF(AND(S63=TRUE, T63=TRUE, U63=TRUE), IF(W63<-0.05, "អនុញ្ញាត (អ្នកផ្គត់ផ្គង់ប្រកាសខ្វះ)", "បានប្រកាស (អនុញ្ញាត)"), IF(AND(S63=FALSE, T63=FALSE, U63=FALSE), "ព្យួរទុក (មិនមានទិន្នន័យ)", "ប្រកាសខុស (ព្យួរទុក)")) | N63: =IF(W63<0,AH63,I63) | O63: =I63-M63 | Q63: 2000-064199 | S63: =Q63=R63 | T63: =AND(MONTH(F63)=MONTH(X63), YEAR(F63)=YEAR(X63)) | U63: =AND(AB63<>"", 'Company information'!D$4<>"", RIGHT(SUBSTITUTE(AB63,"-",""),9)=RIGHT(SUBSTITUTE('Company information'!D$4,"-",""),9)) | V63: =AH63-I63
A64: 56 | C64: កំពង់ផែស្វយ័តភ្នំពេញ "ក.ស.ភ" | D64: L001-100044999 | E64: INV20210101052 | F64: 44409 | G64: 28976 | I64: 28976 | J64: =IF(AND(S64=TRUE, T64=TRUE, U64=TRUE), IF(W64<-0.05, "អនុញ្ញាត (អ្នកផ្គត់ផ្គង់ប្រកាសខ្វះ)", "បានប្រកាស (អនុញ្ញាត)"), IF(AND(S64=FALSE, T64=FALSE, U64=FALSE), "ព្យួរទុក (មិនមានទិន្នន័យ)", "ប្រកាសខុស (ព្យួរទុក)")) | N64: =IF(W64<0,AH64,I64) | O64: =I64-M64 | Q64: INV20210101052 | S64: =Q64=R64 | T64: =AND(MONTH(F64)=MONTH(X64), YEAR(F64)=YEAR(X64)) | U64: =AND(AB64<>"", 'Company information'!D$4<>"", RIGHT(SUBSTITUTE(AB64,"-",""),9)=RIGHT(SUBSTITUTE('Company information'!D$4,"-",""),9)) | V64: =AH64-I64
A65: 57 | C65: សូស៊ីយេតេ កុងសេស្យូនែរ ដឺ ឡាអេរ៉ូព័រ | D65: L001-100047300 | E65: 2100-001119 | F65: 44409 | G65: 535848 | I65: 535848 | J65: =IF(AND(S65=TRUE, T65=TRUE, U65=TRUE), IF(W65<-0.05, "អនុញ្ញាត (អ្នកផ្គត់ផ្គង់ប្រកាសខ្វះ)", "បានប្រកាស (អនុញ្ញាត)"), IF(AND(S65=FALSE, T65=FALSE, U65=FALSE), "ព្យួរទុក (មិនមានទិន្នន័យ)", "ប្រកាសខុស (ព្យួរទុក)")) | N65: =IF(W65<0,AH65,I65) | O65: =I65-M65 | Q65: 2100-001119 | S65: =Q65=R65 | T65: =AND(MONTH(F65)=MONTH(X65), YEAR(F65)=YEAR(X65)) | U65: =AND(AB65<>"", 'Company information'!D$4<>"", RIGHT(SUBSTITUTE(AB65,"-",""),9)=RIGHT(SUBSTITUTE('Company information'!D$4,"-",""),9)) | V65: =AH65-I65
A66: 58 | C66: ហុង ឡេង ហួរ | D66: L001-100068901 | E66: 000154057 | F66: 44440 | G66: 7355 | I66: 7355 | J66: =IF(AND(S66=TRUE, T66=TRUE, U66=TRUE), IF(W66<-0.05, "អនុញ្ញាត (អ្នកផ្គត់ផ្គង់ប្រកាសខ្វះ)", "បានប្រកាស (អនុញ្ញាត)"), IF(AND(S66=FALSE, T66=FALSE, U66=FALSE), "ព្យួរទុក (មិនមានទិន្នន័យ)", "ប្រកាសខុស (ព្យួរទុក)")) | N66: =IF(W66<0,AH66,I66) | O66: =I66-M66 | Q66: 000154057 | S66: =Q66=R66 | T66: =AND(MONTH(F66)=MONTH(X66), YEAR(F66)=YEAR(X66)) | U66: =AND(AB66<>"", 'Company information'!D$4<>"", RIGHT(SUBSTITUTE(AB66,"-",""),9)=RIGHT(SUBSTITUTE('Company information'!D$4,"-",""),9)) | V66: =AH66-I66
A67: 59 | C67: ហុង ឡេង ហួរ | D67: L001-100068901 | E67: 000154056 | F67: 44440 | G67: 7355 | I67: 7355 | J67: =IF(AND(S67=TRUE, T67=TRUE, U67=TRUE), IF(W67<-0.05, "អនុញ្ញាត (អ្នកផ្គត់ផ្គង់ប្រកាសខ្វះ)", "បានប្រកាស (អនុញ្ញាត)"), IF(AND(S67=FALSE, T67=FALSE, U67=FALSE), "ព្យួរទុក (មិនមានទិន្នន័យ)", "ប្រកាសខុស (ព្យួរទុក)")) | N67: =IF(W67<0,AH67,I67) | O67: =I67-M67 | Q67: 000154056 | S67: =Q67=R67 | T67: =AND(MONTH(F67)=MONTH(X67), YEAR(F67)=YEAR(X67)) | U67: =AND(AB67<>"", 'Company information'!D$4<>"", RIGHT(SUBSTITUTE(AB67,"-",""),9)=RIGHT(SUBSTITUTE('Company information'!D$4,"-",""),9)) | V67: =AH67-I67
A68: 60 | C68: កំពង់ផែស្វយ័តភ្នំពេញ "ក.ស.ភ" | D68: L001-100044999 | E68: INV20210101055 | F68: 44409 | G68: 57952 | I68: 57952 | J68: =IF(AND(S68=TRUE, T68=TRUE, U68=TRUE), IF(W68<-0.05, "អនុញ្ញាត (អ្នកផ្គត់ផ្គង់ប្រកាសខ្វះ)", "បានប្រកាស (អនុញ្ញាត)"), IF(AND(S68=FALSE, T68=FALSE, U68=FALSE), "ព្យួរទុក (មិនមានទិន្នន័យ)", "ប្រកាសខុស (ព្យួរទុក)")) | N68: =IF(W68<0,AH68,I68) | O68: =I68-M68 | Q68: INV20210101055 | S68: =Q68=R68 | T68: =AND(MONTH(F68)=MONTH(X68), YEAR(F68)=YEAR(X68)) | U68: =AND(AB68<>"", 'Company information'!D$4<>"", RIGHT(SUBSTITUTE(AB68,"-",""),9)=RIGHT(SUBSTITUTE('Company information'!D$4,"-",""),9)) | V68: =AH68-I68
A69: 61 | C69: កំពង់ផែស្វយ័តក្រុងព្រះសីហនុ | D69: L001-100044638 | E69: 000004581 | F69: 44440 | G69: 143370 | I69: 143370 | J69: =IF(AND(S69=TRUE, T69=TRUE, U69=TRUE), IF(W69<-0.05, "អនុញ្ញាត (អ្នកផ្គត់ផ្គង់ប្រកាសខ្វះ)", "បានប្រកាស (អនុញ្ញាត)"), IF(AND(S69=FALSE, T69=FALSE, U69=FALSE), "ព្យួរទុក (មិនមានទិន្នន័យ)", "ប្រកាសខុស (ព្យួរទុក)")) | N69: =IF(W69<0,AH69,I69) | O69: =I69-M69 | Q69: 000004581 | S69: =Q69=R69 | T69: =AND(MONTH(F69)=MONTH(X69), YEAR(F69)=YEAR(X69)) | U69: =AND(AB69<>"", 'Company information'!D$4<>"", RIGHT(SUBSTITUTE(AB69,"-",""),9)=RIGHT(SUBSTITUTE('Company information'!D$4,"-",""),9)) | V69: =AH69-I69
A70: 62 | C70: កំពង់ផែស្វយ័តក្រុងព្រះសីហនុ | D70: L001-100044638 | E70: 000198486 | F70: 44197 | G70: 20629 | I70: 20629 | J70: =IF(AND(S70=TRUE, T70=TRUE, U70=TRUE), IF(W70<-0.05, "អនុញ្ញាត (អ្នកផ្គត់ផ្គង់ប្រកាសខ្វះ)", "បានប្រកាស (អនុញ្ញាត)"), IF(AND(S70=FALSE, T70=FALSE, U70=FALSE), "ព្យួរទុក (មិនមានទិន្នន័យ)", "ប្រកាសខុស (ព្យួរទុក)")) | N70: =IF(W70<0,AH70,I70) | O70: =I70-M70 | Q70: 000198486 | S70: =Q70=R70 | T70: =AND(MONTH(F70)=MONTH(X70), YEAR(F70)=YEAR(X70)) | U70: =AND(AB70<>"", 'Company information'!D$4<>"", RIGHT(SUBSTITUTE(AB70,"-",""),9)=RIGHT(SUBSTITUTE('Company information'!D$4,"-",""),9)) | V70: =AH70-I70
A71: 63 | C71: ភីស៊ីអាយ សឺវីស | D71: K010-901639639 | E71: 20210017 | F71: 44223 | G71: 81000 | I71: 81000 | J71: =IF(AND(S71=TRUE, T71=TRUE, U71=TRUE), IF(W71<-0.05, "អនុញ្ញាត (អ្នកផ្គត់ផ្គង់ប្រកាសខ្វះ)", "បានប្រកាស (អនុញ្ញាត)"), IF(AND(S71=FALSE, T71=FALSE, U71=FALSE), "ព្យួរទុក (មិនមានទិន្នន័យ)", "ប្រកាសខុស (ព្យួរទុក)")) | N71: =IF(W71<0,AH71,I71) | O71: =I71-M71 | Q71: 20210017 | R71: 2021-0017 | S71: =Q71=R71 | T71: =AND(MONTH(F71)=MONTH(X71), YEAR(F71)=YEAR(X71)) | U71: =AND(AB71<>"", 'Company information'!D$4<>"", RIGHT(SUBSTITUTE(AB71,"-",""),9)=RIGHT(SUBSTITUTE('Company information'!D$4,"-",""),9)) | V71: =AH71-I71 | X71: 44222 | Y71: 2021-0017 | AA71: បុគ្គលជាប់អាករ | AB71: L001-100186998 | AC71: ស្តារឡៃថ៍ អឹភែរឹល មេនូហ្វេកឆឺរីង | AD71: 2539350 | AE71: 2308500 | AF71: 0 | AG71: 0 | AH71: 230850 | AI71: 0 | AJ71: 0 | AK71: 0 | AL71: 0 | AM71: 0 | AN71: 0 | AO71: 0 | AP71: 0 | AS71: បានប្រកាសពន្ធ
A72: 64 | C72: យូសេន ឡូជីស្ទីក (ខេមបូឌា) ខូ អិលធីឌី | D72: L001-104015799 | E72: C07741272 | F72: 44219 | G72: 146160 | I72: 146160 | J72: =IF(AND(S72=TRUE, T72=TRUE, U72=TRUE), IF(W72<-0.05, "អនុញ្ញាត (អ្នកផ្គត់ផ្គង់ប្រកាសខ្វះ)", "បានប្រកាស (អនុញ្ញាត)"), IF(AND(S72=FALSE, T72=FALSE, U72=FALSE), "ព្យួរទុក (មិនមានទិន្នន័យ)", "ប្រកាសខុស (ព្យួរទុក)")) | N72: =IF(W72<0,AH72,I72) | O72: =I72-M72 | Q72: C07741272 | S72: =Q72=R72 | T72: =AND(MONTH(F72)=MONTH(X72), YEAR(F72)=YEAR(X72)) | U72: =AND(AB72<>"", 'Company information'!D$4<>"", RIGHT(SUBSTITUTE(AB72,"-",""),9)=RIGHT(SUBSTITUTE('Company information'!D$4,"-",""),9)) | V72: =AH72-I72
A73: 65 | C73: យូសេន ឡូជីស្ទីក (ខេមបូឌា) ខូ អិលធីឌី | D73: L001-104015799 | E73: C07708108 | F73: 44348 | G73: 160984 | I73: 160984 | J73: =IF(AND(S73=TRUE, T73=TRUE, U73=TRUE), IF(W73<-0.05, "អនុញ្ញាត (អ្នកផ្គត់ផ្គង់ប្រកាសខ្វះ)", "បានប្រកាស (អនុញ្ញាត)"), IF(AND(S73=FALSE, T73=FALSE, U73=FALSE), "ព្យួរទុក (មិនមានទិន្នន័យ)", "ប្រកាសខុស (ព្យួរទុក)")) | N73: =IF(W73<0,AH73,I73) | O73: =I73-M73 | Q73: C07708108 | S73: =Q73=R73 | T73: =AND(MONTH(F73)=MONTH(X73), YEAR(F73)=YEAR(X73)) | U73: =AND(AB73<>"", 'Company information'!D$4<>"", RIGHT(SUBSTITUTE(AB73,"-",""),9)=RIGHT(SUBSTITUTE('Company information'!D$4,"-",""),9)) | V73: =AH73-I73
A74: 66 | C74: វ៉ាយ.ស៊ី ផេកខេជីង ឯ.ក | D74: L001-901700417 | E74: TI0009 | F74: 44227 | G74: 20521518 | I74: 20521518 | J74: =IF(AND(S74=TRUE, T74=TRUE, U74=TRUE), IF(W74<-0.05, "អនុញ្ញាត (អ្នកផ្គត់ផ្គង់ប្រកាសខ្វះ)", "បានប្រកាស (អនុញ្ញាត)"), IF(AND(S74=FALSE, T74=FALSE, U74=FALSE), "ព្យួរទុក (មិនមានទិន្នន័យ)", "ប្រកាសខុស (ព្យួរទុក)")) | N74: =IF(W74<0,AH74,I74) | O74: =I74-M74 | Q74: TI0009 | R74: TI0009 | S74: =Q74=R74 | T74: =AND(MONTH(F74)=MONTH(X74), YEAR(F74)=YEAR(X74)) | U74: =AND(AB74<>"", 'Company information'!D$4<>"", RIGHT(SUBSTITUTE(AB74,"-",""),9)=RIGHT(SUBSTITUTE('Company information'!D$4,"-",""),9)) | V74: =AH74-I74 | X74: 44227 | Y74: TI0009 | AA74: បុគ្គលជាប់អាករ | AB74: L001-901905215 | AC74: វីអ៊ីស៊ិន (ខេមបូឌា) អ៊ិនដាសស្ទ្រី ឯ.ក | AD74: 225736702 | AE74: 205215184 | AF74: 0 | AG74: 0 | AH74: 20521518 | AI74: 0 | AJ74: 0 | AK74: 0 | AL74: 0 | AM74: 0 | AN74: 0 | AO74: 0 | AP74: 0 | AS74: បានប្រកាសពន្ធ
A75: 67 | C75: វ៉ាយ.ស៊ី ផេកខេជីង ឯ.ក | D75: L001-901700417 | E75: TI0014 | F75: 44227 | G75: 8926594 | I75: 8926594 | J75: =IF(AND(S75=TRUE, T75=TRUE, U75=TRUE), IF(W75<-0.05, "អនុញ្ញាត (អ្នកផ្គត់ផ្គង់ប្រកាសខ្វះ)", "បានប្រកាស (អនុញ្ញាត)"), IF(AND(S75=FALSE, T75=FALSE, U75=FALSE), "ព្យួរទុក (មិនមានទិន្នន័យ)", "ប្រកាសខុស (ព្យួរទុក)")) | N75: =IF(W75<0,AH75,I75) | O75: =I75-M75 | Q75: TI0014 | R75: TI0014 | S75: =Q75=R75 | T75: =AND(MONTH(F75)=MONTH(X75), YEAR(F75)=YEAR(X75)) | U75: =AND(AB75<>"", 'Company information'!D$4<>"", RIGHT(SUBSTITUTE(AB75,"-",""),9)=RIGHT(SUBSTITUTE('Company information'!D$4,"-",""),9)) | V75: =AH75-I75 | X75: 44227 | Y75: TI0014 | AA75: បុគ្គលជាប់អាករ | AB75: L001-901905215 | AC75: វីអ៊ីស៊ិន (ខេមបូឌា) អ៊ិនដាសស្ទ្រី ឯ.ក | AD75: 98192524 | AE75: 89265931 | AF75: 0 | AG75: 0 | AH75: 8926593 | AI75: 0 | AJ75: 0 | AK75: 0 | AL75: 0 | AM75: 0 | AN75: 0 | AO75: 0 | AP75: 0 | AS75: បានប្រកាសពន្ធ
A76: 68 | C76: ស៊ីន ហ្វី យ៉ាង ព្រីនធីង & អិកសេសសឺរី ឯ.ក | D76: K010-901906822 | E76: XFY-YD2021015 | F76: 44225 | G76: 4389968 | I76: 4389968 | J76: =IF(AND(S76=TRUE, T76=TRUE, U76=TRUE), IF(W76<-0.05, "អនុញ្ញាត (អ្នកផ្គត់ផ្គង់ប្រកាសខ្វះ)", "បានប្រកាស (អនុញ្ញាត)"), IF(AND(S76=FALSE, T76=FALSE, U76=FALSE), "ព្យួរទុក (មិនមានទិន្នន័យ)", "ប្រកាសខុស (ព្យួរទុក)")) | N76: =IF(W76<0,AH76,I76) | O76: =I76-M76 | Q76: XFY-YD2021015 | R76: XFY-YD2021015 | S76: =Q76=R76 | T76: =AND(MONTH(F76)=MONTH(X76), YEAR(F76)=YEAR(X76)) | U76: =AND(AB76<>"", 'Company information'!D$4<>"", RIGHT(SUBSTITUTE(AB76,"-",""),9)=RIGHT(SUBSTITUTE('Company information'!D$4,"-",""),9)) | V76: =AH76-I76 | X76: 44225 | Y76: XFY-YD2021015 | AA76: បុគ្គលជាប់អាករ | AB76: L001-901905215 | AC76: វីអ៊ីស៊ិន (ខេមបូឌា) អ៊ិនដាសស្ទ្រី ឯ.ក | AD76: 48289651 | AE76: 43899683 | AF76: 0 | AG76: 0 | AH76: 4389968 | AI76: 0 | AJ76: 0 | AK76: 0 | AL76: 0 | AM76: 0 | AN76: 0 | AO76: 0 | AP76: 0 | AS76: បានប្រកាសពន្ធ
A77: 69 | C77: ត្រេនម៉ារីន ឡូជីស្ទីក (ខេមបូឌា) | D77: L001-106004107 | E77: 9960005542 | F77: 44210 | G77: 73691 | I77: 73691 | J77: =IF(AND(S77=TRUE, T77=TRUE, U77=TRUE), IF(W77<-0.05, "អនុញ្ញាត (អ្នកផ្គត់ផ្គង់ប្រកាសខ្វះ)", "បានប្រកាស (អនុញ្ញាត)"), IF(AND(S77=FALSE, T77=FALSE, U77=FALSE), "ព្យួរទុក (មិនមានទិន្នន័យ)", "ប្រកាសខុស (ព្យួរទុក)")) | N77: =IF(W77<0,AH77,I77) | O77: =I77-M77 | Q77: 9960005542 | S77: =Q77=R77 | T77: =AND(MONTH(F77)=MONTH(X77), YEAR(F77)=YEAR(X77)) | U77: =AND(AB77<>"", 'Company information'!D$4<>"", RIGHT(SUBSTITUTE(AB77,"-",""),9)=RIGHT(SUBSTITUTE('Company information'!D$4,"-",""),9)) | V77: =AH77-I77
A78: 70 | C78: ត្រេនម៉ារីន ឡូជីស្ទីក (ខេមបូឌា) | D78: L001-106004107 | E78: 9963004026 | F78: 44210 | G78: 99299 | I78: 99299 | J78: =IF(AND(S78=TRUE, T78=TRUE, U78=TRUE), IF(W78<-0.05, "អនុញ្ញាត (អ្នកផ្គត់ផ្គង់ប្រកាសខ្វះ)", "បានប្រកាស (អនុញ្ញាត)"), IF(AND(S78=FALSE, T78=FALSE, U78=FALSE), "ព្យួរទុក (មិនមានទិន្នន័យ)", "ប្រកាសខុស (ព្យួរទុក)")) | N78: =IF(W78<0,AH78,I78) | O78: =I78-M78 | Q78: 9963004026 | R78: 9963004026 | S78: =Q78=R78 | T78: =AND(MONTH(F78)=MONTH(X78), YEAR(F78)=YEAR(X78)) | U78: =AND(AB78<>"", 'Company information'!D$4<>"", RIGHT(SUBSTITUTE(AB78,"-",""),9)=RIGHT(SUBSTITUTE('Company information'!D$4,"-",""),9)) | V78: =AH78-I78 | X78: 44210 | Y78: 9963004026 | AA78: បុគ្គលជាប់អាករ | AB78: L001-901905215 | AC78: វីអ៊ីស៊ិន (ខេមបូឌា) អ៊ិនដាសស្ទ្រី ឯ.ក | AD78: 1095518 | AE78: 995925 | AF78: 0 | AG78: 0 | AH78: 99593 | AI78: 0 | AJ78: 0 | AK78: 0 | AL78: 0 | AM78: 0 | AN78: 0 | AO78: 0 | AP78: 0 | AS78: បានប្រកាសពន្ធ
A79: 71 | C79: ស្ត្រេតស៍ អ៊ិនធើណេសិនណល ភីធីអ៊ី អិលធីឌី | D79: L001-100045162 | E79: INV2100674 | F79: 44531 | G79: 200202 | I79: 200202 | J79: =IF(AND(S79=TRUE, T79=TRUE, U79=TRUE), IF(W79<-0.05, "អនុញ្ញាត (អ្នកផ្គត់ផ្គង់ប្រកាសខ្វះ)", "បានប្រកាស (អនុញ្ញាត)"), IF(AND(S79=FALSE, T79=FALSE, U79=FALSE), "ព្យួរទុក (មិនមានទិន្នន័យ)", "ប្រកាសខុស (ព្យួរទុក)")) | N79: =IF(W79<0,AH79,I79) | O79: =I79-M79 | Q79: INV2100674 | S79: =Q79=R79 | T79: =AND(MONTH(F79)=MONTH(X79), YEAR(F79)=YEAR(X79)) | U79: =AND(AB79<>"", 'Company information'!D$4<>"", RIGHT(SUBSTITUTE(AB79,"-",""),9)=RIGHT(SUBSTITUTE('Company information'!D$4,"-",""),9)) | V79: =AH79-I79
A80: 72 | C80: ស្ត្រេតស៍ អ៊ិនធើណេសិនណល ភីធីអ៊ី អិលធីឌី | D80: L001-100045162 | E80: INV2024573 | F80: 44197 | G80: 260129 | I80: 260129 | J80: =IF(AND(S80=TRUE, T80=TRUE, U80=TRUE), IF(W80<-0.05, "អនុញ្ញាត (អ្នកផ្គត់ផ្គង់ប្រកាសខ្វះ)", "បានប្រកាស (អនុញ្ញាត)"), IF(AND(S80=FALSE, T80=FALSE, U80=FALSE), "ព្យួរទុក (មិនមានទិន្នន័យ)", "ប្រកាសខុស (ព្យួរទុក)")) | N80: =IF(W80<0,AH80,I80) | O80: =I80-M80 | Q80: INV2024573 | S80: =Q80=R80 | T80: =AND(MONTH(F80)=MONTH(X80), YEAR(F80)=YEAR(X80)) | U80: =AND(AB80<>"", 'Company information'!D$4<>"", RIGHT(SUBSTITUTE(AB80,"-",""),9)=RIGHT(SUBSTITUTE('Company information'!D$4,"-",""),9)) | V80: =AH80-I80
A81: 73 | C81: សូស៊ីយេតេ កុងសេស្យូនែរ ដឺ ឡាអេរ៉ូព័រ | D81: L001-100047300 | E81: INV21000011793 | F81: 44197 | G81: 5799 | I81: 5799 | J81: =IF(AND(S81=TRUE, T81=TRUE, U81=TRUE), IF(W81<-0.05, "អនុញ្ញាត (អ្នកផ្គត់ផ្គង់ប្រកាសខ្វះ)", "បានប្រកាស (អនុញ្ញាត)"), IF(AND(S81=FALSE, T81=FALSE, U81=FALSE), "ព្យួរទុក (មិនមានទិន្នន័យ)", "ប្រកាសខុស (ព្យួរទុក)")) | N81: =IF(W81<0,AH81,I81) | O81: =I81-M81 | Q81: INV21000011793 | S81: =Q81=R81 | T81: =AND(MONTH(F81)=MONTH(X81), YEAR(F81)=YEAR(X81)) | U81: =AND(AB81<>"", 'Company information'!D$4<>"", RIGHT(SUBSTITUTE(AB81,"-",""),9)=RIGHT(SUBSTITUTE('Company information'!D$4,"-",""),9)) | V81: =AH81-I81
A82: 74 | C82: សូស៊ីយេតេ កុងសេស្យូនែរ ដឺ ឡាអេរ៉ូព័រ | D82: L001-100047300 | E82: INV2100004647 | F82: 44197 | G82: 4549 | I82: 4549 | J82: =IF(AND(S82=TRUE, T82=TRUE, U82=TRUE), IF(W82<-0.05, "អនុញ្ញាត (អ្នកផ្គត់ផ្គង់ប្រកាសខ្វះ)", "បានប្រកាស (អនុញ្ញាត)"), IF(AND(S82=FALSE, T82=FALSE, U82=FALSE), "ព្យួរទុក (មិនមានទិន្នន័យ)", "ប្រកាសខុស (ព្យួរទុក)")) | N82: =IF(W82<0,AH82,I82) | O82: =I82-M82 | Q82: INV2100004647 | S82: =Q82=R82 | T82: =AND(MONTH(F82)=MONTH(X82), YEAR(F82)=YEAR(X82)) | U82: =AND(AB82<>"", 'Company information'!D$4<>"", RIGHT(SUBSTITUTE(AB82,"-",""),9)=RIGHT(SUBSTITUTE('Company information'!D$4,"-",""),9)) | V82: =AH82-I82
A83: 75 | C83: សូស៊ីយេតេ កុងសេស្យូនែរ ដឺ ឡាអេរ៉ូព័រ | D83: L001-100047300 | E83: 2100-003714 | F83: 44225 | G83: 6854 | I83: 6854 | J83: =IF(AND(S83=TRUE, T83=TRUE, U83=TRUE), IF(W83<-0.05, "អនុញ្ញាត (អ្នកផ្គត់ផ្គង់ប្រកាសខ្វះ)", "បានប្រកាស (អនុញ្ញាត)"), IF(AND(S83=FALSE, T83=FALSE, U83=FALSE), "ព្យួរទុក (មិនមានទិន្នន័យ)", "ប្រកាសខុស (ព្យួរទុក)")) | N83: =IF(W83<0,AH83,I83) | O83: =I83-M83 | Q83: 2100-003714 | S83: =Q83=R83 | T83: =AND(MONTH(F83)=MONTH(X83), YEAR(F83)=YEAR(X83)) | U83: =AND(AB83<>"", 'Company information'!D$4<>"", RIGHT(SUBSTITUTE(AB83,"-",""),9)=RIGHT(SUBSTITUTE('Company information'!D$4,"-",""),9)) | V83: =AH83-I83
A84: 76 | C84: សូស៊ីយេតេ កុងសេស្យូនែរ ដឺ ឡាអេរ៉ូព័រ | D84: L001-100047300 | E84: 2100-005740 | F84: 44225 | G84: 42731 | I84: 42731 | J84: =IF(AND(S84=TRUE, T84=TRUE, U84=TRUE), IF(W84<-0.05, "អនុញ្ញាត (អ្នកផ្គត់ផ្គង់ប្រកាសខ្វះ)", "បានប្រកាស (អនុញ្ញាត)"), IF(AND(S84=FALSE, T84=FALSE, U84=FALSE), "ព្យួរទុក (មិនមានទិន្នន័យ)", "ប្រកាសខុស (ព្យួរទុក)")) | N84: =IF(W84<0,AH84,I84) | O84: =I84-M84 | Q84: 2100-005740 | S84: =Q84=R84 | T84: =AND(MONTH(F84)=MONTH(X84), YEAR(F84)=YEAR(X84)) | U84: =AND(AB84<>"", 'Company information'!D$4<>"", RIGHT(SUBSTITUTE(AB84,"-",""),9)=RIGHT(SUBSTITUTE('Company information'!D$4,"-",""),9)) | V84: =AH84-I84
A85: 77 | C85: សូស៊ីយេតេ កុងសេស្យូនែរ ដឺ ឡាអេរ៉ូព័រ | D85: L001-100047300 | E85: 2100-005739 | F85: 44225 | G85: 30244 | I85: 30244 | J85: =IF(AND(S85=TRUE, T85=TRUE, U85=TRUE), IF(W85<-0.05, "អនុញ្ញាត (អ្នកផ្គត់ផ្គង់ប្រកាសខ្វះ)", "បានប្រកាស (អនុញ្ញាត)"), IF(AND(S85=FALSE, T85=FALSE, U85=FALSE), "ព្យួរទុក (មិនមានទិន្នន័យ)", "ប្រកាសខុស (ព្យួរទុក)")) | N85: =IF(W85<0,AH85,I85) | O85: =I85-M85 | Q85: 2100-005739 | S85: =Q85=R85 | T85: =AND(MONTH(F85)=MONTH(X85), YEAR(F85)=YEAR(X85)) | U85: =AND(AB85<>"", 'Company information'!D$4<>"", RIGHT(SUBSTITUTE(AB85,"-",""),9)=RIGHT(SUBSTITUTE('Company information'!D$4,"-",""),9)) | V85: =AH85-I85
A86: 78 | C86: សូស៊ីយេតេ កុងសេស្យូនែរ ដឺ ឡាអេរ៉ូព័រ | D86: L001-100047300 | E86: 2100-005347 | F86: 44225 | G86: 86666 | I86: 86666 | J86: =IF(AND(S86=TRUE, T86=TRUE, U86=TRUE), IF(W86<-0.05, "អនុញ្ញាត (អ្នកផ្គត់ផ្គង់ប្រកាសខ្វះ)", "បានប្រកាស (អនុញ្ញាត)"), IF(AND(S86=FALSE, T86=FALSE, U86=FALSE), "ព្យួរទុក (មិនមានទិន្នន័យ)", "ប្រកាសខុស (ព្យួរទុក)")) | N86: =IF(W86<0,AH86,I86) | O86: =I86-M86 | Q86: 2100-005347 | S86: =Q86=R86 | T86: =AND(MONTH(F86)=MONTH(X86), YEAR(F86)=YEAR(X86)) | U86: =AND(AB86<>"", 'Company information'!D$4<>"", RIGHT(SUBSTITUTE(AB86,"-",""),9)=RIGHT(SUBSTITUTE('Company information'!D$4,"-",""),9)) | V86: =AH86-I86
A87: 79 | C87: ស៊ីងហ្គាពួរ កាតុង (ខេមបូឌា) | D87: L001-100121322 | E87: V0015467 | F87: 44225 | G87: 109796 | I87: 109796 | J87: =IF(AND(S87=TRUE, T87=TRUE, U87=TRUE), IF(W87<-0.05, "អនុញ្ញាត (អ្នកផ្គត់ផ្គង់ប្រកាសខ្វះ)", "បានប្រកាស (អនុញ្ញាត)"), IF(AND(S87=FALSE, T87=FALSE, U87=FALSE), "ព្យួរទុក (មិនមានទិន្នន័យ)", "ប្រកាសខុស (ព្យួរទុក)")) | N87: =IF(W87<0,AH87,I87) | O87: =I87-M87 | Q87: V0015467 | R87: V0015467 | S87: =Q87=R87 | T87: =AND(MONTH(F87)=MONTH(X87), YEAR(F87)=YEAR(X87)) | U87: =AND(AB87<>"", 'Company information'!D$4<>"", RIGHT(SUBSTITUTE(AB87,"-",""),9)=RIGHT(SUBSTITUTE('Company information'!D$4,"-",""),9)) | V87: =AH87-I87 | X87: 44225 | Y87: V0015467 | AA87: បុគ្គលជាប់អាករ | AB87: L001-901905215 | AC87: វីអ៊ីស៊ិន (ខេមបូឌា) អ៊ិនដាសស្ទ្រី ឯ.ក | AD87: 1207752 | AE87: 1097956 | AF87: 0 | AG87: 0 | AH87: 109796 | AI87: 0 | AJ87: 0 | AK87: 0 | AL87: 0 | AM87: 0 | AN87: 0 | AO87: 0 | AP87: 0 | AS87: បានប្រកាសពន្ធ
A88: 80 | C88: ស៊ីងហ្គាពួរ កាតុង (ខេមបូឌា) | D88: L001-100121322 | E88: V0015456 | F88: 44224 | G88: 661704 | I88: 661704 | J88: =IF(AND(S88=TRUE, T88=TRUE, U88=TRUE), IF(W88<-0.05, "អនុញ្ញាត (អ្នកផ្គត់ផ្គង់ប្រកាសខ្វះ)", "បានប្រកាស (អនុញ្ញាត)"), IF(AND(S88=FALSE, T88=FALSE, U88=FALSE), "ព្យួរទុក (មិនមានទិន្នន័យ)", "ប្រកាសខុស (ព្យួរទុក)")) | N88: =IF(W88<0,AH88,I88) | O88: =I88-M88 | Q88: V0015456 | R88: V0015456 | S88: =Q88=R88 | T88: =AND(MONTH(F88)=MONTH(X88), YEAR(F88)=YEAR(X88)) | U88: =AND(AB88<>"", 'Company information'!D$4<>"", RIGHT(SUBSTITUTE(AB88,"-",""),9)=RIGHT(SUBSTITUTE('Company information'!D$4,"-",""),9)) | V88: =AH88-I88 | X88: 44224 | Y88: V0015456 | AA88: បុគ្គលជាប់អាករ | AB88: L001-901905215 | AC88: វីអ៊ីស៊ិន (ខេមបូឌា) អ៊ិនដាសស្ទ្រី ឯ.ក | AD88: 7282326 | AE88: 6620296 | AF88: 0 | AG88: 0 | AH88: 662030 | AI88: 0 | AJ88: 0 | AK88: 0 | AL88: 0 | AM88: 0 | AN88: 0 | AO88: 0 | AP88: 0 | AS88: បានប្រកាសពន្ធ
A89: 81 | C89: ស៊ីងហ្គាពួរ កាតុង (ខេមបូឌា) | D89: L001-100121322 | E89: V0015465 | F89: 44225 | G89: 843488 | I89: 843488 | J89: =IF(AND(S89=TRUE, T89=TRUE, U89=TRUE), IF(W89<-0.05, "អនុញ្ញាត (អ្នកផ្គត់ផ្គង់ប្រកាសខ្វះ)", "បានប្រកាស (អនុញ្ញាត)"), IF(AND(S89=FALSE, T89=FALSE, U89=FALSE), "ព្យួរទុក (មិនមានទិន្នន័យ)", "ប្រកាសខុស (ព្យួរទុក)")) | N89: =IF(W89<0,AH89,I89) | O89: =I89-M89 | Q89: V0015465 | R89: V0015465 | S89: =Q89=R89 | T89: =AND(MONTH(F89)=MONTH(X89), YEAR(F89)=YEAR(X89)) | U89: =AND(AB89<>"", 'Company information'!D$4<>"", RIGHT(SUBSTITUTE(AB89,"-",""),9)=RIGHT(SUBSTITUTE('Company information'!D$4,"-",""),9)) | V89: =AH89-I89 | X89: 44225 | Y89: V0015465 | AA89: បុគ្គលជាប់អាករ | AB89: L001-901905215 | AC89: វីអ៊ីស៊ិន (ខេមបូឌា) អ៊ិនដាសស្ទ្រី ឯ.ក | AD89: 9278363 | AE89: 8434875 | AF89: 0 | AG89: 0 | AH89: 843488 | AI89: 0 | AJ89: 0 | AK89: 0 | AL89: 0 | AM89: 0 | AN89: 0 | AO89: 0 | AP89: 0 | AS89: បានប្រកាសពន្ធ
A90: 82 | C90: ស៊ីងហ្គាពួរ កាតុង (ខេមបូឌា) | D90: L001-100121322 | E90: V0015448 | F90: 44223 | G90: 582491 | I90: 582491 | J90: =IF(AND(S90=TRUE, T90=TRUE, U90=TRUE), IF(W90<-0.05, "អនុញ្ញាត (អ្នកផ្គត់ផ្គង់ប្រកាសខ្វះ)", "បានប្រកាស (អនុញ្ញាត)"), IF(AND(S90=FALSE, T90=FALSE, U90=FALSE), "ព្យួរទុក (មិនមានទិន្នន័យ)", "ប្រកាសខុស (ព្យួរទុក)")) | N90: =IF(W90<0,AH90,I90) | O90: =I90-M90 | Q90: V0015448 | R90: V0015448 | S90: =Q90=R90 | T90: =AND(MONTH(F90)=MONTH(X90), YEAR(F90)=YEAR(X90)) | U90: =AND(AB90<>"", 'Company information'!D$4<>"", RIGHT(SUBSTITUTE(AB90,"-",""),9)=RIGHT(SUBSTITUTE('Company information'!D$4,"-",""),9)) | V90: =AH90-I90 | X90: 44223 | Y90: V0015448 | AA90: បុគ្គលជាប់អាករ | AB90: L001-901905215 | AC90: វីអ៊ីស៊ិន (ខេមបូឌា) អ៊ិនដាសស្ទ្រី ឯ.ក | AD90: 6412131 | AE90: 5829210 | AF90: 0 | AG90: 0 | AH90: 582921 | AI90: 0 | AJ90: 0 | AK90: 0 | AL90: 0 | AM90: 0 | AN90: 0 | AO90: 0 | AP90: 0 | AS90: បានប្រកាសពន្ធ
A91: 83 | C91: ស៊ីងហ្គាពួរ កាតុង (ខេមបូឌា) | D91: L001-100121322 | E91: V0015442 | F91: 44222 | G91: 14908 | I91: 14908 | J91: =IF(AND(S91=TRUE, T91=TRUE, U91=TRUE), IF(W91<-0.05, "អនុញ្ញាត (អ្នកផ្គត់ផ្គង់ប្រកាសខ្វះ)", "បានប្រកាស (អនុញ្ញាត)"), IF(AND(S91=FALSE, T91=FALSE, U91=FALSE), "ព្យួរទុក (មិនមានទិន្នន័យ)", "ប្រកាសខុស (ព្យួរទុក)")) | N91: =IF(W91<0,AH91,I91) | O91: =I91-M91 | Q91: V0015442 | R91: V0015442 | S91: =Q91=R91 | T91: =AND(MONTH(F91)=MONTH(X91), YEAR(F91)=YEAR(X91)) | U91: =AND(AB91<>"", 'Company information'!D$4<>"", RIGHT(SUBSTITUTE(AB91,"-",""),9)=RIGHT(SUBSTITUTE('Company information'!D$4,"-",""),9)) | V91: =AH91-I91 | X91: 44222 | Y91: V0015442 | AA91: បុគ្គលជាប់អាករ | AB91: L001-901905215 | AC91: វីអ៊ីស៊ិន (ខេមបូឌា) អ៊ិនដាសស្ទ្រី ឯ.ក | AD91: 164104 | AE91: 149185 | AF91: 0 | AG91: 0 | AH91: 14919 | AI91: 0 | AJ91: 0 | AK91: 0 | AL91: 0 | AM91: 0 | AN91: 0 | AO91: 0 | AP91: 0 | AS91: បានប្រកាសពន្ធ
A92: 84 | C92: ស៊ីងហ្គាពួរ កាតុង (ខេមបូឌា) | D92: L001-100121322 | E92: V00115421 | F92: 44219 | G92: 267960 | I92: 267960 | J92: =IF(AND(S92=TRUE, T92=TRUE, U92=TRUE), IF(W92<-0.05, "អនុញ្ញាត (អ្នកផ្គត់ផ្គង់ប្រកាសខ្វះ)", "បានប្រកាស (អនុញ្ញាត)"), IF(AND(S92=FALSE, T92=FALSE, U92=FALSE), "ព្យួរទុក (មិនមានទិន្នន័យ)", "ប្រកាសខុស (ព្យួរទុក)")) | N92: =IF(W92<0,AH92,I92) | O92: =I92-M92 | Q92: V00115421 | S92: =Q92=R92 | T92: =AND(MONTH(F92)=MONTH(X92), YEAR(F92)=YEAR(X92)) | U92: =AND(AB92<>"", 'Company information'!D$4<>"", RIGHT(SUBSTITUTE(AB92,"-",""),9)=RIGHT(SUBSTITUTE('Company information'!D$4,"-",""),9)) | V92: =AH92-I92
A93: 85 | C93: ស៊ីងហ្គាពួរ កាតុង (ខេមបូឌា) | D93: L001-100121322 | E93: V0015416 | F93: 44218 | G93: 575542 | I93: 575542 | J93: =IF(AND(S93=TRUE, T93=TRUE, U93=TRUE), IF(W93<-0.05, "អនុញ្ញាត (អ្នកផ្គត់ផ្គង់ប្រកាសខ្វះ)", "បានប្រកាស (អនុញ្ញាត)"), IF(AND(S93=FALSE, T93=FALSE, U93=FALSE), "ព្យួរទុក (មិនមានទិន្នន័យ)", "ប្រកាសខុស (ព្យួរទុក)")) | N93: =IF(W93<0,AH93,I93) | O93: =I93-M93 | Q93: V0015416 | R93: V0015416 | S93: =Q93=R93 | T93: =AND(MONTH(F93)=MONTH(X93), YEAR(F93)=YEAR(X93)) | U93: =AND(AB93<>"", 'Company information'!D$4<>"", RIGHT(SUBSTITUTE(AB93,"-",""),9)=RIGHT(SUBSTITUTE('Company information'!D$4,"-",""),9)) | V93: =AH93-I93 | X93: 44218 | Y93: V0015416 | AA93: បុគ្គលជាប់អាករ | AB93: L001-901905215 | AC93: វីអ៊ីស៊ិន (ខេមបូឌា) អ៊ិនដាសស្ទ្រី ឯ.ក | AD93: 6338758 | AE93: 5762507 | AF93: 0 | AG93: 0 | AH93: 576251 | AI93: 0 | AJ93: 0 | AK93: 0 | AL93: 0 | AM93: 0 | AN93: 0 | AO93: 0 | AP93: 0 | AS93: បានប្រកាសពន្ធ
A94: 86 | C94: ស៊ីងហ្គាពួរ កាតុង (ខេមបូឌា) | D94: L001-100121322 | E94: V0015384 | F94: 44214 | G94: 694926 | I94: 694926 | J94: =IF(AND(S94=TRUE, T94=TRUE, U94=TRUE), IF(W94<-0.05, "អនុញ្ញាត (អ្នកផ្គត់ផ្គង់ប្រកាសខ្វះ)", "បានប្រកាស (អនុញ្ញាត)"), IF(AND(S94=FALSE, T94=FALSE, U94=FALSE), "ព្យួរទុក (មិនមានទិន្នន័យ)", "ប្រកាសខុស (ព្យួរទុក)")) | N94: =IF(W94<0,AH94,I94) | O94: =I94-M94 | Q94: V0015384 | R94: V0015384 | S94: =Q94=R94 | T94: =AND(MONTH(F94)=MONTH(X94), YEAR(F94)=YEAR(X94)) | U94: =AND(AB94<>"", 'Company information'!D$4<>"", RIGHT(SUBSTITUTE(AB94,"-",""),9)=RIGHT(SUBSTITUTE('Company information'!D$4,"-",""),9)) | V94: =AH94-I94 | X94: 44214 | Y94: V0015384 | AA94: បុគ្គលជាប់អាករ | AB94: L001-901905215 | AC94: វីអ៊ីស៊ិន (ខេមបូឌា) អ៊ិនដាសស្ទ្រី ឯ.ក | AD94: 7666834 | AE94: 6969849 | AF94: 0 | AG94: 0 | AH94: 696985 | AI94: 0 | AJ94: 0 | AK94: 0 | AL94: 0 | AM94: 0 | AN94: 0 | AO94: 0 | AP94: 0 | AS94: បានប្រកាសពន្ធ
A95: 87 | C95: ស៊ីងហ្គាពួរ កាតុង (ខេមបូឌា) | D95: L001-100121322 | E95: V0015354 | F95: 44209 | G95: 435900 | I95: 435900 | J95: =IF(AND(S95=TRUE, T95=TRUE, U95=TRUE), IF(W95<-0.05, "អនុញ្ញាត (អ្នកផ្គត់ផ្គង់ប្រកាសខ្វះ)", "បានប្រកាស (អនុញ្ញាត)"), IF(AND(S95=FALSE, T95=FALSE, U95=FALSE), "ព្យួរទុក (មិនមានទិន្នន័យ)", "ប្រកាសខុស (ព្យួរទុក)")) | N95: =IF(W95<0,AH95,I95) | O95: =I95-M95 | Q95: V0015354 | R95: V0015354 | S95: =Q95=R95 | T95: =AND(MONTH(F95)=MONTH(X95), YEAR(F95)=YEAR(X95)) | U95: =AND(AB95<>"", 'Company information'!D$4<>"", RIGHT(SUBSTITUTE(AB95,"-",""),9)=RIGHT(SUBSTITUTE('Company information'!D$4,"-",""),9)) | V95: =AH95-I95 | X95: 44209 | Y95: V0015354 | AA95: បុគ្គលជាប់អាករ | AB95: L001-901905215 | AC95: វីអ៊ីស៊ិន (ខេមបូឌា) អ៊ិនដាសស្ទ្រី ឯ.ក | AD95: 4809098 | AE95: 4371907 | AF95: 0 | AG95: 0 | AH95: 437191 | AI95: 0 | AJ95: 0 | AK95: 0 | AL95: 0 | AM95: 0 | AN95: 0 | AO95: 0 | AP95: 0 | AS95: បានប្រកាសពន្ធ
A96: 88 | C96: ស៊ីងហ្គាពួរ កាតុង (ខេមបូឌា) | D96: L001-100121322 | E96: V0015353 | F96: 44209 | G96: 874637 | I96: 874637 | J96: =IF(AND(S96=TRUE, T96=TRUE, U96=TRUE), IF(W96<-0.05, "អនុញ្ញាត (អ្នកផ្គត់ផ្គង់ប្រកាសខ្វះ)", "បានប្រកាស (អនុញ្ញាត)"), IF(AND(S96=FALSE, T96=FALSE, U96=FALSE), "ព្យួរទុក (មិនមានទិន្នន័យ)", "ប្រកាសខុស (ព្យួរទុក)")) | N96: =IF(W96<0,AH96,I96) | O96: =I96-M96 | Q96: V0015353 | R96: V0015353 | S96: =Q96=R96 | T96: =AND(MONTH(F96)=MONTH(X96), YEAR(F96)=YEAR(X96)) | U96: =AND(AB96<>"", 'Company information'!D$4<>"", RIGHT(SUBSTITUTE(AB96,"-",""),9)=RIGHT(SUBSTITUTE('Company information'!D$4,"-",""),9)) | V96: =AH96-I96 | X96: 44209 | Y96: V0015353 | AA96: បុគ្គលជាប់អាករ | AB96: L001-901905215 | AC96: វីអ៊ីស៊ិន (ខេមបូឌា) អ៊ិនដាសស្ទ្រី ឯ.ក | AD96: 9649497 | AE96: 8772270 | AF96: 0 | AG96: 0 | AH96: 877227 | AI96: 0 | AJ96: 0 | AK96: 0 | AL96: 0 | AM96: 0 | AN96: 0 | AO96: 0 | AP96: 0 | AS96: បានប្រកាសពន្ធ
A97: 89 | C97: ស៊ីងហ្គាពួរ កាតុង (ខេមបូឌា) | D97: L001-100121322 | E97: V0015352 | F97: 44209 | G97: 351917 | I97: 351917 | J97: =IF(AND(S97=TRUE, T97=TRUE, U97=TRUE), IF(W97<-0.05, "អនុញ្ញាត (អ្នកផ្គត់ផ្គង់ប្រកាសខ្វះ)", "បានប្រកាស (អនុញ្ញាត)"), IF(AND(S97=FALSE, T97=FALSE, U97=FALSE), "ព្យួរទុក (មិនមានទិន្នន័យ)", "ប្រកាសខុស (ព្យួរទុក)")) | N97: =IF(W97<0,AH97,I97) | O97: =I97-M97 | Q97: V0015352 | R97: V0015352 | S97: =Q97=R97 | T97: =AND(MONTH(F97)=MONTH(X97), YEAR(F97)=YEAR(X97)) | U97: =AND(AB97<>"", 'Company information'!D$4<>"", RIGHT(SUBSTITUTE(AB97,"-",""),9)=RIGHT(SUBSTITUTE('Company information'!D$4,"-",""),9)) | V97: =AH97-I97 | X97: 44209 | Y97: V0015352 | AA97: បុគ្គលជាប់អាករ | AB97: L001-901905215 | AC97: វីអ៊ីស៊ិន (ខេមបូឌា) អ៊ិនដាសស្ទ្រី ឯ.ក | AD97: 3882563 | AE97: 3529603 | AF97: 0 | AG97: 0 | AH97: 352960 | AI97: 0 | AJ97: 0 | AK97: 0 | AL97: 0 | AM97: 0 | AN97: 0 | AO97: 0 | AP97: 0 | AS97: បានប្រកាសពន្ធ
A98: 90 | C98: ស៊ីងហ្គាពួរ កាតុង (ខេមបូឌា) | D98: L001-100121322 | E98: V00115351 | F98: 44209 | G98: 47534 | I98: 47534 | J98: =IF(AND(S98=TRUE, T98=TRUE, U98=TRUE), IF(W98<-0.05, "អនុញ្ញាត (អ្នកផ្គត់ផ្គង់ប្រកាសខ្វះ)", "បានប្រកាស (អនុញ្ញាត)"), IF(AND(S98=FALSE, T98=FALSE, U98=FALSE), "ព្យួរទុក (មិនមានទិន្នន័យ)", "ប្រកាសខុស (ព្យួរទុក)")) | N98: =IF(W98<0,AH98,I98) | O98: =I98-M98 | Q98: V00115351 | S98: =Q98=R98 | T98: =AND(MONTH(F98)=MONTH(X98), YEAR(F98)=YEAR(X98)) | U98: =AND(AB98<>"", 'Company information'!D$4<>"", RIGHT(SUBSTITUTE(AB98,"-",""),9)=RIGHT(SUBSTITUTE('Company information'!D$4,"-",""),9)) | V98: =AH98-I98
A99: 91 | C99: ស៊ីងហ្គាពួរ កាតុង (ខេមបូឌា) | D99: L001-100121322 | E99: V0015281 | F99: 44348 | G99: 97685 | I99: 97685 | J99: =IF(AND(S99=TRUE, T99=TRUE, U99=TRUE), IF(W99<-0.05, "អនុញ្ញាត (អ្នកផ្គត់ផ្គង់ប្រកាសខ្វះ)", "បានប្រកាស (អនុញ្ញាត)"), IF(AND(S99=FALSE, T99=FALSE, U99=FALSE), "ព្យួរទុក (មិនមានទិន្នន័យ)", "ប្រកាសខុស (ព្យួរទុក)")) | N99: =IF(W99<0,AH99,I99) | O99: =I99-M99 | Q99: V0015281 | R99: V0015281 | S99: =Q99=R99 | T99: =AND(MONTH(F99)=MONTH(X99), YEAR(F99)=YEAR(X99)) | U99: =AND(AB99<>"", 'Company information'!D$4<>"", RIGHT(SUBSTITUTE(AB99,"-",""),9)=RIGHT(SUBSTITUTE('Company information'!D$4,"-",""),9)) | V99: =AH99-I99 | X99: 44202 | Y99: V0015281 | AA99: បុគ្គលជាប់អាករ | AB99: L001-901905215 | AC99: វីអ៊ីស៊ិន (ខេមបូឌា) អ៊ិនដាសស្ទ្រី ឯ.ក | AD99: 1077184 | AE99: 979258 | AF99: 0 | AG99: 0 | AH99: 97926 | AI99: 0 | AJ99: 0 | AK99: 0 | AL99: 0 | AM99: 0 | AN99: 0 | AO99: 0 | AP99: 0 | AS99: បានប្រកាសពន្ធ
A100: 92 | C100: ស៊ីងហ្គាពួរ កាតុង (ខេមបូឌា) | D100: L001-100121322 | E100: V0015272 | F100: 44317 | G100: 504848 | I100: 504848 | J100: =IF(AND(S100=TRUE, T100=TRUE, U100=TRUE), IF(W100<-0.05, "អនុញ្ញាត (អ្នកផ្គត់ផ្គង់ប្រកាសខ្វះ)", "បានប្រកាស (អនុញ្ញាត)"), IF(AND(S100=FALSE, T100=FALSE, U100=FALSE), "ព្យួរទុក (មិនមានទិន្នន័យ)", "ប្រកាសខុស (ព្យួរទុក)")) | N100: =IF(W100<0,AH100,I100) | O100: =I100-M100 | Q100: V0015272 | R100: V0015272 | S100: =Q100=R100 | T100: =AND(MONTH(F100)=MONTH(X100), YEAR(F100)=YEAR(X100)) | U100: =AND(AB100<>"", 'Company information'!D$4<>"", RIGHT(SUBSTITUTE(AB100,"-",""),9)=RIGHT(SUBSTITUTE('Company information'!D$4,"-",""),9)) | V100: =AH100-I100 | X100: 44201 | Y100: V0015272 | AA100: បុគ្គលជាប់អាករ | AB100: L001-901905215 | AC100: វីអ៊ីស៊ិន (ខេមបូឌា) អ៊ិនដាសស្ទ្រី ឯ.ក | AD100: 5567018 | AE100: 5060925 | AF100: 0 | AG100: 0 | AH100: 506093 | AI100: 0 | AJ100: 0 | AK100: 0 | AL100: 0 | AM100: 0 | AN100: 0 | AO100: 0 | AP100: 0 | AS100: បានប្រកាសពន្ធ
A101: 93 | C101: ស៊ីងហ្គាពួរ កាតុង (ខេមបូឌា) | D101: L001-100121322 | E101: V0015263 | F101: 44317 | G101: 620794 | I101: 620794 | J101: =IF(AND(S101=TRUE, T101=TRUE, U101=TRUE), IF(W101<-0.05, "អនុញ្ញាត (អ្នកផ្គត់ផ្គង់ប្រកាសខ្វះ)", "បានប្រកាស (អនុញ្ញាត)"), IF(AND(S101=FALSE, T101=FALSE, U101=FALSE), "ព្យួរទុក (មិនមានទិន្នន័យ)", "ប្រកាសខុស (ព្យួរទុក)")) | N101: =IF(W101<0,AH101,I101) | O101: =I101-M101 | Q101: V0015263 | R101: V0015263 | S101: =Q101=R101 | T101: =AND(MONTH(F101)=MONTH(X101), YEAR(F101)=YEAR(X101)) | U101: =AND(AB101<>"", 'Company information'!D$4<>"", RIGHT(SUBSTITUTE(AB101,"-",""),9)=RIGHT(SUBSTITUTE('Company information'!D$4,"-",""),9)) | V101: =AH101-I101 | X101: 44201 | Y101: V0015263 | AA101: បុគ្គលជាប់អាករ | AB101: L001-901905215 | AC101: វីអ៊ីស៊ិន (ខេមបូឌា) អ៊ិនដាសស្ទ្រី ឯ.ក | AD101: 6845582 | AE101: 6223256 | AF101: 0 | AG101: 0 | AH101: 622326 | AI101: 0 | AJ101: 0 | AK101: 0 | AL101: 0 | AM101: 0 | AN101: 0 | AO101: 0 | AP101: 0 | AS101: បានប្រកាសពន្ធ
A102: 94 | C102: ស៊ីងហ្គាពួរ កាតុង (ខេមបូឌា) | D102: L001-100121322 | E102: V0015254 | F102: 44287 | G102: 466560 | I102: 466560 | J102: =IF(AND(S102=TRUE, T102=TRUE, U102=TRUE), IF(W102<-0.05, "អនុញ្ញាត (អ្នកផ្គត់ផ្គង់ប្រកាសខ្វះ)", "បានប្រកាស (អនុញ្ញាត)"), IF(AND(S102=FALSE, T102=FALSE, U102=FALSE), "ព្យួរទុក (មិនមានទិន្នន័យ)", "ប្រកាសខុស (ព្យួរទុក)")) | N102: =IF(W102<0,AH102,I102) | O102: =I102-M102 | Q102: V0015254 | R102: V0015254 | S102: =Q102=R102 | T102: =AND(MONTH(F102)=MONTH(X102), YEAR(F102)=YEAR(X102)) | U102: =AND(AB102<>"", 'Company information'!D$4<>"", RIGHT(SUBSTITUTE(AB102,"-",""),9)=RIGHT(SUBSTITUTE('Company information'!D$4,"-",""),9)) | V102: =AH102-I102 | X102: 44200 | Y102: V0015254 | AA102: បុគ្គលជាប់អាករ | AB102: L001-901905215 | AC102: វីអ៊ីស៊ិន (ខេមបូឌា) អ៊ិនដាសស្ទ្រី ឯ.ក | AD102: 5151168 | AE102: 4682880 | AF102: 0 | AG102: 0 | AH102: 468288 | AI102: 0 | AJ102: 0 | AK102: 0 | AL102: 0 | AM102: 0 | AN102: 0 | AO102: 0 | AP102: 0 | AS102: បានប្រកាសពន្ធ
A103: 95 | C103: ស៊ីងហ្គាពួរ កាតុង (ខេមបូឌា) | D103: L001-100121322 | E103: V0015253 | F103: 44287 | G103: 355226 | I103: 355226 | J103: =IF(AND(S103=TRUE, T103=TRUE, U103=TRUE), IF(W103<-0.05, "អនុញ្ញាត (អ្នកផ្គត់ផ្គង់ប្រកាសខ្វះ)", "បានប្រកាស (អនុញ្ញាត)"), IF(AND(S103=FALSE, T103=FALSE, U103=FALSE), "ព្យួរទុក (មិនមានទិន្នន័យ)", "ប្រកាសខុស (ព្យួរទុក)")) | N103: =IF(W103<0,AH103,I103) | O103: =I103-M103 | Q103: V0015253 | R103: V0015253 | S103: =Q103=R103 | T103: =AND(MONTH(F103)=MONTH(X103), YEAR(F103)=YEAR(X103)) | U103: =AND(AB103<>"", 'Company information'!D$4<>"", RIGHT(SUBSTITUTE(AB103,"-",""),9)=RIGHT(SUBSTITUTE('Company information'!D$4,"-",""),9)) | V103: =AH103-I103 | X103: 44200 | Y103: V0015253 | AA103: បុគ្គលជាប់អាករ | AB103: L001-901905215 | AC103: វីអ៊ីស៊ិន (ខេមបូឌា) អ៊ិនដាសស្ទ្រី ឯ.ក | AD103: 3921953 | AE103: 3565412 | AF103: 0 | AG103: 0 | AH103: 356541 | AI103: 0 | AJ103: 0 | AK103: 0 | AL103: 0 | AM103: 0 | AN103: 0 | AO103: 0 | AP103: 0 | AS103: បានប្រកាសពន្ធ
A104: 96 | C104: កំពង់ផែស្វយ័តក្រុងព្រះសីហនុ | D104: L001-100044638 | E104: 004382 | F104: 44440 | G104: 6075 | I104: 6075 | J104: =IF(AND(S104=TRUE, T104=TRUE, U104=TRUE), IF(W104<-0.05, "អនុញ្ញាត (អ្នកផ្គត់ផ្គង់ប្រកាសខ្វះ)", "បានប្រកាស (អនុញ្ញាត)"), IF(AND(S104=FALSE, T104=FALSE, U104=FALSE), "ព្យួរទុក (មិនមានទិន្នន័យ)", "ប្រកាសខុស (ព្យួរទុក)")) | N104: =IF(W104<0,AH104,I104) | O104: =I104-M104 | Q104: 004382 | S104: =Q104=R104 | T104: =AND(MONTH(F104)=MONTH(X104), YEAR(F104)=YEAR(X104)) | U104: =AND(AB104<>"", 'Company information'!D$4<>"", RIGHT(SUBSTITUTE(AB104,"-",""),9)=RIGHT(SUBSTITUTE('Company information'!D$4,"-",""),9)) | V104: =AH104-I104
...

Sheet Annex IV-EX
A1: តារាងឧបសម្ព័ន្ធ IV
A2: បញ្ជាក់អំពីការលក់
A3: (ការនាំចេញ/លក់បន្ទុករដ្ឋ/លក់តាមអត្រា០%)
A4: ក្រុមហ៊ុន៖ | B4: ='Company information'!D2 | D4: សវនករពន្ធដារ៖ | E4: ='Company information'!D8
A5: លេខ អតប ៖ | B5: ='Company information'!D4 | E5: ='Company information'!E8
A6: ='Company information'!E8 | D6: ទឹកប្រាក់ស្នើសុំបង្វិលសងចំនួន៖ | E6: ='Company information'!H9
A7: ល.រ | B7: បរិយាយ | C7: ប្រតិវេទន៍គយនាំចេញ/វិក្កយបត្រ | E7: តម្លៃជារៀល
C8: លេខ | D8: ចុះថ្ងៃទី ខែ ឆ្នាំ
A9: 1 | B9: សេវាកម្មកាត់ដេរ Garment Service | C9: ACL-20230004 | D9: 45291 | E9: 581845
A10: 2 | B10: នាំចេញសំលៀកបំពាក់ | C10: PFA240512 | D10: 45407 | E10: 74373
A11: 3 | B11: នាំចេញសំលៀកបំពាក់ | C11: PFA240425 | D11: 45385 | E11: 581845
A12: 4 | B12: សេវាកម្មកាត់ដេរ | C12: ACLCMT-20240009 | D12: 45412 | E12: 581845
A13: 5 | B13: សេវាកម្មកាត់ដេរ | C13: ACLCMT-20240007 | D13: 45412 | E13: 99936
A14: 6 | B14: សេវាកម្មកាត់ដេរ | C14: ACLCMT-20240048 | D14: 45443 | E14: 74982
A15: 7 | B15: នាំចេញសំលៀកបំពាក់ | C15: E15445 | D15: 45442 | E15: 74982
A16: 8 | B16: សេវាកម្មកាត់ដេរ | C16: ACLCMT-20240068 | D16: 45471 | E16: 74982
A17: 9 | B17: នាំចេញសំលៀកបំពាក់ | C17: E103463 | D17: 45451 | E17: 74982
A18: 10 | B18: នាំចេញសំលៀកបំពាក់ | C18: E97797 | D18: 45444 | E18: 74982
A19: 11 | B19: សេវាកម្មកាត់ដេរ | C19: ACLCMT-20240168 | D19: 45504 | E19: 74982
A20: 12 | B20: សេវាកម្មកាត់ដេរ | C20: ACLCMT-20240121 | D20: 45504 | E20: 117455
... A22: 14 | B22: នាំចេញសំលៀកបំពាក់ | C22: E139173 | D22: 45495 | E22: 117455
A23: សរុបការនាំចេញ | E23: =SUM(E9:E22)
D25: រាជធានីភ្នំពេញ.ថ្ងៃទី ខែ ឆ្នាំ
D26: មន្ត្រីសវនកម្ម
D28: ='Company information'!D9 | E28: ='Company information'!E9

Sheet Annex V-Local Sale
A1: តារាងឧបសម្ព័ន្ធ V
A2: បញ្ជាក់អំពីអាករលើធាតុចេញ
A3: ( ការលក់ក្នុងស្រុក )
A4: ក្រុមហ៊ុន៖ | B4: ='Company information'!D2 | G4: សវនករពន្ធដារ៖ | H4: ='Company information'!D8
A5: លេខ អតប ៖ | B5: ='Company information'!D4 | H5: ='Company information'!E8
A6: ='Company information'!E8 | F6: ទឹកប្រាក់ស្នើសុំបង្វិលសងចំនួន៖ | H6: ='Company information'!H9
A7: ល.រ | B7: បរិយាយ | C7: វិក្កយបត្រ | E7: អាករតម្លៃ (ដុល្លា) | F7: អត្រាប្តូរប្រាក់ | G7: អាករតម្លៃ (រៀល) | H7: ផ្សេងៗ
C8: លេខ | D8: ថ្ងៃ ខែ ឆ្នាំ
A9: 1 | B9: លក់កាកសំណល់អេតចាយ - Sale Scrap | C9: ACL-20240002 | D9: 45314 | G9: 581845
A10: 2 | B10: លក់កាកសំណល់អេតចាយ - Sale Scrap | C10: ACL-20240001 | D10: 45314 | G10: 100136
A11: 3 | B11: លក់កាកសំណល់អេតចាយ - Sale Scrap | C11: ACL-20240004 | D11: 45341 | G11: 155245
A12: 4 | B12: លក់កាកសំណល់អេតចាយ - Sale Scrap | C12: ACL-20240012 | D12: 45373 | G12: 74982
A13: 5 | B13: លក់កាកសំណល់អេតចាយ - Sale Scrap | C13: ACL-20240011 | D13: 45356 | G13: 99936
A14: 6 | B14: លក់កាកសំណល់អេតចាយ - Sale Scrap | C14: ACL-20240010 | D14: 45356 | G14: 74373
A15: 7 | B15: សេវាកម្មកាត់ដេរ | C15: ACL-20240018 | D15: 45412 | G15: 6885857
A16: 8 | B16: លក់កាកសំណល់អេតចាយ-Sale Scrap | C16: ACL-20240017 | D16: 45412 | G16: 65291
A17: 9 | B17: លក់កាកសំណល់អេតចាយ-Sale Scrap | C17: ACL-20240022 | D17: 45470 | G17: 4482
A18: 10 | B18: លក់កាកសំណល់អេតចាយ-Sale Scrap | C18: ACL-20240025 | D18: 45503 | G18: 117455
A19: 11 | B19: លក់កាកសំណល់អេតចាយ-Sale Scrap | C19: ACL-20240029 | D19: 45534 | G19: 394691
A20: 12 | B20: លក់កាកសំណល់អេតចាយ-Sale Scrap | C20: ACL-20240026 | D20: 45510 | G20: 250215
... A22: 14 | B22: លក់កាកសំណល់អេតចាយ-Sale Scrap | C22: ACL-20240030 | D22: 45600 | G22: 290909
A23: សរុបការលក់ក្នុងស្រុក | G23: =SUM(G9:G22)
G25: រាជធានីភ្នំពេញ.ថ្ងៃទី ខែ ឆ្នាំ
G26: មន្ត្រីសវនកម្ម
G28: ='Company information'!D9 | H28: ='Company information'!E9

Sheet Taxpaid
C4: ='Company information'!D7
B5: ល.រ | C5: ប្រភេទពន្ធ | D5: ចំនួនទឹកប្រាក់ពន្ធ | E5: Jan-2023 | F5: Feb-2023 | G5: Mar-2023 | H5: Apr-2023 | I5: May-2023 | J5: Jun-2023 | K5: Jul-2023 | L5: Aug-2023 | M5: Sep-2023 | N5: Oct-2023 | O5: Nov-2023 | P5: Dec-2023 | Q5: Jan-2024 | R5: Feb-2024 | S5: Mar-2024 | T5: Apr-2024 | U5: May-2024 | V5: Jun-2024 | W5: Jul-2024 | X5: Aug-2024 | Y5: Sep-2024 | Z5: Oct-2024 | AA5: Nov-2024 | AB5: Dec-2024
B6: 1 | C6: ពន្ធប៉ាតង់ | D6: =SUM(E6:AB6) | E6: 0 | F6: 0 | G6: 0 | H6: 0 | I6: 0 | J6: 0 | K6: 0 | L6: 1500000 | M6: 0 | N6: 0 | O6: 0 | P6: 0 | Q6: 0 | R6: 0 | S6: 3000000 | T6: 0 | U6: 0 | V6: 0 | W6: 0 | X6: 0 | Y6: 0 | Z6: 0 | AA6: 0 | AB6: 0
B7: 2 | C7: កម្រៃសេវាចុះបញ្ជី ឬធ្វើបច្ចុប្បន្នភាព | D7: =SUM(E7:AB7) | E7: 0 | F7: 0 | G7: 0 | H7: 0 | I7: 0 | J7: 0 | K7: 0 | L7: 400000 | M7: 0 | N7: 0 | O7: 0 | P7: 0 | Q7: 0 | R7: 0 | S7: 0 | T7: 0 | U7: 0 | V7: 0 | W7: 0 | X7: 0 | Y7: 0 | Z7: 0 | AA7: 200000 | AB7: 0
B8: 3 | C8: ពន្ធលើប្រាក់បៀវត្ស | D8: =SUM(E8:AB8) | E8: 0 | F8: 0 | G8: 0 | H8: 0 | I8: 0 | J8: 0 | K8: 0 | L8: 0 | M8: 14745919 | N8: 17256700 | O8: 16645636 | P8: 17303541 | Q8: 15943205 | R8: 16907178 | S8: 18095811 | T8: 18473483 | U8: 19887604 | V8: 21319783 | W8: 21197056 | X8: 23579307 | Y8: 21157605 | Z8: 31898419 | AA8: 36331895 | AB8: 0
B9: 4 | C9: ពន្ធលើអត្ថប្រយោជន៍បន្ថែម | D9: =SUM(E9:AB9) | E9: 0 | F9: 0 | G9: 0 | H9: 0 | I9: 0 | J9: 0 | K9: 0 | L9: 0 | M9: 0 | N9: 3416033 | O9: 2893088 | P9: 11751147 | Q9: 9486163 | R9: 4889241 | S9: 4916054 | T9: 6439288 | U9: 13906169 | V9: 10494263 | W9: 8379089 | X9: 8881572 | Y9: 10415723 | Z9: 5148907 | AA9: 11905492 | AB9: 0
B10: 5 | C10: ប្រាក់រំដោះពន្ធលើប្រាក់ចំណូល | D10: =SUM(E10:AB10) | E10: 0 | F10: 0 | G10: 0 | H10: 0 | I10: 0 | J10: 0 | K10: 0 | L10: 0 | M10: 0 | N10: 0 | O10: 0 | P10: 0 | Q10: 0 | R10: 0 | S10: 0 | T10: 0 | U10: 0 | V10: 0 | W10: 0 | X10: 0 | Y10: 0 | Z10: 0 | AA10: 0 | AB10: 0
B11: 6 | C11: ពន្ធលើប្រាក់ចំណូលប្រចាំឆ្នាំ | D11: =SUM(E11:AB11) | E11: 0 | F11: 0 | G11: 0 | H11: 0 | I11: 0 | J11: 0 | K11: 0 | L11: 0 | M11: 0 | N11: 0 | O11: 0 | P11: 0 | Q11: 0 | R11: 0 | S11: 0 | T11: 0 | U11: 0 | V11: 0 | W11: 0 | X11: 0 | Y11: 0 | Z11: 0 | AA11: 0 | AB11: 0
B12: 7 | C12: ពន្ធកាត់ទុកលើសេវាកម្ម ១៥% | D12: =SUM(E12:AB12) | E12: 0 | F12: 0 | G12: 0 | H12: 0 | I12: 0 | J12: 0 | K12: 0 | L12: 0 | M12: 0 | N12: 4738214 | O12: 1874218 | P12: 6088836 | Q12: 3880332 | R12: 4292372 | S12: 15258802 | T12: 10939010 | U12: 11238999 | V12: 7855100 | W12: 18447624 | X12: 24896291 | Y12: 23057495 | Z12: 17486099 | AA12: 14246633 | AB12: 0
B13: 8 | C13: ពន្ធកាត់ទុកលើថ្លៃឈ្នួល (រូបវន្ដបុគ្គល) | D13: =SUM(E13:AB13) | E13: 0 | F13: 0 | G13: 0 | H13: 0 | I13: 0 | J13: 0 | K13: 0 | L13: 0 | M13: 0 | N13: 186075 | O13: 185175 | P13: 31209809 | Q13: 4699329 | R13: 6782616 | S13: 6735943 | T13: 6774282 | U13: 6822622 | V13: 7536055 | W13: 6847625 | X13: 6762613 | Y13: 6769281 | Z13: 6772615 | AA13: 6714273 | AB13: 0
B14: 9 | C14: អាករលើតម្លៃបន្ថែម | D14: =SUM(E14:AB14) | E14: 0 | F14: 0 | G14: 0 | H14: 0 | I14: 0 | J14: 0 | K14: 0 | L14: 0 | M14: 0 | N14: 0 | O14: 0 | P14: 0 | Q14: 0 | R14: 241601 | S14: 18911 | T14: 0 | U14: 19155 | V14: 21157 | W14: 19225 | X14: 18986 | Y14: 38011 | Z14: 19014 | AA14: 18851 | AB14: 0
B15: 10 | C15: អាករពិសេសលើទំនិញមួយចំនួន | D15: =SUM(E15:AB15) | E15: 0 | F15: 0 | G15: 0 | H15: 0 | I15: 0 | J15: 0 | K15: 0 | L15: 0 | M15: 0 | N15: 0 | O15: 0 | P15: 0 | Q15: 0 | R15: 0 | S15: 0 | T15: 0 | U15: 0 | V15: 0 | W15: 0 | X15: 0 | Y15: 0 | Z15: 0 | AA15: 0 | AB15: 0
B16: 11 | C16: អាករពិសេសលើសេវាមួយចំនួន | D16: =SUM(E16:AB16) | E16: 0 | F16: 0 | G16: 0 | H16: 0 | I16: 0 | J16: 0 | K16: 0 | L16: 0 | M16: 0 | N16: 0 | O16: 0 | P16: 0 | Q16: 0 | R16: 0 | S16: 0 | T16: 0 | U16: 0 | V16: 0 | W16: 0 | X16: 0 | Y16: 0 | Z16: 0 | AA16: 0 | AB16: 0
B17: 12 | C17: អាករសម្រាប់បំភ្លឺសាធារណៈ | D17: =SUM(E17:AB17) | E17: 0 | F17: 0 | G17: 0 | H17: 0 | I17: 0 | J17: 0 | K17: 0 | L17: 0 | M17: 0 | N17: 0 | O17: 0 | P17: 0 | Q17: 0 | R17: 0 | S17: 0 | T17: 0 | U17: 0 | V17: 0 | W17: 0 | X17: 0 | Y17: 0 | Z17: 0 | AA17: 0 | AB17: 0
... B20: 15 | C20: ពន្ធកាត់ទុកលើការប្រាក់ ១៥% | D20: =SUM(E20:AB20) | E20: 0 | F20: 0 | G20: 0 | H20: 0 | I20: 0 | J20: 0 | K20: 0 | L20: 0 | M20: 0 | N20: 0 | O20: 0 | P20: 0 | Q20: 0 | R20: 0 | S20: 542353 | T20: 0 | U20: 0 | V20: 0 | W20: 0 | X20: 25166817 | Y20: 27019415 | Z20: 0 | AA20: 0 | AB20: 0
C21: សរុបទឹកប្រាក់ពន្ធបានបង់ចូលរដ្ឋ | D21: =SUM(D6:D20)

Sheet Damco
A1: តារាងឧបសម្ព័ន្ឋ
A2: តារាងប្រៀធៀបវិក្ក័យប័ត្រស្នើសុំបង្វិលសងអាករលើតំលៃបន្ថែម ( Cross checking )
A3: ='Annex I-IM State Charge'!#REF!
A4: ='Annex I-IM State Charge'!#REF!
A5: ល.រ | B5: ក្រុមហ៊ុនស្នើសុំបង្វិលសង | E5: អ្នកផ្គត់ផ្គង់ | J5: ផ្សេងៗ
B6: វិក្កយបត្រ | E6: សហគ្រាស | F6: លេខអតប | G6: វិក្កយបត្រ
B7: លេខ | C7: ថ្ងៃទី ខែ ឆ្នាំ | D7: ប្រាក់អាករ | G7: លេខ | H7: ថ្ងៃទី ខែ ឆ្នាំ | I7: ប្រាក់អាករ
A8: 1 | B8: 030209 | C8: 41246 | D8: 58.25 | E8: A P L Logistics | F8: 100046460 | G8: 030209 | H8: 41246 | I8: 58.25 | J8: បានបង់
A9: 2 | B9: 030231 | C9: 41248 | D9: 4 | E9: A P L Logistics | F9: 100046460 | G9: 030231 | H9: 41248 | I9: 4 | J9: បានបង់
A10: 3 | B10: 030241 | C10: 41254 | D10: 49.75 | E10: A P L Logistics | F10: 100046460 | G10: 030241 | H10: 41254 | I10: 49.75 | J10: បានបង់
A11: 4 | B11: 030262 | C11: 41254 | D11: 181.79 | E11: A P L Logistics | F11: 100046460 | G11: 030262 | H11: 41254 | I11: 181.79 | J11: បានបង់
A12: 5 | B12: 030302 | C12: 41260 | D12: 46.69 | E12: A P L Logistics | F12: 100046460 | G12: 030302 | H12: 41260 | I12: 46.69 | J12: បានបង់
A13: 6 | B13: 030328 | C13: 41260 | D13: 236.64 | E13: A P L Logistics | F13: 100046460 | G13: 030328 | H13: 41260 | I13: 236.64 | J13: បានបង់
A14: 7 | B14: 030343 | C14: 41261 | D14: 4 | E14: A P L Logistics | F14: 100046460 | G14: 030343 | H14: 41261 | I14: 4 | J14: បានបង់
A15: 8 | B15: 030353 | C15: 41261 | D15: 10 | E15: A P L Logistics | F15: 100046460 | G15: 030353 | H15: 41261 | I15: 10 | J15: បានបង់
A16: 9 | B16: 030450 | C16: 41274 | D16: 87.52 | E16: A P L Logistics | F16: 100046460 | G16: 030450 | H16: 41274 | I16: 87.52 | J16: បានបង់
A17: 10 | B17: 030469 | C17: 41274 | D17: 39.29 | E17: A P L Logistics | F17: 100046460 | G17: 030469 | H17: 41274 | I17: 39.29 | J17: បានបង់
A18: Total 12/2012 | D18: =SUM(D8:D17) | H18: USD | I18: =SUM(I8:I17)
A19: Total 12/2012 | G19: 3995 | H19: RIEL | I19: =I18*G19
A20: 1 | B20: 029920 | C20: 41218 | D20: 77 | E20: A P L Logistics | F20: 100046460 | G20: 029920 | H20: 41218 | I20: 77 | J20: បានបង់
A21: 2 | B21: 029981 | C21: 41225 | D21: 115.89 | E21: A P L Logistics | F21: 100046460 | G21: 029981 | H21: 41225 | I21: 115.89 | J21: បានបង់
A22: 3 | B22: 030003 | C22: 41225 | D22: 82.91 | E22: A P L Logistics | F22: 100046460 | G22: 030003 | H22: 41225 | I22: 82.91 | J22: បានបង់
A23: 4 | B23: 030044 | C23: 41232 | D23: 55.32 | E23: A P L Logistics | F23: 100046460 | G23: 030044 | H23: 41232 | I23: 55.32 | J23: បានបង់
A24: 5 | B24: 030062 | C24: 41232 | D24: 32.03 | E24: A P L Logistics | F24: 100046460 | G24: 030062 | H24: 41232 | I24: 32.03 | J24: បានបង់
A25: Total 11/2012 | D25: =SUM(D20:D24) | H25: USD | I25: =SUM(I20:I24)
A26: Total 11/2012 | G26: 3999 | H26: RIEL | I26: =I25*G26
A27: 1 | B27: 029638 | C27: 41183 | D27: 89.93 | E27: A P L Logistics | F27: 100046460 | G27: 029638 | H27: 41183 | I27: 89.93 | J27: បានបង់
A28: 2 | B28: 029716 | C28: 41190 | D28: 49.63 | E28: A P L Logistics | F28: 100046460 | G28: 029716 | H28: 41190 | I28: 49.63 | J28: បានបង់
A29: 3 | B29: 029766 | C29: 41197 | D29: 115.81 | E29: A P L Logistics | F29: 100046460 | G29: 029766 | H29: 41197 | I29: 115.81 | J29: បានបង់
A30: 4 | B30: 029816 | C30: 41204 | D30: 101.98 | E30: A P L Logistics | F30: 100046460 | G30: 029816 | H30: 41204 | I30: 101.98 | J30: បានបង់
A31: 5 | B31: 029869 | C31: 41211 | D31: 67.28 | E31: A P L Logistics | F31: 100046460 | G31: 029869 | H31: 41211 | I31: 67.28 | J31: បានបង់
A32: Total 10/2012 | D32: =SUM(D27:D31) | H32: USD | I32: =SUM(I27:I31)
A33: Total 10/2012 | G33: 4028 | H33: RIEL | I33: =I32*G33
A34: 1 | B34: 029426 | C34: 41162 | D34: 206.96 | E34: A P L Logistics | F34: 100046460 | G34: 029426 | H34: 41162 | I34: 206.96 | J34: បានបង់
A35: 2 | B35: 029501 | C35: 41169 | D35: 69.7 | E35: A P L Logistics | F35: 100046460 | G35: 029501 | H35: 41169 | I35: 69.7 | J35: បានបង់
A36: 3 | B36: 029565 | C36: 41176 | D36: 46.66 | E36: A P L Logistics | F36: 100046460 | G36: 029565 | H36: 41176 | I36: 46.66 | J36: បានបង់
A37: Total 09/2012 | D37: =SUM(D34:D36) | H37: USD | I37: =SUM(I34:I36)
A38: Total 09/2012 | G38: 4044 | H38: RIEL | I38: =I37*G38
A39: 1 | B39: 029026 | C39: 41127 | D39: 37.84 | E39: A P L Logistics | F39: 100046460 | G39: 029026 | H39: 41127 | I39: 37.84 | J39: បានបង់
A40: 2 | B40: 029107 | C40: 41134 | D40: 95.46 | E40: A P L Logistics | F40: 100046460 | G40: 029107 | H40: 41134 | I40: 95.46 | J40: បានបង់
A41: 3 | B41: 029223 | C41: 41141 | D41: 106.66 | E41: A P L Logistics | F41: 100046460 | G41: 029223 | H41: 41141 | I41: 106.66 | J41: បានបង់
A42: 4 | B42: 029278 | C42: 41148 | D42: 32.8 | E42: A P L Logistics | F42: 100046460 | G42: 029278 | H42: 41148 | I42: 32.8 | J42: បានបង់
A43: Total 08/2012 | D43: =SUM(D39:D42) | H43: USD | I43: =SUM(I39:I42)
A44: Total 08/2012 | G44: 4053 | H44: RIEL | I44: =I43*G44
A45: 1 | B45: 028640 | C45: 41092 | D45: 29.26 | E45: A P L Logistics | F45: 100046460 | G45: 028640 | H45: 41092 | I45: 29.26 | J45: បានបង់
A46: 2 | B46: 028709 | C46: 41099 | D46: 24.66 | E46: A P L Logistics | F46: 100046460 | G46: 028709 | H46: 41099 | I46: 24.66 | J46: បានបង់
A47: 3 | B47: 028809 | C47: 41106 | D47: 31.02 | E47: A P L Logistics | F47: 100046460 | G47: 028809 | H47: 41106 | I47: 31.02 | J47: បានបង់
A48: 4 | B48: 028874 | C48: 41113 | D48: 209.58 | E48: A P L Logistics | F48: 100046460 | G48: 028874 | H48: 41113 | I48: 209.58 | J48: បានបង់
A49: 5 | B49: 028550 | C49: 41115 | D49: 66.92 | E49: A P L Logistics | F49: 100046460 | G49: 028550 | H49: 41115 | I49: 66.92 | J49: បានបង់
A50: 6 | B50: 028948 | C50: 41120 | D50: 73.23 | E50: A P L Logistics | F50: 100046460 | G50: 028948 | H50: 41120 | I50: 73.23 | J50: បានបង់
A51: 7 | B51: 028961 | C51: 41120 | D51: 27.84 | E51: A P L Logistics | F51: 100046460 | G51: 028961 | H51: 41120 | I51: 27.84 | J51: បានបង់
A52: Total 07/2012 | D52: =SUM(D45:D51) | H52: USD | I52: =SUM(I45:I51)
A53: Total 07/2012 | G53: 4073 | H53: RIEL | I53: =I52*G53
A54: 1 | B54: 030377 | C54: 41267 | D54: 53.34 | E54: A P L Logistics | F54: 100046460 | G54: 030377 | H54: 41267 | I54: 53.34 | J54: បានបង់
A55: 2 | B55: 030407 | C55: 41267 | D55: 63.05 | E55: A P L Logistics | F55: 100046460 | G55: 030407 | H55: 41267 | I55: 63.05 | J55: បានបង់
A56: 3 | B56: 030516 | C56: 41281 | D56: 81 | E56: A P L Logistics | F56: 100046460 | G56: 030516 | H56: 41281 | I56: 81 | J56: បានបង់
A57: 4 | B57: 030532 | C57: 41281 | D57: 335.98 | E57: A P L Logistics | F57: 100046460 | G57: 030532 | H57: 41281 | I57: 335.98 | J57: បានបង់
A58: 5 | B58: 030562 | C58: 41282 | D58: 10 | E58: A P L Logistics | F58: 100046460 | G58: 030562 | H58: 41282 | I58: 10 | J58: បានបង់
A59: 6 | B59: 030586 | C59: 41285 | D59: 7.2 | E59: A P L Logistics | F59: 100046460 | G59: 030586 | H59: 41285 | I59: 7.2 | J59: បានបង់
A60: 7 | B60: 030614 | C60: 41286 | D60: 217.03 | E60: A P L Logistics | F60: 100046460 | G60: 030614 | H60: 41288 | I60: 217.03 | J60: បានបង់
A61: 8 | B61: 030638 | C61: 41289 | D61: 10 | E61: A P L Logistics | F61: 100046460 | G61: 030638 | H61: 41289 | I61: 10 | J61: បានបង់
A62: 9 | B62: 030758 | C62: 41296 | D62: 25.25 | E62: A P L Logistics | F62: 100046460 | G62: 030758 | H62: 41296 | I62: 25.25 | J62: បានបង់
A63: 10 | B63: 030848 | C63: 41302 | D63: 357.23 | E63: A P L Logistics | F63: 100046460 | G63: 030848 | H63: 41302 | I63: 357.23 | J63: បានបង់
A64: Total 01/2013 | D64: =SUM(D54:D63) | H64: USD | I64: =SUM(I54:I63)
A65: Total 01/2013 | G65: 3995 | H65: RIEL | I65: =I64*G65
A66: 1 | B66: 030891 | C66: 41310 | D66: 28.52 | E66: A P L Logistics | F66: 100046460 | G66: 030891 | H66: 41310 | I66: 28.52 | J66: បានបង់
A67: 2 | B67: 030911 | C67: 41310 | D67: 374.87 | E67: A P L Logistics | F67: 100046460 | G67: 030911 | H67: 41310 | I67: 374.87 | J67: បានបង់
A68: 3 | B68: 030965 | C68: 41312 | D68: 10 | E68: A P L Logistics | F68: 100046460 | G68: 030965 | H68: 41312 | I68: 10 | J68: បានបង់
A69: 4 | B69: 030999 | C69: 41316 | D69: 115 | E69: A P L Logistics | F69: 100046460 | G69: 030999 | H69: 41316 | I69: 115 | J69: បានបង់
A70: 5 | B70: 031026 | C70: 41317 | D70: 4 | E70: A P L Logistics | F70: 100046460 | G70: 031026 | H70: 41317 | I70: 4 | J70: បានបង់
A71: 6 | B71: 031069 | C71: 41323 | D71: 266.83 | E71: A P L Logistics | F71: 100046460 | G71: 031069 | H71: 41323 | I71: 266.83 | J71: បានបង់
A72: 7 | B72: 031108 | C72: 41326 | D72: 20 | E72: A P L Logistics | F72: 100046460 | G72: 031108 | H72: 41326 | I72: 20 | J72: បានបង់
A73: 8 | B73: 031138 | C73: 41331 | D73: 142.19 | E73: A P L Logistics | F73: 100046460 | G73: 031138 | H73: 41331 | I73: 142.19 | J73: បានបង់
A74: Total 02/2013 | D74: =SUM(D66:D73) | H74: USD | I74: =SUM(I66:I73)
A75: Total 02/2013 | G75: 3995 | H75: RIEL | I75: =I74*G75
A76: 1 | B76: 031210 | C76: 41337 | D76: 115.18 | E76: A P L Logistics | F76: 100046460 | G76: 031210 | H76: 41337 | I76: 115.18 | J76: បានបង់
A77: 2 | B77: 031195 | C77: 41337 | D77: 107.71 | E77: A P L Logistics | F77: 100046460 | G77: 031195 | H77: 41337 | I77: 107.71 | J77: បានបង់
A78: 3 | B78: 031383 | C78: 41344 | D78: 109.81 | E78: A P L Logistics | F78: 100046460 | G78: 031383 | H78: 41344 | I78: 109.81 | J78: បានបង់
A79: 4 | B79: 031454 | C79: 41351 | D79: 307.84 | E79: A P L Logistics | F79: 100046460 | G79: 031454 | H79: 41351 | I79: 307.84 | J79: បានបង់
A80: 5 | B80: 031507 | C80: 41354 | D80: 8 | E80: APL Logistics | F80: 100046460 | G80: 031507 | H80: 41354 | I80: 8 | J80: បានបង់
A81: 6 | B81: 031511 | C81: 41354 | D81: 10 | E81: APL Logistics | F81: 100046460 | G81: 031511 | H81: 41354 | I81: 10 | J81: បានបង់
A82: 7 | B82: 031543 | C82: 41358 | D82: 190.8 | E82: A P L Logistics | F82: 100046460 | G82: 031543 | H82: 41358 | I82: 190.8 | J82: បានបង់
A83: 8 | B83: 031588 | C83: 41360 | D83: 8 | E83: APL Logistics | F83: 100046460 | G83: 031588 | H83: 41360 | I83: 8 | J83: បានបង់
A84: 9 | B84: 031592 | C84: 41360 | D84: 10 | E84: APL Logistics | F84: 100046460 | G84: 031592 | H84: 41360 | I84: 10 | J84: បានបង់
A85: Total 03/2013 | D85: =SUM(D76:D84) | H85: USD | I85: =SUM(I76:I84)
A86: Total 03/2013 | G86: 3995 | H86: RIEL | I86: =I85*G86
A87: 1 | B87: 031616 | C87: 41365 | D87: 40.32 | E87: APL Logistics | F87: 100046460 | G87: 031616 | H87: 41365 | I87: 40.32 | J87: បានបង់
A88: 2 | B88: 031641 | C88: 41366 | D88: 168.98 | E88: A P L Logistics | F88: 100046460 | G88: 031641 | H88: 41366 | I88: 168.98 | J88: បានបង់
A89: 3 | B89: 031704 | C89: 41372 | D89: 104.23 | E89: A P L Logistics | F89: 100046460 | G89: 031704 | H89: 41372 | I89: 104.23 | J89: បានបង់
A90: 4 | B90: 031730 | C90: 41372 | D90: 222.39 | E90: A P L Logistics | F90: 100046460 | G90: 031730 | H90: 41372 | I90: 222.39 | J90: បានបង់
A91: 5 | B91: 031771 | C91: 41374 | D91: 10 | E91: APL Logistics | F91: 100046460 | G91: 031771 | H91: 41374 | I91: 10 | J91: បានបង់
A92: 6 | B92: 31799 | C92: 41382 | D92: 149.76 | E92: A P L Logistics | F92: 100046460 | G92: 31799 | H92: 41382 | I92: 149.76 | J92: បានបង់
A93: 7 | B93: 31883 | C93: 41386 | D93: 144.43 | E93: A P L Logistics | F93: 100046460 | G93: 31883 | H93: 41386 | I93: 144.43 | J93: បានបង់
A94: 8 | B94: 31901 | C94: 41387 | D94: 8 | E94: APL Logistics | F94: 100046460 | G94: 31901 | H94: 41387 | I94: 8 | J94: បានបង់
A95: 9 | B95: 031922 | C95: 41394 | D95: 134.76 | E95: A P L Logistics | F95: 100046460 | G95: 031922 | H95: 41394 | I95: 134.76 | J95: បានបង់
A96: 10 | B96: 31940 | C96: 41394 | D96: 155.38 | E96: A P L Logistics | F96: 100046460 | G96: 31940 | H96: 41394 | I96: 155.38 | J96: បានបង់
A97: Total 04/2013 | D97: =SUM(D87:D96) | H97: USD | I97: =SUM(I87:I96)
A98: Total 04/2013 | G98: 4000 | H98: RIEL | I98: =I97*G98
A99: 1 | B99: 031981 | C99: 41397 | D99: 20 | E99: APL Logistics | F99: 100046460 | G99: 031981 | H99: 41397 | I99: 20 | J99: បានបង់
A100: 2 | B100: 031984 | C100: 41400 | D100: 25 | E100: APL Logistics | F100: 100046460 | G100: 031984 | H100: 41400 | I100: 25 | J100: បានបង់
...

Sheet Chea Fat
A1: តារាងឧបសម្ព័ន្ឋ
A2: តារាងប្រៀធៀបវិក្ក័យប័ត្រស្នើសុំបង្វិលសងអាករលើតំលៃបន្ថែម ( Cross checking )
A3: នាមករណ៏សហគ្រាស : Maurea Garments Corp
A4: VAT TIN : 1 0 0 0 5 2 9 6 7
A5: ល.រ | B5: ក្រុមហ៊ុនស្នើសុំបង្វិលសង | E5: អ្នកផ្គត់ផ្គង់ | J5: ផ្សេងៗ
B6: វិក័យបត្រ័ | E6: សហគ្រាស | F6: លេខអតប | G6: វិក័យបត្រ័
B7: លេខ | C7: ថ្ងៃទី ខែ ឆ្នាំ | D7: ប្រាក់អាករ | G7: លេខ | H7: ថ្ងៃទី ខែ ឆ្នាំ | I7: ប្រាក់អាករ
A8: 1 | B8: 07-0360 | C8: 41842 | D8: 41.5 | E8: YUSEN LOGISTICS | F8: 104015799 | G8: 07-0360 | H8: 41842 | I8: 41.5
A9: 2 | B9: 07-0367 | C9: 41842 | D9: 64.57 | E9: YUSEN LOGISTICS | F9: 104015799 | G9: 07-0367 | H9: 41842 | I9: 64.57
A10: 3 | B10: 07-0368 | C10: 41842 | D10: 59.11 | E10: YUSEN LOGISTICS | F10: 104015799 | G10: 07-0368 | H10: 41842 | I10: 59.11
A11: 4 | B11: 07-0517 | C11: 41849 | D11: 75.93 | E11: YUSEN LOGISTICS | F11: 104015799 | G11: 07-0517 | H11: 41849 | I11: 75.93
A12: 5 | B12: 08-0039 | C12: 41856 | D12: 46.05 | E12: YUSEN LOGISTICS | F12: 104015799 | G12: 08-0039 | H12: 41856 | I12: 46.05
A13: 6 | B13: 08-0044 | C13: 41856 | D13: 41.5 | E13: YUSEN LOGISTICS | F13: 104015799 | G13: 08-0044 | H13: 41856 | I13: 41.5
A14: 7 | B14: 08-0185 | C14: 41864 | D14: 27.9 | E14: YUSEN LOGISTICS | F14: 104015799 | G14: 08-0185 | H14: 41864 | I14: 27.9
A15: 8 | B15: 08-0677 | C15: 41882 | D15: 143 | E15: YUSEN LOGISTICS | F15: 104015799 | G15: 08-0677 | H15: 41882 | I15: 143
A16: 9 | B16: 08-0685 | C16: 41882 | D16: 60.33 | E16: YUSEN LOGISTICS | F16: 104015799 | G16: 08-0685 | H16: 41882 | I16: 60.33
A17: 10 | B17: 09-0111 | C17: 41892 | D17: 27.53 | E17: YUSEN LOGISTICS | F17: 104015799 | G17: 09-0111 | H17: 41892 | I17: 27.53
A18: 11 | B18: 09-0117 | C18: 41892 | D18: 53.64 | E18: YUSEN LOGISTICS | F18: 104015799 | G18: 09-0117 | H18: 41892 | I18: 53.64
A19: 12 | B19: 09-0199 | C19: 41898 | D19: 34.77 | E19: YUSEN LOGISTICS | F19: 104015799 | G19: 09-0199 | H19: 41898 | I19: 34.77
... A40: 33 | B40: 502-0531 | C40: 42059 | D40: 102.92 | E40: YUSEN LOGISTICS | F40: 104015799 | G40: 502-0531 | H40: 42059 | I40: 102.92
A41: TOTAL 7/2012-02/2015 | D41: =SUM(D8:D40) | I41: =SUM(I8:I40)
E44: YUSEN LOGISTICS | F44: 104015799 | G44: 2-00309 | H44: 41619 | I44: 5

Sheet S G L CAMBODIA
A1: តារាងឧបសម្ព័ន្ឋ
A2: តារាងប្រៀធៀបវិក្ក័យប័ត្រស្នើសុំបង្វិលសងអាករលើតំលៃបន្ថែម ( Cross checking )
A3: នាមករណ៏សហគ្រាស : Maurea Garments Corp
A4: VAT TIN : 1 0 0 0 5 2 9 6 7
A5: ល.រ | B5: ក្រុមហ៊ុនស្នើសុំបង្វិលសង | E5: អ្នកផ្គត់ផ្គង់ | J5: ផ្សេងៗ
B6: វិក័យបត្រ័ | E6: សហគ្រាស | F6: លេខអតប | G6: វិក័យបត្រ័
B7: លេខ | C7: ថ្ងៃទី ខែ ឆ្នាំ | D7: ប្រាក់អាករ | G7: លេខ | H7: ថ្ងៃទី ខែ ឆ្នាំ | I7: ប្រាក់អាករ
A8: 1 | B8: 227231 | C8: 41246 | D8: 8.5 | E8: S G L CAMBODIA | F8: 100119816 | G8: 227231 | H8: 41246 | I8: 8.5
A9: 2 | B9: 227288 | C9: 41246 | D9: 52.36 | E9: S G L CAMBODIA | F9: 100119816 | G9: 227288 | H9: 41246 | I9: 52.36
A10: 3 | B10: 227430 | C10: 41255 | D10: 21.2 | E10: S G L CAMBODIA | F10: 100119816 | G10: 227430 | H10: 41255 | I10: 21.2
A11: 4 | B11: 227461 | C11: 41255 | D11: 29.57 | E11: S G L CAMBODIA | F11: 100119816 | G11: 227461 | H11: 41255 | I11: 29.57
A12: 5 | B12: 227539 | C12: 41260 | D12: 34.24 | E12: S G L CAMBODIA | F12: 100119816 | G12: 227539 | H12: 41260 | I12: 34.24
A13: 6 | B13: 227543 | C13: 41260 | D13: 8.93 | E13: S G L CAMBODIA | F13: 100119816 | G13: 227543 | H13: 41260 | I13: 8.93
A14: 7 | B14: 227552 | C14: 41260 | D14: 27.62 | E14: S G L CAMBODIA | F14: 100119816 | G14: 227552 | H14: 41260 | I14: 27.62
A15: 8 | B15: 227583 | C15: 41261 | D15: 57.77 | E15: S G L CAMBODIA | F15: 100119816 | G15: 227583 | H15: 41261 | I15: 57.77
A16: 9 | B16: 227586 | C16: 41261 | D16: 24 | E16: S G L CAMBODIA | F16: 100119816 | G16: 227586 | H16: 41261 | I16: 24
A17: 10 | B17: 227605 | C17: 41261 | D17: 28.88 | E17: S G L CAMBODIA | F17: 100119816 | G17: 227605 | H17: 41261 | I17: 28.88
A18: 11 | B18: 227826 | C18: 41274 | D18: 24 | E18: S G L CAMBODIA | F18: 100119816 | G18: 227826 | H18: 41274 | I18: 24
A19: 12 | B19: 227862 | C19: 41274 | D19: 36.26 | E19: S G L CAMBODIA | F19: 100119816 | G19: 227862 | H19: 41274 | I19: 36.26
... A458: 455 | B458: 443954 | C458: 42002 | D458: 44.24 | E458: S G L CAMBODIA | F458: 100119816 | G458: 443954 | H458: 42002 | I458: 44.24
A459: TOTAL 7/2012-02/2015 | D459: =SUM(D8:D458) | I459: =SUM(I8:I458)

Sheet Sheet3
A1: តារាងឧបសម្ព័ន្ឋ
A2: តារាងប្រៀធៀបវិក្ក័យប័ត្រស្នើសុំបង្វិលសងអាករលើតំលៃបន្ថែម ( Cross checking )
A3: នាមករណ៏សហគ្រាស : Maurea Garments Corp
A4: VAT TIN : 1 0 0 0 5 2 9 6 7
A5: ល.រ | B5: ក្រុមហ៊ុនស្នើសុំបង្វិលសង | E5: អ្នកផ្គត់ផ្គង់ | J5: ផ្សេងៗ
B6: វិក័យបត្រ័ | E6: សហគ្រាស | F6: លេខអតប | G6: វិក័យបត្រ័
B7: លេខ | C7: ថ្ងៃទី ខែ ឆ្នាំ | D7: ប្រាក់អាករ | G7: លេខ | H7: ថ្ងៃទី ខែ ឆ្នាំ | I7: ប្រាក់អាករ

Sheet Sale - June
A1: សៀវភៅទិនានុប្បវត្តិលក់- នាំចេញ
A2: ខែ​​ មិថុនា ឆ្នាំ ២០១៥
A3: ជី អេវើរហ្រ្គីន( ខេមបូឌា​ ) នីតធីង | K3: Vat:100193102
A4: ភូមិជ្រៃកោង សង្កាត់ចោមចៅ ខណ្ឌ ពោធិសែនជ័យ ក្រុង ភ្នំពេញ | K4: Average: | L4: 4088
A5: វិក្ក័យប័ត្រ | I5: ការផ្គត់ផ្គង់
A6: កាលបរិចេ្ឆទ | B6: វិក្ក័យប័ត្រ | C6: អ្នកទិញ | D6: លេខ អតប | E6: បរិយាយ | F6: បរិមាណ | I6: karlk;Cab;Gakr | M6: សរុបថ្លៃទិញ
D7: TIN | G7: ការផ្គត់ផ្គង់ | H7: ការនាំចេញ | I7: lk;;»übuKþlCab;Gakr | K7: lk;;»üGñkeRbIR)as; | M7: រួមទាំអាករ
G8: មិនជាប់អាករ | H8: អត្រា​​ 0 % | I8: តំលៃជាប់អាករ | J8: អាករ | K8: តំលៃជាប់អាករ | L8: អាករ
A9: 42160 | B9: E 55119 | C9: LPP S.A | E9: Men's Top | F9: 137 CT | H9: 41519138 | M9: =G9+H9
A10: 42160 | B10: E 53624 | C10: PRIMARK | E10: See Val Note | F10: 655 CT | H10: 157610622 | M10: =G10+H10
A11: 42160 | B11: E 9812 | C11: SMYK SP Z.O.O | E11: Girls Knitted Dress | F11: 518 CT | H11: 75926121 | M11: =G11+H11
A12: 42164 | B12: E 10122 | C12: SMYK SP Z.O.O | E12: Girls Knitted Sweat Shirt | F12: 404 CT | H12: 109260590 | M12: =G12+H12
A13: 42167 | B13: E 57854 | C13: PRIMARK | E13: Men's Long Sleeve Hoodie | F13: 550 CT | H13: 136860570 | M13: =G13+H13
A14: 42167 | B14: E 57078 | C14: LPP S.A | E14: Men's Top | F14: 1094 CT | H14: 189450332 | M14: =G14+H14
A15: 42174 | B15: E 60607 | C15: CAPRI SRL | E15: Men's Hoody | F15: 827 CT | H15: 267888456 | M15: =G15+H15
A16: 42174 | B16: E 59730 | C16: LPP S.A | E16: Men's Jogging Top | F16: 815 CT | H16: 233561904 | M16: =G16+H16
A17: 42174 | B17: E 60079 | C17: LPP S.A | E17: Men's Sweater +Top | F17: 400 CT | H17: 106100285 | M17: =G17+H17
A18: 42175 | B18: E 61426 | C18: VISAGE LIMITED | E18: Men's Pari / Monica / Leyton Crew | F18: 556 CT | H18: 145296432 | M18: =G18+H18
A19: 42175 | B19: E 61432 | C19: PRIMARK STORES LIMITED | E19: See Val Note | F19: 1220 CT | H19: 299682480 | M19: =G19+H19
A20: 42181 | B20: E 63424 | C20: PRIMARK US CORP | E20: Men Chest Print Zip | F20: 37 CT | H20: 6493691 | M20: =G20+H20
... A22: 42181 | B22: E 63568 | C22: VISAGE LIMITED | E22: Men's Morgan Crew + Connect Crew+ Leyton | F22: 338 CT | H22: 94840834 | M22: =G22+H22
A23: =L4 | E23: Riel | F23: =SUM(F9:F22) | H23: =SUM(H9:H22) | M23: =SUM(M9:M22)
A24: Total USD | E24: USD | G24: =G23/L4 | H24: =H23/L4 | I24: =I23*4034 | J24: =J23*4034 | K24: =K23*4034 | L24: =L23*4034 | M24: =M23/L4
G25: Box 12 | H25: Box 13 | I25: Box 14 | J25: Box 15 | K25: Box 14 | L25: Box 15
H26: Approved By :
N27: =H23*1%
H28: =H24*1%
G29: Sales
G30: July | H30: ='Sale - Jul'!H30 | I30: 21 invoices
G31: Aug | H31: ='Sale - Aug'!I47 | I31: 38 invoices
G32: June | H32: =H23 | I32: 14 invoices
G33: Total: | H33: =SUM(H30:H32) | I33: =14+38+21
H37: =H24*1%

Sheet Sale - Jul
A1: សៀវភៅទិនានុប្បវត្តិលក់- នាំចេញ
A2: ខែ​​ កក្កដា ឆ្នាំ ២០១៥
A3: ជី អេវើរហ្រ្គីន( ខេមបូឌា​ ) នីតធីង | K3: Vat:100193102
A4: ភូមិជ្រៃកោង សង្កាត់ចោមចៅ ខណ្ឌ ពោធិសែនជ័យ ក្រុង ភ្នំពេញ | K4: Average: | L4: 4099
A5: វិក្ក័យប័ត្រ | I5: ការផ្គត់ផ្គង់
A6: កាលបរិចេ្ឆទ | B6: វិក្ក័យប័ត្រ | C6: អ្នកទិញ | D6: លេខ អតប | E6: បរិយាយ | F6: បរិមាណ | I6: karlk;Cab;Gakr | M6: សរុបថ្លៃទិញ
D7: TIN | G7: ការផ្គត់ផ្គង់ | H7: ការនាំចេញ | I7: lk;;»übuKþlCab;Gakr | K7: lk;;»üGñkeRbIR)as; | M7: រួមទាំអាករ
G8: មិនជាប់អាករ | H8: អត្រា​​ 0 % | I8: តំលៃជាប់អាករ | J8: អាករ | K8: តំលៃជាប់អាករ | L8: អាករ
A9: 42188 | B9: E 65884 | C9: LPP S.A | E9: Men's Jogging Top | F9: 1841 CT | H9: 469164366 | M9: =G9+H9
A10: 42188 | B10: E 65884 | C10: LPP S.A | E10: Men's Knit Trousers | F10: 631 CT | H10: 224637197 | M10: =G10+H10
A11: 42188 | B11: E 65484 | C11: Primark Tiendas Slu | E11: Men's Zip Thru Hoody | F11: 343 CT | H11: 88553682 | M11: =G11+H11
A12: 42189 | B12: E 67494 | C12: PRIMARK | E12: Men's Long Sleeve Zip Thru Hoodie | F12: 1093 CT | H12: 282184182 | M12: =G12+H12
A13: 42194 | B13: E 68109 | C13: PRIMARK STORES LIMITED | E13: 7B (Boy) Core Hoody | F13: 600 CT | H13: 137692800 | M13: =G13+H13
A14: 42194 | B14: E 68146 | C14: PRIMARK | E14: Men's Zip Thru Hoody | F14: 772 CT | H14: 199310328 | M14: =G14+H14
A15: 42195 | B15: E 69396 | C15: LPP S.A | E15: Men's Knit Sweater + Jogging Top | F15: 1133 CT | H15: 222232983 | M15: =G15+H15
A16: 42195 | B16: E 69396 | C16: LPP S.A | E16: Men's Knit Trousers | F16: 39 CT | H16: 15787217 | M16: =G16+H16
A17: 42195 | B17: E 69549 | C17: PRIMARK STORES LIMITED | E17: Men + Boy Hoodies | F17: 638 CT | H17: 147298512 | M17: =G17+H17
A18: 42196 | B18: E 70637 | C18: LPP S.A | E18: Ladies Jogging Top | F18: 490 CT | H18: 108300780 | M18: =G18+H18
A19: 42196 | B19: E 70637 | C19: LPP S.A | E19: Men's Knit Trousers | F19: 99 CT | H19: 39649873 | M19: =G19+H19
A20: 42196 | B20: E 70627 | C20: Primark Tiendas Slu | E20: Men's Zip Thru Hoody | F20: 2066 CT | H20: 532736694 | M20: =G20+H20
... A29: 42203 | B29: E 73524 | C29: VDR FASHION GROUP BV | E29: Ladies Knitted Blazer | F29: 191 CT | H29: 114575606 | M29: =G29+H29
A30: =L4 | E30: Riel | F30: =SUM(F9:F29) | H30: =SUM(H9:H29) | M30: =SUM(M9:M29)
A31: Total USD | E31: USD | G31: =G30/L4 | H31: =H30/L4 | I31: =I30*4034 | J31: =J30*4034 | K31: =K30*4034 | L31: =L30*4034 | M31: =M30/L4
G32: Box 12 | H32: Box 13 | I32: Box 14 | J32: Box 15 | K32: Box 14 | L32: Box 15
H33: Approved By :
H35: =H31*1%
H44: =H31*1%

Sheet Sale - Aug
A1: សៀវភៅទិនានុប្បវត្តិលក់- នាំចេញ
A2: ខែ​​ សីហា ឆ្នាំ ២០១៥
A3: ជី អេវើរហ្រ្គីន( ខេមបូឌា​ ) នីតធីង | L3: Vat:100193102
A4: ភូមិជ្រៃកោង សង្កាត់ចោមចៅ ខណ្ឌ ពោធិសែនជ័យ ក្រុង ភ្នំពេញ | L4: Average: | M4: 4095
A5: វិក្ក័យប័ត្រ | J5: ការផ្គត់ផ្គង់
A6: កាលបរិចេ្ឆទ | B6: វិក្ក័យប័ត្រ | C6: អ្នកទិញ | D6: លេខ អតប | E6: បរិយាយ | F6: បរិមាណ | J6: karlk;Cab;Gakr | N6: សរុបថ្លៃទិញ
D7: TIN | F7: ការផ្គត់ផ្គង់ | I7: ការនាំចេញ | J7: lk;;»übuKþlCab;Gakr | L7: lk;;»üGñkeRbIR)as; | N7: រួមទាំអាករ
F8: មិនជាប់អាករ | I8: អត្រា​​ 0 % | J8: តំលៃជាប់អាករ | K8: អាករ | L8: តំលៃជាប់អាករ | M8: អាករ
A9: 42202 | B9: E 72202 | C9: Primark Us Corp | E9: Men Zip Thru Hoody | F9: 65 | G9: CT | I9: 16764930 | N9: =H9+I9
A10: 42203 | B10: E 13027 | C10: LPP S.A | E10: Ladies Knit Jogging Top | F10: 64 | G10: CT | I10: 26424115 | N10: =H10+I10
A11: 42208 | B11: E 13359 | C11: VDR Fashion Group BV | E11: Ladies Knit Shirt | F11: 36 | G11: CT | I11: 29192000 | N11: =H11+I11
A12: 42209 | B12: E 74804 | C12: Primark Us Corp | E12: Boy Hoody | F12: 305 | G12: CT | I12: 70028000 | N12: =H12+I12
A13: 42209 | B13: E 74578 | C13: LPP S.A | E13: Men's Jogging Top | F13: 904 | G13: CT | I13: 242980473 | N13: =H13+I13
A14: 42210 | B14: E 76431 | C14: Primark | E14: Men Zip Thru Hoody | F14: 700 | G14: CT | I14: 180986400 | N14: =H14+I14
A15: 42210 | B15: E 76547 | C15: Primark Stores Limited | E15: 7/2Boy Core Hoody | F15: 800 | G15: CT | I15: 174420000 | N15: =H15+I15
A16: 42210 | B16: E 65557 | C16: LPP S.A | E16: Ladies Jogging Top | F16: 680 | G16: CT | I16: 178829338 | N16: =H16+I16
A17: 42210 | B17: E 65557 | C17: LPP S.A | E17: Men's Knit Trousers | F17: 93 | G17: CT | I17: 36022203 | N17: =H17+I17
A18: 42215 | B18: E 76966 | C18: Primark | E18: See Val Note | F18: 355 | G18: CT | I18: 89531330 | N18: =H18+I18
A19: 42215 | B19: E 76966 | C19: Primark | E19: Ladies Nylon Zip Back Fl Legging | F19: 267 | G19: CT | I19: 191743220 | N19: =H19+I19
A20: 42216 | B20: E 78298 | C20: Primark Us Corp | E20: Mens Hoody | F20: 70 | G20: CT | I20: 18116280 | N20: =H20+I20
... A41: 42237 | B41: E 87246 | C41: Primark Stores Limited | E41: Boy's Hoody | F41: 200 | G41: CT | I41: 41197900 | N41: =H41+I41
A42: 42237 | B42: E 87199 | C42: Primakr Tiendas S.l.u. | E42: Men's Knit Chest Print Zip Thru | F42: 250 | G42: CT | I42: =15750*4079 | N42: =H42+I42
A43: 42237 | B43: E 87074 | C43: Primark 47 Mary Street Dublin1. | E43: Men's Knit Chest Print Zip Thru | F43: 192 | G43: CT | I43: 49339584 | N43: =H43+I43
A44: 42237 | B44: E 86097 | C44: Primark Stores Limited | E44: See Val Note | F44: 756 | G44: CT | I44: 178378749 | N44: =H44+I44
A45: 42237 | B45: E 86347 | C45: LPP S.A | E45: Men's Jogging Top | F45: 725 | G45: CT | I45: 162100480 | N45: =H45+I45
A46: 42237 | B46: E 86347 | C46: LPP S.A | E46: Men's Knit Trousers | F46: 531 | G46: CT | I46: 203679970 | N46: =H46+I46
A47: =M4 | E47: Riel | I47: =SUM(I9:I46) | N47: =SUM(N9:N46)
A48: Total USD | E48: USD | H48: =H47/M4 | I48: =I47/M4 | J48: =J47*4034 | K48: =K47*4034 | L48: =L47*4034 | M48: =M47*4034 | N48: =N47/M4
H49: Box 12 | J49: Box 14 | K49: Box 15 | L49: Box 14 | M49: Box 15
I50: Approved By :
I52: =I48*1%
I61: =I48*1%
