Workbook
Name \A: #REF!
Name \D: #REF!
Name \E: #REF!
Name \G: '[1]Company Related Premises'!#REF!
Name \H: '[1]Company Related Premises'!#REF!
Name \L: '[1]Company Related Premises'!#REF!
Name \M: '[1]Company Related Premises'!#REF!
Name \N: #REF!
Name \O: #REF!
Name \P: #REF!
Name \Q: #REF!
Name \R: #REF!
Name \S: #REF!
Name \T: #REF!
Name \U: #REF!
Name \V: #REF!
Name \W: #REF!
Name \X: #REF!
Name \xy: #REF!
Name \Y: #REF!
Name \Z: #REF!
Name __PR1: [2]Sheet!#REF!
Name __SR1: #REF!
Name __SR2: #REF!
Name _PR1: [2]Sheet!#REF!
Name _SR1: #REF!
Name _SR2: #REF!
Name aa: #REF!
Name aaa: #REF!
Name abcd: #REF!
Name All: #REF!
Name ANLAGE_III: [3]Anlagevermögen!$A$1:$Z$29
Name data84: '[4]Purchase Order'!$E$40
Name dflt3: '[4]Customize Your Purchase Order'!$F$24
Name dflt4: '[4]Customize Your Purchase Order'!$E$25
Name DRPAUSE: #REF!
Name DSCTEMP: [5]DSCTEMP!$A$1:$B$65536
Name FTBSch: [2]Sheet!#REF!
Name hh: [2]Sheet!#REF!
Name is: '[6]Company Related Premises'!#REF!
Name jngiüorajg: #REF!
Name ll: #REF!
Name new: #REF!
Name PeriodsInYear: #REF!
Name PrintArea: #REF!
Name qqqqqqqqqqqqqqqqqqqqq: #REF!
Name RANDO: #REF!
Name RANDU: #REF!
Name re: [7]Sheet!#REF!
Name Report: #REF!
Name Sale: #REF!
Name SalSch: #REF!
Name Seite1: #REF!
Name Seite2: #REF!
Name Seite3: #REF!
Name Spec: #REF!
Name SR: #REF!
Name SRC: #REF!
Name tes: [2]Sheet!#REF!
Name Test: [2]Sheet!#REF!

Sheet Company information
B2: COMPANY NAME (KHMER) | D2: ឈ្មោះសហគ្រាសជាអក្សរខ្មែរ | E2: វ៉ាយអិលធី​ អ៊ិនធើណេសិនណល
B3: COMPANY NAME (ENGLISH) | D3: ឈ្មោះសហគ្រាសជាអក្សរឡាតាំង | E3: YLT INTERNATIONAL CO., LTD.
B4: VAT NUMBER | D4: លេខអត្តសញ្ញាណកម្ម | E4: L001-100192823
B5: Business Activity | E5: រោងចក្រផលិតរានទេវតាធ្វើពីឈើ
B6: Address | D6: អាសយដ្ឋានអាជីវកម្មគោលដេីម | E6: ភូមិសទ្ធា ឃុំរំចេក ស្រុកព្រះស្ដេច ខេត្តព្រៃវែង
B7: Request Period | E7: ខែធ្នូ ឆ្នាំ២០២២ ដល់ខែធ្នូ ឆ្នាំ២០២៤
B8: Auditor Name | E8: លោក ជុំ សុភា | F8: លោក ជា ហុកស័រ
E9: ជុំ សុភា | F9: ជា ហុកស័រ
B10: Phone Number
B11: លេខគណនីធនាគារ | E11: 0111011419621
B12: ឈ្មោះធនាគារ | E12: ភ្នំពេញ ពាណិជ្ជ
B13: Person to Contact
B14: Position
B15: Audit timeline | E15: ពីថ្ងៃទី12 ខែវិច្ឆិកា ឆ្នាំ2025 ដល់ថ្ងៃទី19 ខែវិច្ឆិកា ឆ្នាំ2025
B17: MOC NUMBER | E17: MOC-33121739
B18: MOC DATE OF ISSUE | E18: 41513
B19: PATENT ISSUE DATE | E19: 45323 | F19: ទឹកប្រាក់ | G19: 5000000
B20: VAT CERTIFICATE ISSUE DATE | E20: 42388
B21: Request Date | E21: ស្នើសុំបង្វិលសងអាករលើតម្លៃបន្ថែមតាមអនឡាញចុះថ្ងៃទី៣ ខែកុម្ភៈ ឆ្នាំ២០២៥ | H21: 45691
B22: Amount of Request | E22: 352496017

Sheet Annex 0-IM State Charge
A1: តារាងឧបសម្ព័ន្ធ 0
A2: បញ្ជាក់អំពីអាករលើធាតុចូលដែលមិនអាចស្នើសុំជាឥណទាន
A3: ( ការនាំចូលជាបន្ទុករបស់រដ្ឋ )
A4: ក្រុមហ៊ុន៖ | B4: ='Company information'!E2 -> វ៉ាយអិលធី​ អ៊ិនធើណេសិនណល | G4: សវនករពន្ធដារ៖ | H4: ='Company information'!E8 -> លោក ជុំ សុភា
A5: លេខ អតប៖ | B5: ='Company information'!E4 -> L001-100192823 | H5: ='Company information'!F8 -> លោក ជា ហុកស័រ
A6: ='Company information'!E21 -> ស្នើសុំបង្វិលសងអាករលើតម្លៃបន្ថែមតាមអនឡាញចុះថ្ងៃទី៣ ខែកុម្ភៈ ឆ្នាំ២០២៥ | G6: ទឹកប្រាក់ស្នើសុំបង្វិលសងចំនួន៖ | H6: ='Company information'!E22 -> 352496017
A7: ល.រ | B7: បរិយាយ | C7: ប្រតិវេទន៍គយនាំចូល/វិក្កយបត្រ | E7: បង្កាន់ដៃទទួលប្រាក់ | G7: ប្រាក់អាករ (រៀល) | H7: ផ្សេងៗ
C8: លេខ | D8: ចុះថ្ងៃទី ខែ ឆ្នាំ | E8: លេខ | F8: ថ្ងៃ ខែ ឆ្នាំ
A17: សរុបអាករលើការនាំចូលជាបន្ទុករដ្ឋ | G17: =SUM(G9:G16) -> 0
E19: រាជធានីភ្នំពេញ.ថ្ងៃទី ខែ ឆ្នាំ២០២៥
E20: មន្ត្រីសវនកម្ម
E23: ='Company information'!E9 -> ជុំ សុភា | H23: ='Company information'!F9 -> ជា ហុកស័រ

Sheet Annex I-IM Non-State Charge
A1: តារាងឧបសម្ព័ន្ធ I
A2: តារាងផ្ទៀងផ្ទាត់បញ្ជាក់អំពីអាករលើធាតុចូលដែលអាចស្នើសុំជាឥណទាន
A3: ( ការនាំចូល ឬ អាករលើតម្លៃបន្ថែមតាមវិធីគិតអាករជំនួស(Reverse Charge))
A4: ក្រុមហ៊ុន៖ | B4: ='Company information'!E2 -> វ៉ាយអិលធី​ អ៊ិនធើណេសិនណល | G4: សវនករពន្ធដារ៖ | H4: ='Company information'!E8 -> លោក ជុំ សុភា
A5: លេខ អតប៖ | B5: ='Company information'!E4 -> L001-100192823 | H5: ='Company information'!F8 -> លោក ជា ហុកស័រ
A6: ='Company information'!E21 -> ស្នើសុំបង្វិលសងអាករលើតម្លៃបន្ថែមតាមអនឡាញចុះថ្ងៃទី៣ ខែកុម្ភៈ ឆ្នាំ២០២៥ | G6: ទឹកប្រាក់ស្នើសុំបង្វិលសងចំនួន៖ | H6: ='Company information'!E22 -> 352496017
A7: ល.រ | B7: បរិយាយ | C7: ប្រតិវេទន៍គយនាំចូល/ វិក្កយបត្រ | E7: បង្កាន់ដៃទទួលប្រាក់ | G7: ប្រាក់អាករ (រៀល) | H7: លទ្ធផលផ្ទៀងផ្ទាត់ជាមួយទិន្នន័យពីអគ្គនាយកដ្ឋានគយ/ ឬ អាករគិតជំនួស(Reverse Charge) | I7: ទឹកប្រាក់អនុញ្ញាត
C8: លេខ | D8: ចុះថ្ងៃទី ខែ ឆ្នាំ | E8: លេខ | F8: ថ្ងៃ ខែ ឆ្នាំ | J8: បានប្រកាស | K8: ខ្វះ
A10: I. ការនាំចូល
A11: 1 | B11: វត្ថុធាតុដើម | C11: IXXXX2 | D11: 45503 | G11: 566431 | H11: អនុញ្ញាត (បានប្រកាស) | I11: =J11 -> 566431 | J11: 566431 | K11: =G11-J11 -> 0
A12: =A11+1 -> 2 | B12: SERVICE FEE ON SOCIAL INSURANCE FOR MARCH 24 | C12: IXXXX1 | D12: 45373 | G12: 583920 | H12: ព្យួរទុក (មិនមានឯកសារគាំទ្រ) | I12: =J12 -> 0 | K12: =G12-J12 -> 583920
A13: =A12+1 -> 3 | B13: ទិញឡានToyota Raize | C13: IXXXX3 | D13: 45401 | G13: 569736 | H13: មិនអនុញ្ញាត (មិនអនុញ្ញាតជាឥណទាន) | I13: =J13 -> 0 | K13: =G13-J13 -> 569736
A14: =A13+1 -> 4 | B14: សម្ភារៈការិយាល័យ | C14: IXXXX4 | D14: 45434 | G14: 552821 | H14: ព្យួរទុក (មិនមានក្នុងប្រព័ន្ធ) | I14: =J14 -> 0 | K14: =G14-J14 -> 552821
A15: =A14+1 -> 5 | B15: សម្ភារៈការិយាល័យ | C15: IXXXX5 | D15: 45462 | G15: 554476 | H15: ព្យួរទុក (មិនមានក្នុងប្រព័ន្ធ) | I15: =J15 -> 0 | K15: =G15-J15 -> 554476
A16: II. អាករលើតម្លៃបន្ថែមតាមវិធីគិតអាករជំនួស(Reverse Charge)
A17: 1 | B17: E-BOOKING AIR TICKET | C17: REVERS.322XX | D17: 45352 | G17: 50262 | H17: អនុញ្ញាត (បានប្រកាស) | I17: 5000 | J17: 5000 | K17: =G17-J17 -> 45262
A19: សរុបអាករលើការនាំចូល ឬ អាករលើតម្លៃបន្ថែមតាមវិធីគិតអាករជំនួស(Reverse Charge) | G19: =SUM(G10:G18) -> 2877646 | H19: សរុបទឺកប្រាក់អនុញ្ញាត | I19: =SUM(I11:I18) -> 571431 | J19: =SUM(J11:J18) -> 571431 | K19: =SUM(K11:K18) -> 2306215
A20: សេចក្តីធានាអះអាងរបស់មន្ត្រីសវនករទទួលបន្ទុក៖ លទ្ធផលផ្ទៀងផ្ទាត់ឥណទានអាករ ចំពោះការនាំចូល ឬ/និង អាករលើតម្លៃបន្ថែមតាមវិធីគិតអាករជំនួស(Reverse Charge)ខាងលើពិតជាត្រឹមត្រូវតាមរបាយការណ៍លម្អិតដែលបានទាញទិន្នន័យពីអគ្គនាយកដ្ឋានគយ/ប្រព័ន្ធE-Filing ពិតប្រាកដមែន។
G23: រាជធានីភ្នំពេញ.ថ្ងៃទី ខែ ឆ្នាំ២០២៥
G24: មន្ត្រីសវនកម្ម
G27: ='Company information'!E9 -> ជុំ សុភា | H27: ='Company information'!F9 -> ជា ហុកស័រ

Sheet AnnexII-Local Pur
A1: តារាងឧបសម្ព័ន្ធ II
A2: តារាងផ្ទៀងផ្ទាត់បញ្ជាក់អំពីអាករលើធាតុចូលដែលអាចស្នើសុំជាឥណទាន
A3: (ការទិញក្នុងស្រុក)
A4: ក្រុមហ៊ុន៖ | B4: ='Company information'!E2 -> វ៉ាយអិលធី​ អ៊ិនធើណេសិនណល | I4: សវនករពន្ធដារ៖ | K4: ='Company information'!E8 -> លោក ជុំ សុភា
A5: លេខ អតប៖ | B5: ='Company information'!E4 -> L001-100192823 | K5: ='Company information'!F8 -> លោក ជា ហុកស័រ | L5: FOR REPORT | R5: សម្គាល់ផ្សេងៗ | T5: បញ្ចូលទិន្នន័យអ្នកផ្គត់ផ្គង់
A6: ='Company information'!E21 -> ស្នើសុំបង្វិលសងអាករលើតម្លៃបន្ថែមតាមអនឡាញចុះថ្ងៃទី៣ ខែកុម្ភៈ ឆ្នាំ២០២៥ | I6: ទឹកប្រាក់ស្នើសុំបង្វិលសងចំនួន៖ | J6: ='Company information'!E22 -> 352496017
A7: ល.រ | B7: បរិយាយ | C7: អ្នកផ្គត់ផ្គង់ | D7: លេខ អតប | E7: វិក្កយបត្រ | G7: ទឹកប្រាក់អាករ | J7: ស្ថានភាព | K7: ផ្សេង (សម្គាល់) | N7: ពិនិត្យឡើងវិញ | O7: VAR INVOICE T/F | P7: VAR. DATE T/F | Q7: VAR. SUPPLIER & PUCHASER | R7: តេស្តទឹកប្រាក់លម្អៀង | S7: សម្កាល់ | T7: កាលបរិច្ឆេទ | U7: លេខវិក្កយបត្រ ឬប្រតិវេទគយ | V7: លេខលិខិតជូនដំណឹងឥណទាន | W7: អ្នកទិញ | Z7: តម្លៃសរុបលើវិក្កយបត្រ | AA7: តម្លៃ​​មិន​រួមអតប និងមិនជាប់​អតប​ | AC7: អាករលើតម្លៃបន្ថែមអត្រា ០% | AD7: អាករលើតម្លៃបន្ថែម | AF7: Under
E8: លេខ | F8: ថ្ងៃ ខែ ឆ្នាំ | G8: ជាដុល្លារអាមេរិក | H8: អត្រា | I8: ជារៀល | W8: ប្រភេទ | X8: លេខសម្គាល់ចុះបញ្ជីពន្ធដា TIN/BIN/TID | Y8: ឈ្មោះ | AA8: តម្លៃមិនរួមអតប | AB8: ការលក់មិនជាប់អតប | AD8: ការលក់ក្នុងស្រុក | AE8: អតបលើការនាំចេញ
L9: បានប្រកាស | M9: នៅខ្វះ
A10: 1 | B10: Buy supplies(L Corner pad) | C10: M.G PROFESS PACKING CO., LTD. | D10: B105-902203045 | E10: MG-2022-0067 | F10: 44925 | I10: 1646800 | J10: បានប្រកាស (អនុញ្ញាត) | L10: 1646800 | M10: 0
A11: =A10+1 -> 2 | B11: Buy supplies(Catton) | C11: MINO PLASTIC INDUSTRY Ltd. | D11: L001-108003280 | E11: MINO202200054 | F11: 44925 | I11: 2901939 | J11: បានប្រកាស (អនុញ្ញាត) | L11: 2901939 | M11: 0
A12: =A11+1 -> 3 | B12: Rental land fee | C12: YLT PROPERTY CO., LTD. | D12: B113-104015977 | E12: 2022-012 | F12: 44925 | I12: 2881900 | J12: បានប្រកាស (អនុញ្ញាត) | L12: 2881900 | M12: 0
A13: =A12+1 -> 4 | B13: Buy supupplies( Supercaledered paper) | C13: MING JI PAPER CO., LTD. | D13: L001-901703837 | E13: 22001447 | F13: 44925 | I13: 1006359 | J13: បានប្រកាស (អនុញ្ញាត) | L13: 1006359 | M13: 0
A14: =A13+1 -> 5 | B14: Copy machine rental fee | C14: BAEKSANG COMPUTER & TRADE (CAMBODIA) CO., LTD. | D14: K009-901504078 | E14: BCT-01679 | F14: 44925 | I14: 90739 | J14: បានប្រកាស (អនុញ្ញាត) | L14: 90739 | M14: 0 | N14: BCT01679
A15: =A14+1 -> 6 | B15: Internet fee | C15: Ezecom Co., Ltd. | D15: L001-100141846 | E15: 902366 | F15: 44923 | I15: 67881 | J15: បានប្រកាស (អនុញ្ញាត) | L15: 67881 | M15: 0 | N15: បានត្រួតពិនិត្យ
A16: =A15+1 -> 7 | B16: Tax consulting service(Vat Refund) | C16: ANDREW & PHILIP ACCOUNTING CO., LTD. (A & P ACCOUNTING) | D16: K005-100161359 | E16: 221903 | F16: 44916 | I16: 2058000 | J16: បានប្រកាស (អនុញ្ញាត) | L16: 2058000 | M16: 0
A17: =A16+1 -> 8 | B17: Security fee | C17: អ៊ឹម ភី អេ អ៊ិនធើណេស្យុនណល់ | D17: L001-100044689 | E17: 51135 | F17: 44909 | I17: 378120 | J17: បានប្រកាស (អនុញ្ញាត) | L17: 378120 | M17: 0
A18: =A17+1 -> 9 | B18: Accounting and tax consulting service | C18: ANDREW & PHILIP ACCOUNTING CO., LTD. (A & P ACCOUNTING) | D18: K005-100161359 | E18: 221777 | F18: 44896 | I18: 205650 | J18: បានប្រកាស (អនុញ្ញាត) | L18: 205650 | M18: 0
A19: =A18+1 -> 10 | B19: Maintenance fee | C19: កាំម៉ិនតែល | D19: L001-100045049 | E19: 8524 | F19: 44896 | I19: 1234 | J19: ប្រកាសរួម (ព្យួរទុក) | M19: 1234
A20: =A19+1 -> 11 | B20: Telephone expense | C20: កាំម៉ិនតែល | D20: L001-100045049 | E20: 8520 | F20: 44896 | I20: 8074 | J20: ប្រកាសរួម (ព្យួរទុក) | M20: 8074
A21: =A20+1 -> 12 | B21: I-Customs permit, Customs clearance, Trucking fee, .... | C21: 2020JUN LOGISTICS CO., LTD. | D21: K010-902001839 | E21: 2022-0774 | F21: 44910 | I21: 614295 | J21: បានប្រកាស (អនុញ្ញាត) | L21: 614295 | M21: 0 | N21: បានត្រួតពិនិត្យ
A22: =A21+1 -> 13 | B22: I-Lift on&Lift off charge | C22: កំពង់ផែស្វយ័តក្រុងព្រះសីហនុ | D22: L001-100044638 | E22: 220878 | F22: 44923 | I22: 23455 | J22: ព្យួរទុក (មិនមានទិន្នន័យ) | M22: 23455
A23: =A22+1 -> 14 | B23: I-Customs permit,Customs clearance,Trucking fee, non insurance... | C23: 2020JUN LOGISTICS CO., LTD. | D23: K010-902001839 | E23: 2022-0746 | F23: 44910 | I23: 626623 | J23: បានប្រកាស (អនុញ្ញាត) | L23: 626623 | M23: 0 | N23: បានត្រួតពិនិត្យ
A24: =A23+1 -> 15 | B24: I-Lift on & Lift off Fee | C24: កំពង់ផែស្វយ័តក្រុងព្រះសីហនុ | D24: L001-100044638 | E24: 206435 | F24: 44896 | I24: 23444 | J24: ព្យួរទុក (មិនមានទិន្នន័យ) | M24: 23444
A25: =A24+1 -> 16 | B25: E-Custom clearance Trucking fee, Lift on charge.... | C25: 2020JUN LOGISTICS CO., LTD. | D25: K010-902001839 | E25: 2022-0784 | F25: 44910 | I25: 524308 | J25: បានប្រកាស (អនុញ្ញាត) | L25: 524308 | M25: 0 | N25: បានត្រួតពិនិត្យ
A26: =A25+1 -> 17 | B26: E-Lift off charge,Gate fee charge | C26: កំពង់ផែស្វយ័តភ្នំពេញ "ក.ស.ភ" | D26: L001-100044999 | E26: INV20221291657 | F26: 44925 | I26: 29642 | J26: បានប្រកាស (អនុញ្ញាត) | L26: 29642 | M26: 0 | N26: ពិនិត្យរួច
A27: =A26+1 -> 18 | B27: E-Customs clearance, Trucking fee , Lift on charge... | C27: 2020JUN LOGISTICS CO., LTD. | D27: K010-902001839 | E27: 2022-0783 | F27: 44910 | I27: 565398 | J27: បានប្រកាស (អនុញ្ញាត) | L27: 565398 | M27: 0 | N27: បានត្រួតពិនិត្យ
A28: =A27+1 -> 19 | B28: E-Lift off charge, Gate fee charge | C28: កំពង់ផែស្វយ័តភ្នំពេញ "ក.ស.ភ" | D28: L001-100044999 | E28: INV20221291658 | F28: 44925 | I28: 29642 | J28: បានប្រកាស (អនុញ្ញាត) | L28: 29642 | M28: 0 | N28: ពិនិត្យរួច
A29: =A28+1 -> 20 | B29: E-Customs clearance fee, trucking fee E255 | C29: 2020JUN LOGISTICS CO., LTD. | D29: K010-902001839 | E29: 2022-0772 | F29: 44910 | I29: 524308 | J29: បានប្រកាស (អនុញ្ញាត) | L29: 524308 | M29: 0 | N29: បានត្រួតពិនិត្យ
A30: =A29+1 -> 21 | B30: E-Lift off charge, Gate fee charge | C30: កំពង់ផែស្វយ័តភ្នំពេញ "ក.ស.ភ" | D30: L001-100044999 | E30: INV20221291255 | F30: 44923 | I30: 29628 | J30: បានប្រកាស (អនុញ្ញាត) | L30: 29628 | M30: 0 | N30: ពិនិត្យរួច
A31: =A30+1 -> 22 | B31: E-Customs clearance, Trucking fee, Lift on charge... | C31: 2020JUN LOGISTICS CO., LTD. | D31: K010-902001839 | E31: 2022-0771 | F31: 44910 | I31: 672232 | J31: បានប្រកាស (អនុញ្ញាត) | L31: 672232 | M31: 0 | N31: បានត្រួតពិនិត្យ
A32: =A31+1 -> 23 | B32: E-Lift off charge,Gate fee charge | C32: កំពង់ផែស្វយ័តភ្នំពេញ "ក.ស.ភ" | D32: L001-100044999 | E32: INV20221291254 | F32: 44923 | I32: 29628 | J32: បានប្រកាស (អនុញ្ញាត) | L32: 29628 | M32: 0 | N32: ពិនិត្យរួច
A33: =A32+1 -> 24 | B33: E-Customs clearance, trucking fee, lift on charge....E250 | C33: 2020JUN LOGISTICS CO., LTD. | D33: K010-902001839 | E33: 2022-0758 | F33: 44910 | I33: 672232 | J33: បានប្រកាស (អនុញ្ញាត) | L33: 672232 | M33: 0 | N33: បានត្រួតពិនិត្យ
A34: =A33+1 -> 25 | B34: E-Lift off charge, Gate fee charge(E250) | C34: កំពង់ផែស្វយ័តភ្នំពេញ "ក.ស.ភ" | D34: L001-100044999 | E34: INV20221288940 | F34: 44911 | I34: 29599 | J34: បានប្រកាស (អនុញ្ញាត) | L34: 29599 | M34: 0 | N34: ពិនិត្យរួច
A35: =A34+1 -> 26 | B35: E-Customs clearance charge, Trucking fee, lift on charge.... | C35: 2020JUN LOGISTICS CO., LTD. | D35: K010-902001839 | E35: 2022-0738 | F35: 44910 | I35: 713322 | J35: បានប្រកាស (អនុញ្ញាត) | L35: 713322 | M35: 0 | N35: បានត្រួតពិនិត្យ
A36: =A35+1 -> 27 | B36: E-Customs clearance,Trucking fee, Lift on charge .... | C36: 2020JUN LOGISTICS CO., LTD. | D36: K010-902001839 | E36: 2022-0737 | F36: 44910 | I36: 672232 | J36: បានប្រកាស (អនុញ្ញាត) | L36: 672232 | M36: 0 | N36: បានត្រួតពិនិត្យ
... A39: =A38+1 -> 30 | B39: E-Lift off charge, and Gate fee charge | C39: កំពង់ផែស្វយ័តភ្នំពេញ "ក.ស.ភ" | D39: L001-100044999 | E39: INV20221286735 | F39: 44901 | I39: 29660 | J39: បានប្រកាស (អនុញ្ញាត) | L39: 29660 | M39: 0 | N39: ពិនិត្យរួច
A40: =A39+1 -> 31 | B40: Rental land fee | C40: YLT PROPERTY CO., LTD. | D40: B113-104015977 | E40: 2023-001 | F40: 44957 | I40: 2872800 | J40: បានប្រកាស (អនុញ្ញាត) | L40: 2872800 | M40: 0
A41: =A40+1 -> 32 | B41: Copy machine fee | C41: BAEKSANG COMPUTER & TRADE (CAMBODIA) CO., LTD. | D41: K009-901504078 | E41: BCT-00146 | F41: 44957 | I41: 82080 | J41: បានប្រកាស (អនុញ្ញាត) | L41: 82080 | M41: 0
A42: =A41+1 -> 33 | B42: Buy supplies(Cotton) | C42: MINO PLASTIC INDUSTRY Ltd. | D42: L001-108003280 | E42: MINO202300002 | F42: 44957 | I42: 2937894 | J42: បានប្រកាស (អនុញ្ញាត) | L42: 2937894 | M42: 0
A43: =A42+1 -> 34 | B43: Buy supplies( STAPLE PIN AHACHER) | C43: MING JI PAPER CO., LTD. | D43: L001-901703837 | E43: 23000055 | F43: 44950 | I43: 370350 | J43: បានប្រកាស (អនុញ្ញាត) | L43: 370350 | M43: 0
A44: =A43+1 -> 35 | B44: Buy supplies(Corner pad /Catton) | C44: M.G PROFESS PACKING CO., LTD. | D44: B105-902203045 | E44: MG-2023-0011 | F44: 44956 | I44: 73800 | J44: បានប្រកាស (អនុញ្ញាត) | L44: 73800 | M44: 0
A45: =A44+1 -> 36 | B45: Internet fee | C45: Ezecom Co., Ltd. | D45: L001-100141846 | E45: EZE-TI-23-01-001225 | F45: 44954 | I45: 67700 | J45: បានប្រកាស (អនុញ្ញាត) | L45: 67700 | M45: 0 | N45: បានត្រួតពិនិត្យ
A46: =A45+1 -> 37 | B46: Security fee | C46: អ៊ឹម ភី អេ អ៊ិនធើណេស្យុនណល់ | D46: L001-100044689 | E46: 51512 | F46: 44942 | I46: 378580 | J46: បានប្រកាស (អនុញ្ញាត) | L46: 378580 | M46: 0
A47: =A46+1 -> 38 | B47: Accounting and tax consulting service | C47: ANDREW & PHILIP ACCOUNTING CO., LTD. (A & P ACCOUNTING) | D47: K005-100161359 | E47: 230015 | F47: 44928 | I47: 206000 | J47: បានប្រកាស (អនុញ្ញាត) | L47: 206000 | M47: 0
A48: =A47+1 -> 39 | B48: Mobile expense | C48: កាំម៉ិនតែល | D48: L001-100045049 | E48: 8527 | F48: 44927 | I48: 6698 | J48: ប្រកាសរួម (ព្យួរទុក) | M48: 6698
A49: =A48+1 -> 40 | B49: Maintenance fee | C49: កាំម៉ិនតែល | D49: L001-100045049 | E49: 8531 | F49: 44927 | I49: 1235 | J49: ប្រកាសរួម (ព្យួរទុក) | M49: 1235
A50: =A49+1 -> 41 | B50: E-Customs clearance ,Trucking fee ,Lift on charge .... | C50: 2020JUN LOGISTICS CO., LTD. | D50: K010-902001839 | E50: 2023-0017 | F50: 44939 | I50: 566362 | J50: បានប្រកាស (អនុញ្ញាត) | L50: 566362 | M50: 0 | N50: បានត្រួតពិនិត្យ
A51: =A50+1 -> 42 | B51: E-Lift off charge, Gate fee charge(E10) | C51: កំពង់ផែស្វយ័តភ្នំពេញ "ក.ស.ភ" | D51: L001-100044999 | E51: INV20230105314 | F51: 44954 | I51: 29542 | J51: បានប្រកាស (អនុញ្ញាត) | L51: 29542 | M51: 0 | N51: ពិនិត្យរួច
A52: =A51+1 -> 43 | B52: E-Customs clearance. trucking fee, Lift on charge..... | C52: 2020JUN LOGISTICS CO., LTD. | D52: K010-902001839 | E52: 2022-0043 | F52: 44939 | I52: 582826 | J52: ប្រកាសខុស (ព្យួរទុក) | M52: 582826 | N52: 2023-0043
A53: =A52+1 -> 44 | B53: E-Customs clearance, trucking fee, lift on charge ....(7) | C53: 2020JUN LOGISTICS CO., LTD. | D53: K010-902001839 | E53: 2023-0042 | F53: 44939 | I53: 582826 | J53: បានប្រកាស (អនុញ្ញាត) | L53: 582826 | M53: 0 | N53: បានត្រួតពិនិត្យ
A54: =A53+1 -> 45 | B54: E-Lift off charge, gate fee charge (E7&E8) | C54: កំពង់ផែស្វយ័តភ្នំពេញ "ក.ស.ភ" | D54: L001-100044999 | E54: INV20230104332 | F54: 44949 | I54: 59299 | J54: បានប្រកាស (អនុញ្ញាត) | L54: 59299 | M54: 0 | N54: ពិនិត្យរួច
A55: =A54+1 -> 46 | B55: E-Customs clearance, Trucking fee, lift on charge... | C55: 2020JUN LOGISTICS CO., LTD. | D55: K010-902001839 | E55: 2023-0022 | F55: 44939 | I55: 566362 | J55: បានប្រកាស (អនុញ្ញាត) | L55: 566362 | M55: 0 | N55: បានត្រួតពិនិត្យ
A56: =A55+1 -> 47 | B56: E-Lift off charge, gate fee charge(E4) | C56: កំពង់ផែស្វយ័តភ្នំពេញ "ក.ស.ភ" | D56: L001-100044999 | E56: INV20230102381 | F56: 44939 | I56: 29635 | J56: បានប្រកាស (អនុញ្ញាត) | L56: 29635 | M56: 0 | N56: ពិនិត្យរួច
A57: =A56+1 -> 48 | B57: E-Customs clearance charge, trucking fee , Lift on charge.... | C57: 2020JUN LOGISTICS CO., LTD. | D57: K010-902001839 | E57: 2023-0014 | F57: 44939 | I57: 599290 | J57: បានប្រកាស (អនុញ្ញាត) | L57: 599290 | M57: 0 | N57: បានត្រួតពិនិត្យ
A58: =A57+1 -> 49 | B58: E-Lift -off charge, Gate fee charge (E3) | C58: កំពង់ផែស្វយ័តភ្នំពេញ "ក.ស.ភ" | D58: L001-100044999 | E58: INV20230101422 | F58: 44935 | I58: 29664 | J58: បានប្រកាស (អនុញ្ញាត) | L58: 29664 | M58: 0 | N58: ពិនិត្យរួច
A59: =A58+1 -> 50 | B59: E-Customs clearance charge, trucking fee, ...... | C59: 2020JUN LOGISTICS CO., LTD. | D59: K010-902001839 | E59: 2023-0013 | F59: 44939 | I59: 562246 | J59: បានប្រកាស (អនុញ្ញាត) | L59: 562246 | M59: 0 | N59: បានត្រួតពិនិត្យ
A60: =A59+1 -> 51 | B60: E-Lift off charge, Gate fee charge (E 2) | C60: កំពង់ផែស្វយ័តភ្នំពេញ "ក.ស.ភ" | D60: L001-100044999 | E60: INV20230101421 | F60: 44935 | I60: 19776 | J60: បានប្រកាស (អនុញ្ញាត) | L60: 19776 | M60: 0 | N60: ពិនិត្យរួច
A61: =A60+1 -> 52 | B61: I-Customs permit, customs clearance charge, trucking charge...... | C61: 2020JUN LOGISTICS CO., LTD. | D61: K010-902001839 | E61: 2023-0054 | F61: 44939 | I61: 627690 | J61: បានប្រកាស (អនុញ្ញាត) | L61: 627690 | M61: 0 | N61: បានត្រួតពិនិត្យ
A62: =A61+1 -> 53 | B62: I-Lift on & Lift off charge I 7313& I7319 | C62: កំពង់ផែស្វយ័តក្រុងព្រះសីហនុ | D62: L001-100044638 | E62: 14437 | F62: 44953 | I62: 23387 | J62: ព្យួរទុក (មិនមានទិន្នន័យ) | M62: 23387
A63: =A62+1 -> 54 | B63: I-Customs permit, customs clearance charge, trucking fee,...... | C63: 2020JUN LOGISTICS CO., LTD. | D63: K010-902001839 | E63: 2023-0053 | F63: 44939 | I63: 1511395 | J63: បានប្រកាស (អនុញ្ញាត) | L63: 1511395 | M63: 0 | N63: បានត្រួតពិនិត្យ
A64: =A63+1 -> 55 | B64: I-Lift on charge, Gate fee charge | C64: កំពង់ផែស្វយ័តភ្នំពេញ "ក.ស.ភ" | D64: L001-100044999 | E64: INV20230103413 | F64: 44943 | I64: 88884 | J64: បានប្រកាស (អនុញ្ញាត) | L64: 88884 | M64: 0 | N64: ពិនិត្យរួច
A65: =A64+1 -> 56 | B65: I-Customs permit, Customs clearance charge, trucking fee ....... | C65: 2020JUN LOGISTICS CO., LTD. | D65: K010-902001839 | E65: 2023-0037 | F65: 44939 | I65: 660618 | J65: បានប្រកាស (អនុញ្ញាត) | L65: 660618 | M65: 0 | N65: បានត្រួតពិនិត្យ
A66: =A65+1 -> 57 | B66: I-Lift on& Lift off fee | C66: កំពង់ផែស្វយ័តក្រុងព្រះសីហនុ | D66: L001-100044638 | E66: 7457 | F66: 44940 | I66: 35809 | J66: ព្យួរទុក (មិនមានទិន្នន័យ) | M66: 35809
A67: =A66+1 -> 58 | B67: Buy supplies(L corner Pad) | C67: M.G PROFESS PACKING CO., LTD. | D67: B105-902203045 | E67: MG-2023-0025 | F67: 44985 | I67: 1212900 | J67: បានប្រកាស (អនុញ្ញាត) | L67: 1212900 | M67: 0
A68: =A67+1 -> 59 | B68: I-Lift on &Lift off (I13327) | C68: កំពង់ផែស្វយ័តក្រុងព្រះសីហនុ | D68: L001-100044638 | E68: 27887 | F68: 44985 | I68: 23045 | J68: ព្យួរទុក (មិនមានទិន្នន័យ) | M68: 23045
A69: =A68+1 -> 60 | B69: I-Customs permit, Customs clearance charge, trucking fee .....(I1088) | C69: 2020JUN LOGISTICS CO., LTD. | D69: K010-902001839 | E69: 2023-0089 | F69: 44978 | I69: 617474 | J69: បានប្រកាស (អនុញ្ញាត) | L69: 617474 | M69: 0 | N69: បានត្រួតពិនិត្យ
A70: =A69+1 -> 61 | B70: I-Lift on charge & Gate fee charge (I1088) | C70: កំពង់ផែស្វយ័តភ្នំពេញ "ក.ស.ភ" | D70: L001-100044999 | E70: INV20230207326 | F70: 44965 | I70: 29513 | J70: បានប្រកាស (អនុញ្ញាត) | L70: 29513 | M70: 0 | N70: ពិនិត្យរួច
A71: =A70+1 -> 62 | B71: I-Customs permit, customs clearance charge, Trucking fee...(I888) | C71: 2020JUN LOGISTICS CO., LTD. | D71: K010-902001839 | E71: 2023-0090 | F71: 44978 | I71: 584954 | J71: បានប្រកាស (អនុញ្ញាត) | L71: 584954 | M71: 0 | N71: បានត្រួតពិនិត្យ
A72: =A71+1 -> 63 | B72: E-Customs clearance charge, Trucking fee, Lift on charge ....(E24) | C72: 2020JUN LOGISTICS CO., LTD. | D72: K010-902001839 | E72: 2023-0094 | F72: 44978 | I72: 559344 | J72: បានប្រកាស (អនុញ្ញាត) | L72: 559344 | M72: 0 | N72: បានត្រួតពិនិត្យ
A73: =A72+1 -> 64 | B73: E-Lift off charge, Gate fee charge (E24) | C73: កំពង់ផែស្វយ័តភ្នំពេញ "ក.ស.ភ" | D73: L001-100044999 | E73: INV20230210421 | F73: 44982 | I73: 29131 | J73: បានប្រកាស (អនុញ្ញាត) | L73: 29131 | M73: 0 | N73: ពិនិត្យរួច
A74: =A73+1 -> 65 | B74: E-Customs clearance charge, trucking fee, lift on charge ....(E23) | C74: 2020JUN LOGISTICS CO., LTD. | D74: K010-902001839 | E74: 2023-0093 | F74: 44978 | I74: 559344 | J74: បានប្រកាស (អនុញ្ញាត) | L74: 559344 | M74: 0 | N74: បានត្រួតពិនិត្យ
A75: =A74+1 -> 66 | B75: E-Lift off charge & Gate fee charge (E23) | C75: កំពង់ផែស្វយ័តភ្នំពេញ "ក.ស.ភ" | D75: L001-100044999 | E75: INV20230210422 | F75: 44982 | I75: 29131 | J75: បានប្រកាស (អនុញ្ញាត) | L75: 29131 | M75: 0 | N75: ពិនិត្យរួច
A76: =A75+1 -> 67 | B76: E-Customs clearance charge, Trucking fee, lift on charge ....(E20) | C76: 2020JUN LOGISTICS CO., LTD. | D76: K010-902001839 | E76: 2023-0087 | F76: 44978 | I76: 665034 | J76: បានប្រកាស (អនុញ្ញាត) | L76: 665034 | M76: 0 | N76: បានត្រួតពិនិត្យ
A77: =A76+1 -> 68 | B77: E-Lift off charge, Gate fee charge (E20) | C77: កំពង់ផែស្វយ័តភ្នំពេញ "ក.ស.ភ" | D77: L001-100044999 | E77: INV20230209080 | F77: 44975 | I77: 29390 | J77: បានប្រកាស (អនុញ្ញាត) | L77: 29390 | M77: 0 | N77: ពិនិត្យរួច
A78: =A77+1 -> 69 | B78: E-Customs clearance charge, trucking fee, lift on charge ..(E19) | C78: 2020JUN LOGISTICS CO., LTD. | D78: K010-902001839 | E78: 2023-0086 | F78: 44978 | I78: 482109 | J78: បានប្រកាស (អនុញ្ញាត) | L78: 482109 | M78: 0 | N78: បានត្រួតពិនិត្យ
A79: =A78+1 -> 70 | B79: E-Lift off charge, Gate fee charge (E19) | C79: កំពង់ផែស្វយ័តភ្នំពេញ "ក.ស.ភ" | D79: L001-100044999 | E79: INV20230209077 | F79: 44975 | I79: 19594 | J79: បានប្រកាស (អនុញ្ញាត) | L79: 19594 | M79: 0 | N79: ពិនិត្យរួច
A80: =A79+1 -> 71 | B80: E-Customs clearance , Trucking fee, Lift on charge ...(E21) | C80: 2020JUN LOGISTICS CO., LTD. | D80: K010-902001839 | E80: 2023-0088 | F80: 44978 | I80: 518694 | J80: បានប្រកាស (អនុញ្ញាត) | L80: 518694 | M80: 0 | N80: បានត្រួតពិនិត្យ
... A88: =A87+1 -> 79 | B88: E-Lift off charge, Gate fee charge (E13) | C88: កំពង់ផែស្វយ័តភ្នំពេញ "ក.ស.ភ" | D88: L001-100044999 | E88: INV20230206931 | F88: 44963 | I88: 19718 | J88: បានប្រកាស (អនុញ្ញាត) | L88: 19718 | M88: 0 | N88: ពិនិត្យរួច
A89: =A88+1 -> 80 | B89: Rental land fee | C89: YLT PROPERTY CO., LTD. | D89: B113-104015977 | E89: 2023-002 | F89: 44985 | I89: 2830100 | J89: បានប្រកាស (អនុញ្ញាត) | L89: 2830100 | M89: 0
A90: =A89+1 -> 81 | B90: Internet fee | C90: Ezecom Co., Ltd. | D90: L001-100141846 | E90: EZE-TI-23-02-002458 | F90: 44985 | I90: 66693 | J90: បានប្រកាស (អនុញ្ញាត) | L90: 66693 | M90: 0 | N90: បានត្រួតពិនិត្យ
A91: =A90+1 -> 82 | B91: Copy machine rental | C91: BAEKSANG COMPUTER & TRADE (CAMBODIA) CO., LTD. | D91: K009-901504078 | E91: BCT-00291 | F91: 44985 | I91: 80860 | J91: បានប្រកាស (អនុញ្ញាត) | L91: 80860 | M91: 0
A92: =A91+1 -> 83 | B92: Buy supplies(Cotton) | C92: MINO PLASTIC INDUSTRY Ltd. | D92: L001-108003280 | E92: MINO202300009 | F92: 44985 | I92: 2919022 | J92: បានប្រកាស (អនុញ្ញាត) | L92: 2919022 | M92: 0
A93: =A92+1 -> 84 | B93: Security fee | C93: អ៊ឹម ភី អេ អ៊ិនធើណេស្យុនណល់ | D93: L001-100044689 | E93: 52085 | F93: 44975 | I93: 375176 | J93: បានប្រកាស (អនុញ្ញាត) | L93: 375176 | M93: 0
A94: =A93+1 -> 85 | B94: Accounting and tax consulting service | C94: ANDREW & PHILIP ACCOUNTING CO., LTD. (A & P ACCOUNTING) | D94: K005-100161359 | E94: 230167 | F94: 44958 | I94: 205500 | J94: បានប្រកាស (អនុញ្ញាត) | L94: 205500 | M94: 0
A95: =A94+1 -> 86 | B95: Maintenance fee | C95: កាំម៉ិនតែល | D95: L001-100045049 | E95: 8538 | F95: 44958 | I95: 1233 | J95: ប្រកាសរួម (ព្យួរទុក) | M95: 1233
A96: =A95+1 -> 87 | B96: Telephone expense | C96: កាំម៉ិនតែល | D96: L001-100045049 | E96: 8534 | F96: 44958 | I96: 4389 | J96: ប្រកាសរួម (ព្យួរទុក) | M96: 4389
A97: =A96+1 -> 88 | B97: Service charge for repair car | C97: អេ & អេ អូតូ គ្រុប | D97: L001-100192173 | E97: 212000102 | F97: 44964 | I97: 43840 | J97: បានប្រកាស (អនុញ្ញាត) | L97: 43840 | M97: 0
A98: =A97+1 -> 89 | B98: Service charge for repair car | C98: អេ & អេ អូតូ គ្រុប | D98: L001-100192173 | E98: 212000126 | F98: 44965 | I98: 135640 | J98: បានប្រកាស (អនុញ្ញាត) | L98: 135640 | M98: 0
A99: =A98+1 -> 90 | B99: Accounting and tax consulting service (Service for annual 2022yr) | C99: ANDREW & PHILIP ACCOUNTING CO., LTD. (A & P ACCOUNTING) | D99: K005-100161359 | E99: 230610 | F99: 45014 | I99: 405200 | J99: បានប្រកាស (អនុញ្ញាត) | L99: 405200 | M99: 0
A100: =A99+1 -> 91 | B100: Accounting service (Final payment service 2022) | C100: ANDREW & PHILIP ACCOUNTING CO., LTD. (A & P ACCOUNTING) | D100: K005-100161359 | E100: 230595 | F100: 45012 | I100: 1826100 | J100: បានប្រកាស (អនុញ្ញាត) | L100: 1826100 | M100: 0
A101: =A100+1 -> 92 | B101: I-Customs permit, trucking fee, non insurance .... | C101: 2020JUN LOGISTICS CO., LTD. | D101: K010-902001839 | E101: 2023-0122 | F101: 44999 | I101: 587105 | J101: បានប្រកាស (អនុញ្ញាត) | L101: 587105 | M101: 0 | N101: បានត្រួតពិនិត្យ
A102: =A101+1 -> 93 | B102: I-Lift on &Lift off charge | C102: កំពង់ផែស្វយ័តក្រុងព្រះសីហនុ | D102: L001-100044638 | E102: 32269 | F102: 44992 | I102: 23085 | J102: ព្យួរទុក (មិនមានទិន្នន័យ) | M102: 23085
A103: =A102+1 -> 94 | B103: I-Customs permit, customs clearance charge, trucking fee, inspection fee.... | C103: 2020JUN LOGISTICS CO., LTD. | D103: K010-902001839 | E103: 2023-0123 | F103: 44999 | I103: 599252 | J103: បានប្រកាស (អនុញ្ញាត) | L103: 599252 | M103: 0 | N103: បានត្រួតពិនិត្យ
A104: =A103+1 -> 95 | B104: I-Lift on & Lift off (I15534) | C104: កំពង់ផែស្វយ័តក្រុងព្រះសីហនុ | D104: L001-100044638 | E104: 32272 | F104: 44992 | I104: 35235 | J104: ព្យួរទុក (មិនមានទិន្នន័យ) | M104: 35235
A105: =A104+1 -> 96 | B105: I-Customs permit, customs clearance fee, trucking fee, Non insurance... | C105: 2020JUN LOGISTICS CO., LTD. | D105: K010-902001839 | E105: 2023-0126 | F105: 45001 | I105: 470669 | J105: បានប្រកាស (អនុញ្ញាត) | L105: 470669 | M105: 0 | N105: បានត្រួតពិនិត្យ
A106: =A105+1 -> 97 | B106: I-Lift on charge, gate fee charge (I1601) | C106: កំពង់ផែស្វយ័តភ្នំពេញ "ក.ស.ភ" | D106: L001-100044999 | E106: INV20230311339 | F106: 44988 | I106: 19488 | J106: បានប្រកាស (អនុញ្ញាត) | L106: 19488 | M106: 0 | N106: ពិនិត្យរួច
A107: =A106+1 -> 98 | B107: I-Customs permit, customs clearance fee, trucking fee, non insurance, ..(I13327) | C107: 2020JUN LOGISTICS CO., LTD. | D107: K010-902001839 | E107: 2023-0100 | F107: 44987 | I107: 577230 | J107: បានប្រកាស (អនុញ្ញាត) | L107: 577230 | M107: 0 | N107: បានត្រួតពិនិត្យ
A108: =A107+1 -> 99 | B108: E-Customs clearance, trucking fee, Lift on charge, Customs export permit ..(E33) | C108: 2020JUN LOGISTICS CO., LTD. | D108: K010-902001839 | E108: 2023-0138 | F108: 45015 | I108: 557968 | J108: បានប្រកាស (អនុញ្ញាត) | L108: 557968 | M108: 0 | N108: បានត្រួតពិនិត្យ
A109: =A108+1 -> 100 | B109: E-Lift off charge, Gate fee charge (E33) | C109: កំពង់ផែស្វយ័តភ្នំពេញ "ក.ស.ភ" | D109: L001-100044999 | E109: INV20230315225 | F109: 45012 | I109: 29218 | J109: បានប្រកាស (អនុញ្ញាត) | L109: 29218 | M109: 0 | N109: ពិនិត្យរួច
...

Sheet Annex III-EX
A1: តារាងឧបសម្ព័ន្ធ III
A2: បញ្ជាក់អំពីការលក់
A3: (ការនាំចេញ/លក់បន្ទុករដ្ឋ/លក់តាមអត្រា០%)
A4: ក្រុមហ៊ុន៖ | B4: ='Company information'!E2 -> វ៉ាយអិលធី​ អ៊ិនធើណេសិនណល | D4: សវនករពន្ធដារ៖ | E4: ='Company information'!E8 -> លោក ជុំ សុភា
A5: លេខ អតប ៖ | B5: ='Company information'!E4 -> L001-100192823 | E5: ='Company information'!F8 -> លោក ជា ហុកស័រ
A6: ='Company information'!E21 -> ស្នើសុំបង្វិលសងអាករលើតម្លៃបន្ថែមតាមអនឡាញចុះថ្ងៃទី៣ ខែកុម្ភៈ ឆ្នាំ២០២៥ | D6: ទឹកប្រាក់ស្នើសុំបង្វិលសងចំនួន៖ | E6: ='Company information'!E22 -> 352496017
A7: ល.រ | B7: បរិយាយ | C7: ប្រតិវេទន៍គយនាំចេញ/វិក្កយបត្រ | E7: តម្លៃជារៀល
C8: លេខ | D8: ចុះថ្ងៃទី ខែ ឆ្នាំ
A10: 1 | B10: SCRAP STEEL CORD GLUE | C10: GTAP-TS-202403-01/E4531 | D10: 27-03-2024 | E10: 781804
A11: =A10+1 -> 2 | B11: TRUCK BUS RADIAL TYRE | C11: GTT202400774/E4029 | D11: 15-03-2024 | E11: 132450398
A12: =A11+1 -> 3
A13: =A12+1 -> 4
A14: =A13+1 -> 5
A15: =A14+1 -> 6
A16: =A15+1 -> 7
A17: =A16+1 -> 8
A18: =A17+1 -> 9
A19: =A18+1 -> 10
A20: =A19+1 -> 11
A21: =A20+1 -> 12
A22: =A21+1 -> 13
A23: =A22+1 -> 14
... A1690: =A1689+1 -> 1681
A1692: ទឹកប្រាក់សរុបចំនួន | E1692: =SUM(E10:E1690) -> 133232202 | I1692: =E1692+'Annex IV-Local Sale'!G12*10 -> 188347762
D1694: រាជធានីភ្នំពេញ.ថ្ងៃទី ខែ ឆ្នាំ២០២៥
D1695: មន្ត្រីសវនកម្ម
D1698: ='Company information'!E9 -> ជុំ សុភា | E1698: ='Company information'!F9 -> ជា ហុកស័រ

Sheet Annex IV-Local Sale
A1: តារាងឧបសម្ព័ន្ធ IV
A2: បញ្ជាក់អំពីអាករលើធាតុចេញ
A3: ( ការលក់ក្នុងស្រុក )
A4: ក្រុមហ៊ុន៖ | B4: ='Company information'!E2 -> វ៉ាយអិលធី​ អ៊ិនធើណេសិនណល | G4: សវនករពន្ធដារ៖ | H4: ='Company information'!E8 -> លោក ជុំ សុភា
A5: លេខ អតប ៖ | B5: ='Company information'!E4 -> L001-100192823 | H5: ='Company information'!F8 -> លោក ជា ហុកស័រ
A6: ='Company information'!E21 -> ស្នើសុំបង្វិលសងអាករលើតម្លៃបន្ថែមតាមអនឡាញចុះថ្ងៃទី៣ ខែកុម្ភៈ ឆ្នាំ២០២៥ | F6: ទឹកប្រាក់ស្នើសុំបង្វិលសងចំនួន៖ | H6: ='Company information'!E22 -> 352496017
A7: ល.រ | B7: បរិយាយ | C7: វិក្កយបត្រ | E7: អាករតម្លៃ (ដុល្លា) | F7: អត្រាប្តូរប្រាក់ | G7: អាករតម្លៃ (រៀល) | H7: ផ្សេងៗ
C8: លេខ | D8: ថ្ងៃ ខែ ឆ្នាំ
A10: 1 | B10: CUT TIRES | C10: GT20240001 | D10: 45446 | G10: 5511556
A12: សរុបអាករលើការលក់ក្នុងស្រុក | G12: =SUM(G10:G10) -> 5511556
G14: រាជធានីភ្នំពេញ.ថ្ងៃទី ខែ ឆ្នាំ២០២៥
G15: មន្ត្រីសវនកម្ម
M16: 543815675772
M17: 26860899310
F18: ='Company information'!E9 -> ជុំ សុភា | H18: ='Company information'!F9 -> ជា ហុកស័រ | M18: =SUM(M16:M17) -> 570676575082
M19: 40586375597
M20: 5769650
M21: =SUM(M19:M20) -> 40592145247

Sheet 303B
A1: បរិយាយ | B1: កាលបរិច្ឆេទស្នើសុំ | C1: បំណុលពន្ធ | D1: ទឹកប្រាក់ស្នើសុំ | E1: ទឹកប្រាក់សំរេចបង្វិលសង | F1: ទឹកប្រាក់ត្រូវបង្វិលសង | G1: បំណុលពន្ធនៅសល់
A2: ស្នើសុំលើកទី1
A3: ស្នើសុំលើកទី2
A4: ស្នើសុំលើកទី3
A5: ស្នើសុំលើកទី4
A6: ស្នើសុំលើកទី5
A7: ស្នើសុំលើកទី... | B7: ='Company information'!E21 -> ស្នើសុំបង្វិលសងអាករលើតម្លៃបន្ថែមតាមអនឡាញចុះថ្ងៃទី៣ ខែកុម្ភៈ ឆ្នាំ២០២៥ | D7: ='Company information'!E22 -> 352496017 | E7: ='AnnexII-Local Pur'!C743 -> 349012336
A9: បរិយាយ | B9: ចំនួនច្បាប់ | C9: លេខ | D9: សរុបទឹកប្រាក់ អតប VAT | F9: បរិយាយ | G9: ចំនួនច្បាប់ | H9: លេខ | I9: ទឹកប្រាក់សរុប
A10: ប្រតិវេទន៍គយសម្រាប់ការនាំចូល (បន្ទុករដ្ឋ) | B10: =COUNT('Annex 0-IM State Charge'!G9:G15) -> 0 | C10: មានភ្ជាប់ក្នុងតារាងឧបសម្ព័ន្ធ I | D10: ='Annex 0-IM State Charge'!G17 -> 0 | F10: ប្រតិវេទន៍គយសំរាប់ការនាំចេញ
A11: ប្រតិវេទន៍គយសម្រាប់ការនាំចូល (មិនមែនបន្ទុករដ្ឋ) | B11: =COUNT('Annex I-IM Non-State Charge'!G16:G17) -> 1 | C11: មានភ្ជាប់ក្នុងតារាងឧបសម្ព័ន្ធ II | D11: ='Annex I-IM Non-State Charge'!G19 -> 2877646 | F11: ឯកសារដឹកជញ្ជូន
A12: វិក្ក័យប័ត្រទិញក្នុងស្រុក | B12: =COUNT('AnnexII-Local Pur'!I9:I723) -> 713 | C12: មានភ្ជាប់ក្នុងតារាងឧបសម្ព័ន្ធ III | D12: ='AnnexII-Local Pur'!I724 -> 353183179 | F12: វិក្កយបត្រសំរាប់ការនាំចេញ | G12: =COUNT('Annex III-EX'!E9:E1691) -> 2 | H12: មានភ្ជាប់ក្នុងតារាងឧបសម្ព័ន្ធ IV | I12: ='Annex III-EX'!E1692 -> 133232202
F13: វិក្កយបត្រសំរាប់ការលក់ក្នុងស្រុក | G13: =COUNT('Annex IV-Local Sale'!G9:G11) -> 1 | H13: មានភ្ជាប់ក្នុងតារាងឧបសម្ព័ន្ធ V | I13: ='Annex IV-Local Sale'!G12*10 -> 55115560
F14: ឯកសារទូទាត់
F15: ឯកសារផ្សេងៗទៀត
A17: បរិយាយ | B17: ទិន្នានុប្បវត្តទិញ | D17: ទិន្នានុប្បវត្តលក់ | F17: ទឹកប្រាក់អាចបង្វិលសង
B18: តម្លៃ | C18: អាករ | D18: តម្លៃ | E18: អាករ
A19: យោង
A20: អាករលើធាតុចូល
A21: - នាំចូល | B21: =C21*10 -> 28776460 | C21: =D11 -> 2877646
A22: - ទិញក្នុងស្រុក | B22: =D12*10 -> 3531831790 | C22: =B22*10% -> 353183179
A23: អាករលើធាតុចេញ
A24: - នាំចេញ | D24: ='Annex III-EX'!E1692 -> 133232202
A25: - លក់ក្នុងស្រុក | D25: ='Annex IV-Local Sale'!G12*10 -> 55115560 | E25: =D25*10% -> 5511556
A26: សរុប | B26: =SUM(B21:B22) -> 3560608250 | C26: =SUM(C21:C22) -> 356060825 | D26: =SUM(D24:D25) -> 188347762 | E26: =SUM(E24:E25) -> 5511556 | F26: =C26-E26 -> 350549269
A28: ទឹកប្រាក់ស្នើសុំបង្វិលសង | B28: ទឹកប្រាក់កាត់បន្ថយ | C28: ទឹកប្រាក់នៅសល់ | D28: មូលហេតុ
A29: ='Company information'!E22 -> 352496017 | B29: =A29-C29 -> 3483681 | C29: ='AnnexII-Local Pur'!C743 -> 349012336 | D29: មិនបានប្រកាស ខុសលេខវិក្កយបត្រ វិក្កយបត្រស្ទួន និងព្យួរទុក

Sheet Taxpaid
C4: ='Company information'!E7 -> ខែធ្នូ ឆ្នាំ២០២២ ដល់ខែធ្នូ ឆ្នាំ២០២៤
B5: ល.រ | C5: ប្រភេទពន្ធ | D5: ចំនួនទឺកប្រាក់ពន្ធ | E5: 43221 | F5: =EDATE(E5,1) -> 43252 | G5: =EDATE(F5,1) -> 43282 | H5: =EDATE(G5,1) -> 43313 | I5: =EDATE(H5,1) -> 43344 | J5: =EDATE(I5,1) -> 43374 | K5: =EDATE(J5,1) -> 43405 | L5: =EDATE(K5,1) -> 43435 | M5: =EDATE(L5,1) -> 43466 | ... DX5: =EDATE(DW5,1) -> 46966
B6: 1 | C6: ពន្ធលើប្រាក់បៀវត្ស | D6: =SUM(E6:DX6) -> 0
B7: 2 | C7: ពន្ធលើអត្ថប្រយោជន៍បន្ថែម | D7: =SUM(E7:DX7) -> 0
B8: 3 | C8: ប្រាក់រំដោះពន្ធលើប្រាក់ចំណូល | D8: =SUM(E8:DX8) -> 0
B9: 4 | C9: ពន្ធលើប្រាក់ចំណូលប្រចាំឆ្នាំ | D9: =SUM(E9:DX9) -> 0
B10: 5 | C10: ពន្ធកាត់ទុកលើសេវាកម្ម ១៥% | D10: =SUM(E10:DX10) -> 0
B11: 6 | C11: ពន្ធកាត់ទុកលើអនិវាសនជន(ការប្រាក់) | D11: =SUM(E11:DX11) -> 0
B12: 7 | C12: ពន្ធកាត់ទុកលើអនិវាសនជន(សេវាគ្រប់គ្រង បច្ចេកទេស) | D12: =SUM(E12:DX12) -> 0
B13: 8 | C13: ពន្ធកាត់ទុកលើអនិវាសនជន (ភាគលាភ) | D13: =SUM(E13:DX13) -> 0
B14: 9 | C14: ពន្ធកាត់ទុកលើថ្លៃឈ្នួល (រូបវន្តបុគ្គល) | D14: =SUM(E14:DX14) -> 0
B15: 10 | C15: ពន្ធកាត់ទុកលើថ្លៃឈ្នួល (នីតិបុគ្គល) | D15: =SUM(E15:DX15) -> 0
B16: 11 | C16: ពន្ធលើផ្ទាំងផ្សព្វផ្សាយ - ផ្ទាំងផ្សាយពាណិជ្ជកម្ម | D16: =SUM(E16:DX16) -> 0
B17: 12 | C17: អាករលើតម្លៃបន្ថែម | D17: =SUM(E17:DX17) -> 0
... B20: 14 | C20: ពន្ធប៉ាតង់ | D20: =SUM(E20:DX20) -> 0
C21: សរុបទឹកប្រាក់ពន្ធបានបង់ចូលរដ្ឋ | D21: =SUM(D6:D20) -> 0

Sheet Damco
A1: តារាងឧបសម្ព័ន្ឋ
A2: តារាងប្រៀធៀបវិក្ក័យប័ត្រស្នើសុំបង្វិលសងអាករលើតំលៃបន្ថែម ( Cross checking )
A3: ='Annex 0-IM State Charge'!#REF! -> #REF!
A4: ='Annex 0-IM State Charge'!#REF! -> #REF!
A5: ល.រ | B5: ក្រុមហ៊ុនស្នើសុំបង្វិលសង | E5: អ្នកផ្គត់ផ្គង់ | J5: ផ្សេងៗ
B6: វិក្កយបត្រ | E6: សហគ្រាស | F6: លេខអតប | G6: វិក្កយបត្រ
B7: លេខ | C7: ថ្ងៃទី ខែ ឆ្នាំ | D7: ប្រាក់អាករ | G7: លេខ | H7: ថ្ងៃទី ខែ ឆ្នាំ | I7: ប្រាក់អាករ
A8: 1 | B8: 030209 | C8: 41246 | D8: 58.25 | E8: A P L Logistics | F8: 100046460 | G8: 030209 | H8: 41246 | I8: 58.25 | J8: បានបង់
A9: 2 | B9: 030231 | C9: 41248 | D9: 4 | E9: A P L Logistics | F9: 100046460 | G9: 030231 | H9: 41248 | I9: 4 | J9: បានបង់
A10: 3 | B10: 030241 | C10: 41254 | D10: 49.75 | E10: A P L Logistics | F10: 100046460 | G10: 030241 | H10: 41254 | I10: 49.75 | J10: បានបង់
A11: 4 | B11: 030262 | C11: 41254 | D11: 181.79 | E11: A P L Logistics | F11: 100046460 | G11: 030262 | H11: 41254 | I11: 181.79 | J11: បានបង់
A12: 5 | B12: 030302 | C12: 41260 | D12: 46.69 | E12: A P L Logistics | F12: 100046460 | G12: 030302 | H12: 41260 | I12: 46.69 | J12: បានបង់
A13: 6 | B13: 030328 | C13: 41260 | D13: 236.64 | E13: A P L Logistics | F13: 100046460 | G13: 030328 | H13: 41260 | I13: 236.64 | J13: បានបង់
A14: 7 | B14: 030343 | C14: 41261 | D14: 4 | E14: A P L Logistics | F14: 100046460 | G14: 030343 | H14: 41261 | I14: 4 | J14: បានបង់
A15: 8 | B15: 030353 | C15: 41261 | D15: 10 | E15: A P L Logistics | F15: 100046460 | G15: 030353 | H15: 41261 | I15: 10 | J15: បានបង់
A16: 9 | B16: 030450 | C16: 41274 | D16: 87.52 | E16: A P L Logistics | F16: 100046460 | G16: 030450 | H16: 41274 | I16: 87.52 | J16: បានបង់
A17: 10 | B17: 030469 | C17: 41274 | D17: 39.29 | E17: A P L Logistics | F17: 100046460 | G17: 030469 | H17: 41274 | I17: 39.29 | J17: បានបង់
A18: Total 12/2012 | D18: =SUM(D8:D17) -> 717.93 | H18: USD | I18: =SUM(I8:I17) -> 717.93
A19: Total 12/2012 | G19: 3995 | H19: RIEL | I19: =I18*G19 -> 2868130.3
A20: 1 | B20: 029920 | C20: 41218 | D20: 77 | E20: A P L Logistics | F20: 100046460 | G20: 029920 | H20: 41218 | I20: 77 | J20: បានបង់
A21: 2 | B21: 029981 | C21: 41225 | D21: 115.89 | E21: A P L Logistics | F21: 100046460 | G21: 029981 | H21: 41225 | I21: 115.89 | J21: បានបង់
A22: 3 | B22: 030003 | C22: 41225 | D22: 82.91 | E22: A P L Logistics | F22: 100046460 | G22: 030003 | H22: 41225 | I22: 82.91 | J22: បានបង់
A23: 4 | B23: 030044 | C23: 41232 | D23: 55.32 | E23: A P L Logistics | F23: 100046460 | G23: 030044 | H23: 41232 | I23: 55.32 | J23: បានបង់
A24: 5 | B24: 030062 | C24: 41232 | D24: 32.03 | E24: A P L Logistics | F24: 100046460 | G24: 030062 | H24: 41232 | I24: 32.03 | J24: បានបង់
A25: Total 11/2012 | D25: =SUM(D20:D24) -> 363.15 | H25: USD | I25: =SUM(I20:I24) -> 363.15
A26: Total 11/2012 | G26: 3999 | H26: RIEL | I26: =I25*G26 -> 1452236.8
A27: 1 | B27: 029638 | C27: 41183 | D27: 89.93 | E27: A P L Logistics | F27: 100046460 | G27: 029638 | H27: 41183 | I27: 89.93 | J27: បានបង់
A28: 2 | B28: 029716 | C28: 41190 | D28: 49.63 | E28: A P L Logistics | F28: 100046460 | G28: 029716 | H28: 41190 | I28: 49.63 | J28: បានបង់
A29: 3 | B29: 029766 | C29: 41197 | D29: 115.81 | E29: A P L Logistics | F29: 100046460 | G29: 029766 | H29: 41197 | I29: 115.81 | J29: បានបង់
A30: 4 | B30: 029816 | C30: 41204 | D30: 101.98 | E30: A P L Logistics | F30: 100046460 | G30: 029816 | H30: 41204 | I30: 101.98 | J30: បានបង់
A31: 5 | B31: 029869 | C31: 41211 | D31: 67.28 | E31: A P L Logistics | F31: 100046460 | G31: 029869 | H31: 41211 | I31: 67.28 | J31: បានបង់
A32: Total 10/2012 | D32: =SUM(D27:D31) -> 424.63 | H32: USD | I32: =SUM(I27:I31) -> 424.63
A33: Total 10/2012 | G33: 4028 | H33: RIEL | I33: =I32*G33 -> 1710409.6
A34: 1 | B34: 029426 | C34: 41162 | D34: 206.96 | E34: A P L Logistics | F34: 100046460 | G34: 029426 | H34: 41162 | I34: 206.96 | J34: បានបង់
A35: 2 | B35: 029501 | C35: 41169 | D35: 69.7 | E35: A P L Logistics | F35: 100046460 | G35: 029501 | H35: 41169 | I35: 69.7 | J35: បានបង់
A36: 3 | B36: 029565 | C36: 41176 | D36: 46.66 | E36: A P L Logistics | F36: 100046460 | G36: 029565 | H36: 41176 | I36: 46.66 | J36: បានបង់
A37: Total 09/2012 | D37: =SUM(D34:D36) -> 323.32 | H37: USD | I37: =SUM(I34:I36) -> 323.32
A38: Total 09/2012 | G38: 4044 | H38: RIEL | I38: =I37*G38 -> 1307506.1
A39: 1 | B39: 029026 | C39: 41127 | D39: 37.84 | E39: A P L Logistics | F39: 100046460 | G39: 029026 | H39: 41127 | I39: 37.84 | J39: បានបង់
A40: 2 | B40: 029107 | C40: 41134 | D40: 95.46 | E40: A P L Logistics | F40: 100046460 | G40: 029107 | H40: 41134 | I40: 95.46 | J40: បានបង់
A41: 3 | B41: 029223 | C41: 41141 | D41: 106.66 | E41: A P L Logistics | F41: 100046460 | G41: 029223 | H41: 41141 | I41: 106.66 | J41: បានបង់
A42: 4 | B42: 029278 | C42: 41148 | D42: 32.8 | E42: A P L Logistics | F42: 100046460 | G42: 029278 | H42: 41148 | I42: 32.8 | J42: បានបង់
A43: Total 08/2012 | D43: =SUM(D39:D42) -> 272.76 | H43: USD | I43: =SUM(I39:I42) -> 272.76
A44: Total 08/2012 | G44: 4053 | H44: RIEL | I44: =I43*G44 -> 1105496.3
A45: 1 | B45: 028640 | C45: 41092 | D45: 29.26 | E45: A P L Logistics | F45: 100046460 | G45: 028640 | H45: 41092 | I45: 29.26 | J45: បានបង់
A46: 2 | B46: 028709 | C46: 41099 | D46: 24.66 | E46: A P L Logistics | F46: 100046460 | G46: 028709 | H46: 41099 | I46: 24.66 | J46: បានបង់
A47: 3 | B47: 028809 | C47: 41106 | D47: 31.02 | E47: A P L Logistics | F47: 100046460 | G47: 028809 | H47: 41106 | I47: 31.02 | J47: បានបង់
A48: 4 | B48: 028874 | C48: 41113 | D48: 209.58 | E48: A P L Logistics | F48: 100046460 | G48: 028874 | H48: 41113 | I48: 209.58 | J48: បានបង់
A49: 5 | B49: 028550 | C49: 41115 | D49: 66.92 | E49: A P L Logistics | F49: 100046460 | G49: 028550 | H49: 41115 | I49: 66.92 | J49: បានបង់
A50: 6 | B50: 028948 | C50: 41120 | D50: 73.23 | E50: A P L Logistics | F50: 100046460 | G50: 028948 | H50: 41120 | I50: 73.23 | J50: បានបង់
A51: 7 | B51: 028961 | C51: 41120 | D51: 27.84 | E51: A P L Logistics | F51: 100046460 | G51: 028961 | H51: 41120 | I51: 27.84 | J51: បានបង់
A52: Total 07/2012 | D52: =SUM(D45:D51) -> 462.51 | H52: USD | I52: =SUM(I45:I51) -> 462.51
A53: Total 07/2012 | G53: 4073 | H53: RIEL | I53: =I52*G53 -> 1883803.2
A54: 1 | B54: 030377 | C54: 41267 | D54: 53.34 | E54: A P L Logistics | F54: 100046460 | G54: 030377 | H54: 41267 | I54: 53.34 | J54: បានបង់
A55: 2 | B55: 030407 | C55: 41267 | D55: 63.05 | E55: A P L Logistics | F55: 100046460 | G55: 030407 | H55: 41267 | I55: 63.05 | J55: បានបង់
A56: 3 | B56: 030516 | C56: 41281 | D56: 81 | E56: A P L Logistics | F56: 100046460 | G56: 030516 | H56: 41281 | I56: 81 | J56: បានបង់
A57: 4 | B57: 030532 | C57: 41281 | D57: 335.98 | E57: A P L Logistics | F57: 100046460 | G57: 030532 | H57: 41281 | I57: 335.98 | J57: បានបង់
A58: 5 | B58: 030562 | C58: 41282 | D58: 10 | E58: A P L Logistics | F58: 100046460 | G58: 030562 | H58: 41282 | I58: 10 | J58: បានបង់
A59: 6 | B59: 030586 | C59: 41285 | D59: 7.2 | E59: A P L Logistics | F59: 100046460 | G59: 030586 | H59: 41285 | I59: 7.2 | J59: បានបង់
A60: 7 | B60: 030614 | C60: 41286 | D60: 217.03 | E60: A P L Logistics | F60: 100046460 | G60: 030614 | H60: 41288 | I60: 217.03 | J60: បានបង់
A61: 8 | B61: 030638 | C61: 41289 | D61: 10 | E61: A P L Logistics | F61: 100046460 | G61: 030638 | H61: 41289 | I61: 10 | J61: បានបង់
A62: 9 | B62: 030758 | C62: 41296 | D62: 25.25 | E62: A P L Logistics | F62: 100046460 | G62: 030758 | H62: 41296 | I62: 25.25 | J62: បានបង់
A63: 10 | B63: 030848 | C63: 41302 | D63: 357.23 | E63: A P L Logistics | F63: 100046460 | G63: 030848 | H63: 41302 | I63: 357.23 | J63: បានបង់
A64: Total 01/2013 | D64: =SUM(D54:D63) -> 1160.08 | H64: USD | I64: =SUM(I54:I63) -> 1160.08
A65: Total 01/2013 | G65: 3995 | H65: RIEL | I65: =I64*G65 -> 4634519.6
A66: 1 | B66: 030891 | C66: 41310 | D66: 28.52 | E66: A P L Logistics | F66: 100046460 | G66: 030891 | H66: 41310 | I66: 28.52 | J66: បានបង់
A67: 2 | B67: 030911 | C67: 41310 | D67: 374.87 | E67: A P L Logistics | F67: 100046460 | G67: 030911 | H67: 41310 | I67: 374.87 | J67: បានបង់
A68: 3 | B68: 030965 | C68: 41312 | D68: 10 | E68: A P L Logistics | F68: 100046460 | G68: 030965 | H68: 41312 | I68: 10 | J68: បានបង់
A69: 4 | B69: 030999 | C69: 41316 | D69: 115 | E69: A P L Logistics | F69: 100046460 | G69: 030999 | H69: 41316 | I69: 115 | J69: បានបង់
A70: 5 | B70: 031026 | C70: 41317 | D70: 4 | E70: A P L Logistics | F70: 100046460 | G70: 031026 | H70: 41317 | I70: 4 | J70: បានបង់
A71: 6 | B71: 031069 | C71: 41323 | D71: 266.83 | E71: A P L Logistics | F71: 100046460 | G71: 031069 | H71: 41323 | I71: 266.83 | J71: បានបង់
A72: 7 | B72: 031108 | C72: 41326 | D72: 20 | E72: A P L Logistics | F72: 100046460 | G72: 031108 | H72: 41326 | I72: 20 | J72: បានបង់
A73: 8 | B73: 031138 | C73: 41331 | D73: 142.19 | E73: A P L Logistics | F73: 100046460 | G73: 031138 | H73: 41331 | I73: 142.19 | J73: បានបង់
A74: Total 02/2013 | D74: =SUM(D66:D73) -> 961.41 | H74: USD | I74: =SUM(I66:I73) -> 961.41
A75: Total 02/2013 | G75: 3995 | H75: RIEL | I75: =I74*G75 -> 3840833
A76: 1 | B76: 031210 | C76: 41337 | D76: 115.18 | E76: A P L Logistics | F76: 100046460 | G76: 031210 | H76: 41337 | I76: 115.18 | J76: បានបង់
A77: 2 | B77: 031195 | C77: 41337 | D77: 107.71 | E77: A P L Logistics | F77: 100046460 | G77: 031195 | H77: 41337 | I77: 107.71 | J77: បានបង់
A78: 3 | B78: 031383 | C78: 41344 | D78: 109.81 | E78: A P L Logistics | F78: 100046460 | G78: 031383 | H78: 41344 | I78: 109.81 | J78: បានបង់
A79: 4 | B79: 031454 | C79: 41351 | D79: 307.84 | E79: A P L Logistics | F79: 100046460 | G79: 031454 | H79: 41351 | I79: 307.84 | J79: បានបង់
A80: 5 | B80: 031507 | C80: 41354 | D80: 8 | E80: APL Logistics | F80: 100046460 | G80: 031507 | H80: 41354 | I80: 8 | J80: បានបង់
A81: 6 | B81: 031511 | C81: 41354 | D81: 10 | E81: APL Logistics | F81: 100046460 | G81: 031511 | H81: 41354 | I81: 10 | J81: បានបង់
A82: 7 | B82: 031543 | C82: 41358 | D82: 190.8 | E82: A P L Logistics | F82: 100046460 | G82: 031543 | H82: 41358 | I82: 190.8 | J82: បានបង់
A83: 8 | B83: 031588 | C83: 41360 | D83: 8 | E83: APL Logistics | F83: 100046460 | G83: 031588 | H83: 41360 | I83: 8 | J83: បានបង់
A84: 9 | B84: 031592 | C84: 41360 | D84: 10 | E84: APL Logistics | F84: 100046460 | G84: 031592 | H84: 41360 | I84: 10 | J84: បានបង់
A85: Total 03/2013 | D85: =SUM(D76:D84) -> 867.34 | H85: USD | I85: =SUM(I76:I84) -> 867.34
A86: Total 03/2013 | G86: 3995 | H86: RIEL | I86: =I85*G86 -> 3465023.3
A87: 1 | B87: 031616 | C87: 41365 | D87: 40.32 | E87: APL Logistics | F87: 100046460 | G87: 031616 | H87: 41365 | I87: 40.32 | J87: បានបង់
A88: 2 | B88: 031641 | C88: 41366 | D88: 168.98 | E88: A P L Logistics | F88: 100046460 | G88: 031641 | H88: 41366 | I88: 168.98 | J88: បានបង់
A89: 3 | B89: 031704 | C89: 41372 | D89: 104.23 | E89: A P L Logistics | F89: 100046460 | G89: 031704 | H89: 41372 | I89: 104.23 | J89: បានបង់
A90: 4 | B90: 031730 | C90: 41372 | D90: 222.39 | E90: A P L Logistics | F90: 100046460 | G90: 031730 | H90: 41372 | I90: 222.39 | J90: បានបង់
A91: 5 | B91: 031771 | C91: 41374 | D91: 10 | E91: APL Logistics | F91: 100046460 | G91: 031771 | H91: 41374 | I91: 10 | J91: បានបង់
A92: 6 | B92: 31799 | C92: 41382 | D92: 149.76 | E92: A P L Logistics | F92: 100046460 | G92: 31799 | H92: 41382 | I92: 149.76 | J92: បានបង់
A93: 7 | B93: 31883 | C93: 41386 | D93: 144.43 | E93: A P L Logistics | F93: 100046460 | G93: 31883 | H93: 41386 | I93: 144.43 | J93: បានបង់
A94: 8 | B94: 31901 | C94: 41387 | D94: 8 | E94: APL Logistics | F94: 100046460 | G94: 31901 | H94: 41387 | I94: 8 | J94: បានបង់
A95: 9 | B95: 031922 | C95: 41394 | D95: 134.76 | E95: A P L Logistics | F95: 100046460 | G95: 031922 | H95: 41394 | I95: 134.76 | J95: បានបង់
A96: 10 | B96: 31940 | C96: 41394 | D96: 155.38 | E96: A P L Logistics | F96: 100046460 | G96: 31940 | H96: 41394 | I96: 155.38 | J96: បានបង់
A97: Total 04/2013 | D97: =SUM(D87:D96) -> 1138.25 | H97: USD | I97: =SUM(I87:I96) -> 1138.25
A98: Total 04/2013 | G98: 4000 | H98: RIEL | I98: =I97*G98 -> 4553000
A99: 1 | B99: 031981 | C99: 41397 | D99: 20 | E99: APL Logistics | F99: 100046460 | G99: 031981 | H99: 41397 | I99: 20 | J99: បានបង់
A100: 2 | B100: 031984 | C100: 41400 | D100: 25 | E100: APL Logistics | F100: 100046460 | G100: 031984 | H100: 41400 | I100: 25 | J100: បានបង់
...

Sheet Chea Fat
A1: តារាងឧបសម្ព័ន្ឋ
A2: តារាងប្រៀធៀបវិក្ក័យប័ត្រស្នើសុំបង្វិលសងអាករលើតំលៃបន្ថែម ( Cross checking )
A3: នាមករណ៏សហគ្រាស : Maurea Garments Corp
A4: VAT TIN : 1 0 0 0 5 2 9 6 7
A5: ល.រ | B5: ក្រុមហ៊ុនស្នើសុំបង្វិលសង | E5: អ្នកផ្គត់ផ្គង់ | J5: ផ្សេងៗ
B6: វិក័យបត្រ័ | E6: សហគ្រាស | F6: លេខអតប | G6: វិក័យបត្រ័
B7: លេខ | C7: ថ្ងៃទី ខែ ឆ្នាំ | D7: ប្រាក់អាករ | G7: លេខ | H7: ថ្ងៃទី ខែ ឆ្នាំ | I7: ប្រាក់អាករ
A8: 1 | B8: 07-0360 | C8: 41842 | D8: 41.5 | E8: YUSEN LOGISTICS | F8: 104015799 | G8: 07-0360 | H8: 41842 | I8: 41.5
A9: 2 | B9: 07-0367 | C9: 41842 | D9: 64.57 | E9: YUSEN LOGISTICS | F9: 104015799 | G9: 07-0367 | H9: 41842 | I9: 64.57
A10: 3 | B10: 07-0368 | C10: 41842 | D10: 59.11 | E10: YUSEN LOGISTICS | F10: 104015799 | G10: 07-0368 | H10: 41842 | I10: 59.11
A11: 4 | B11: 07-0517 | C11: 41849 | D11: 75.93 | E11: YUSEN LOGISTICS | F11: 104015799 | G11: 07-0517 | H11: 41849 | I11: 75.93
A12: 5 | B12: 08-0039 | C12: 41856 | D12: 46.05 | E12: YUSEN LOGISTICS | F12: 104015799 | G12: 08-0039 | H12: 41856 | I12: 46.05
A13: 6 | B13: 08-0044 | C13: 41856 | D13: 41.5 | E13: YUSEN LOGISTICS | F13: 104015799 | G13: 08-0044 | H13: 41856 | I13: 41.5
A14: 7 | B14: 08-0185 | C14: 41864 | D14: 27.9 | E14: YUSEN LOGISTICS | F14: 104015799 | G14: 08-0185 | H14: 41864 | I14: 27.9
A15: 8 | B15: 08-0677 | C15: 41882 | D15: 143 | E15: YUSEN LOGISTICS | F15: 104015799 | G15: 08-0677 | H15: 41882 | I15: 143
A16: 9 | B16: 08-0685 | C16: 41882 | D16: 60.33 | E16: YUSEN LOGISTICS | F16: 104015799 | G16: 08-0685 | H16: 41882 | I16: 60.33
A17: 10 | B17: 09-0111 | C17: 41892 | D17: 27.53 | E17: YUSEN LOGISTICS | F17: 104015799 | G17: 09-0111 | H17: 41892 | I17: 27.53
A18: 11 | B18: 09-0117 | C18: 41892 | D18: 53.64 | E18: YUSEN LOGISTICS | F18: 104015799 | G18: 09-0117 | H18: 41892 | I18: 53.64
A19: 12 | B19: 09-0199 | C19: 41898 | D19: 34.77 | E19: YUSEN LOGISTICS | F19: 104015799 | G19: 09-0199 | H19: 41898 | I19: 34.77
... A40: 33 | B40: 502-0531 | C40: 42059 | D40: 102.92 | E40: YUSEN LOGISTICS | F40: 104015799 | G40: 502-0531 | H40: 42059 | I40: 102.92
A41: TOTAL 7/2012-02/2015 | D41: =SUM(D8:D40) -> 1831.45 | I41: =SUM(I8:I40) -> 1831.45
E44: YUSEN LOGISTICS | F44: 104015799 | G44: 2-00309 | H44: 41619 | I44: 5

Sheet S G L CAMBODIA
A1: តារាងឧបសម្ព័ន្ឋ
A2: តារាងប្រៀធៀបវិក្ក័យប័ត្រស្នើសុំបង្វិលសងអាករលើតំលៃបន្ថែម ( Cross checking )
A3: នាមករណ៏សហគ្រាស : Maurea Garments Corp
A4: VAT TIN : 1 0 0 0 5 2 9 6 7
A5: ល.រ | B5: ក្រុមហ៊ុនស្នើសុំបង្វិលសង | E5: អ្នកផ្គត់ផ្គង់ | J5: ផ្សេងៗ
B6: វិក័យបត្រ័ | E6: សហគ្រាស | F6: លេខអតប | G6: វិក័យបត្រ័
B7: លេខ | C7: ថ្ងៃទី ខែ ឆ្នាំ | D7: ប្រាក់អាករ | G7: លេខ | H7: ថ្ងៃទី ខែ ឆ្នាំ | I7: ប្រាក់អាករ
A8: 1 | B8: 227231 | C8: 41246 | D8: 8.5 | E8: S G L CAMBODIA | F8: 100119816 | G8: 227231 | H8: 41246 | I8: 8.5
A9: 2 | B9: 227288 | C9: 41246 | D9: 52.36 | E9: S G L CAMBODIA | F9: 100119816 | G9: 227288 | H9: 41246 | I9: 52.36
A10: 3 | B10: 227430 | C10: 41255 | D10: 21.2 | E10: S G L CAMBODIA | F10: 100119816 | G10: 227430 | H10: 41255 | I10: 21.2
A11: 4 | B11: 227461 | C11: 41255 | D11: 29.57 | E11: S G L CAMBODIA | F11: 100119816 | G11: 227461 | H11: 41255 | I11: 29.57
A12: 5 | B12: 227539 | C12: 41260 | D12: 34.24 | E12: S G L CAMBODIA | F12: 100119816 | G12: 227539 | H12: 41260 | I12: 34.24
A13: 6 | B13: 227543 | C13: 41260 | D13: 8.93 | E13: S G L CAMBODIA | F13: 100119816 | G13: 227543 | H13: 41260 | I13: 8.93
A14: 7 | B14: 227552 | C14: 41260 | D14: 27.62 | E14: S G L CAMBODIA | F14: 100119816 | G14: 227552 | H14: 41260 | I14: 27.62
A15: 8 | B15: 227583 | C15: 41261 | D15: 57.77 | E15: S G L CAMBODIA | F15: 100119816 | G15: 227583 | H15: 41261 | I15: 57.77
A16: 9 | B16: 227586 | C16: 41261 | D16: 24 | E16: S G L CAMBODIA | F16: 100119816 | G16: 227586 | H16: 41261 | I16: 24
A17: 10 | B17: 227605 | C17: 41261 | D17: 28.88 | E17: S G L CAMBODIA | F17: 100119816 | G17: 227605 | H17: 41261 | I17: 28.88
A18: 11 | B18: 227826 | C18: 41274 | D18: 24 | E18: S G L CAMBODIA | F18: 100119816 | G18: 227826 | H18: 41274 | I18: 24
A19: 12 | B19: 227862 | C19: 41274 | D19: 36.26 | E19: S G L CAMBODIA | F19: 100119816 | G19: 227862 | H19: 41274 | I19: 36.26
... A458: 455 | B458: 443954 | C458: 42002 | D458: 44.24 | E458: S G L CAMBODIA | F458: 100119816 | G458: 443954 | H458: 42002 | I458: 44.24
A459: TOTAL 7/2012-02/2015 | D459: =SUM(D8:D458) -> 16281.5 | I459: =SUM(I8:I458) -> 16281.5

Sheet Sheet3
A1: តារាងឧបសម្ព័ន្ឋ
A2: តារាងប្រៀធៀបវិក្ក័យប័ត្រស្នើសុំបង្វិលសងអាករលើតំលៃបន្ថែម ( Cross checking )
A3: នាមករណ៏សហគ្រាស : Maurea Garments Corp
A4: VAT TIN : 1 0 0 0 5 2 9 6 7
A5: ល.រ | B5: ក្រុមហ៊ុនស្នើសុំបង្វិលសង | E5: អ្នកផ្គត់ផ្គង់ | J5: ផ្សេងៗ
B6: វិក័យបត្រ័ | E6: សហគ្រាស | F6: លេខអតប | G6: វិក័យបត្រ័
B7: លេខ | C7: ថ្ងៃទី ខែ ឆ្នាំ | D7: ប្រាក់អាករ | G7: លេខ | H7: ថ្ងៃទី ខែ ឆ្នាំ | I7: ប្រាក់អាករ

Sheet Sale - June
A1: សៀវភៅទិនានុប្បវត្តិលក់- នាំចេញ
A2: ខែ​​ មិថុនា ឆ្នាំ ២០១៥
A3: ជី អេវើរហ្រ្គីន( ខេមបូឌា​ ) នីតធីង | K3: Vat:100193102
A4: ភូមិជ្រៃកោង សង្កាត់ចោមចៅ ខណ្ឌ ពោធិសែនជ័យ ក្រុង ភ្នំពេញ | K4: Average: | L4: 4088
A5: វិក្ក័យប័ត្រ | I5: ការផ្គត់ផ្គង់
A6: កាលបរិចេ្ឆទ | B6: វិក្ក័យប័ត្រ | C6: អ្នកទិញ | D6: លេខ អតប | E6: បរិយាយ | F6: បរិមាណ | I6: karlk;Cab;Gakr | M6: សរុបថ្លៃទិញ
D7: TIN | G7: ការផ្គត់ផ្គង់ | H7: ការនាំចេញ | I7: lk;;»übuKþlCab;Gakr | K7: lk;;»üGñkeRbIR)as; | M7: រួមទាំអាករ
G8: មិនជាប់អាករ | H8: អត្រា​​ 0 % | I8: តំលៃជាប់អាករ | J8: អាករ | K8: តំលៃជាប់អាករ | L8: អាករ
A9: 42160 | B9: E 55119 | C9: LPP S.A | E9: Men's Top | F9: 137 CT | H9: 41519138 | M9: =G9+H9 -> 41519138
A10: 42160 | B10: E 53624 | C10: PRIMARK | E10: See Val Note | F10: 655 CT | H10: 157610622 | M10: =G10+H10 -> 157610622
A11: 42160 | B11: E 9812 | C11: SMYK SP Z.O.O | E11: Girls Knitted Dress | F11: 518 CT | H11: 75926121 | M11: =G11+H11 -> 75926121
A12: 42164 | B12: E 10122 | C12: SMYK SP Z.O.O | E12: Girls Knitted Sweat Shirt | F12: 404 CT | H12: 109260590 | M12: =G12+H12 -> 109260590
A13: 42167 | B13: E 57854 | C13: PRIMARK | E13: Men's Long Sleeve Hoodie | F13: 550 CT | H13: 136860570 | M13: =G13+H13 -> 136860570
A14: 42167 | B14: E 57078 | C14: LPP S.A | E14: Men's Top | F14: 1094 CT | H14: 189450332 | M14: =G14+H14 -> 189450332
A15: 42174 | B15: E 60607 | C15: CAPRI SRL | E15: Men's Hoody | F15: 827 CT | H15: 267888456 | M15: =G15+H15 -> 267888456
A16: 42174 | B16: E 59730 | C16: LPP S.A | E16: Men's Jogging Top | F16: 815 CT | H16: 233561904 | M16: =G16+H16 -> 233561904
A17: 42174 | B17: E 60079 | C17: LPP S.A | E17: Men's Sweater +Top | F17: 400 CT | H17: 106100285 | M17: =G17+H17 -> 106100285
A18: 42175 | B18: E 61426 | C18: VISAGE LIMITED | E18: Men's Pari / Monica / Leyton Crew | F18: 556 CT | H18: 145296432 | M18: =G18+H18 -> 145296432
A19: 42175 | B19: E 61432 | C19: PRIMARK STORES LIMITED | E19: See Val Note | F19: 1220 CT | H19: 299682480 | M19: =G19+H19 -> 299682480
A20: 42181 | B20: E 63424 | C20: PRIMARK US CORP | E20: Men Chest Print Zip | F20: 37 CT | H20: 6493691 | M20: =G20+H20 -> 6493691
... A22: 42181 | B22: E 63568 | C22: VISAGE LIMITED | E22: Men's Morgan Crew + Connect Crew+ Leyton | F22: 338 CT | H22: 94840834 | M22: =G22+H22 -> 94840834
A23: =L4 -> 4088 | E23: Riel | F23: =SUM(F9:F22) -> 0 | H23: =SUM(H9:H22) -> 1890852742 | M23: =SUM(M9:M22) -> 1890852742
A24: Total USD | E24: USD | G24: =G23/L4 -> 0 | H24: =H23/L4 -> 462537.36 | I24: =I23*4034 -> 0 | J24: =J23*4034 -> 0 | K24: =K23*4034 -> 0 | L24: =L23*4034 -> 0 | M24: =M23/L4 -> 462537.36
G25: Box 12 | H25: Box 13 | I25: Box 14 | J25: Box 15 | K25: Box 14 | L25: Box 15
H26: Approved By :
N27: =H23*1% -> 18908527
H28: =H24*1% -> 4625.3736
G29: Sales
G30: July | H30: ='Sale - Jul'!H30 -> 3379679902 | I30: 21 invoices
G31: Aug | H31: ='Sale - Aug'!I47 -> 5225078447 | I31: 38 invoices
G32: June | H32: =H23 -> 1890852742 | I32: 14 invoices
G33: Total: | H33: =SUM(H30:H32) -> 10495611091 | I33: =14+38+21 -> 73
H37: =H24*1% -> 4625.3736

Sheet Sale - Jul
A1: សៀវភៅទិនានុប្បវត្តិលក់- នាំចេញ
A2: ខែ​​ កក្កដា ឆ្នាំ ២០១៥
A3: ជី អេវើរហ្រ្គីន( ខេមបូឌា​ ) នីតធីង | K3: Vat:100193102
A4: ភូមិជ្រៃកោង សង្កាត់ចោមចៅ ខណ្ឌ ពោធិសែនជ័យ ក្រុង ភ្នំពេញ | K4: Average: | L4: 4099
A5: វិក្ក័យប័ត្រ | I5: ការផ្គត់ផ្គង់
A6: កាលបរិចេ្ឆទ | B6: វិក្ក័យប័ត្រ | C6: អ្នកទិញ | D6: លេខ អតប | E6: បរិយាយ | F6: បរិមាណ | I6: karlk;Cab;Gakr | M6: សរុបថ្លៃទិញ
D7: TIN | G7: ការផ្គត់ផ្គង់ | H7: ការនាំចេញ | I7: lk;;»übuKþlCab;Gakr | K7: lk;;»üGñkeRbIR)as; | M7: រួមទាំអាករ
G8: មិនជាប់អាករ | H8: អត្រា​​ 0 % | I8: តំលៃជាប់អាករ | J8: អាករ | K8: តំលៃជាប់អាករ | L8: អាករ
A9: 42188 | B9: E 65884 | C9: LPP S.A | E9: Men's Jogging Top | F9: 1841 CT | H9: 469164366 | M9: =G9+H9 -> 469164366
A10: 42188 | B10: E 65884 | C10: LPP S.A | E10: Men's Knit Trousers | F10: 631 CT | H10: 224637197 | M10: =G10+H10 -> 224637197
A11: 42188 | B11: E 65484 | C11: Primark Tiendas Slu | E11: Men's Zip Thru Hoody | F11: 343 CT | H11: 88553682 | M11: =G11+H11 -> 88553682
A12: 42189 | B12: E 67494 | C12: PRIMARK | E12: Men's Long Sleeve Zip Thru Hoodie | F12: 1093 CT | H12: 282184182 | M12: =G12+H12 -> 282184182
A13: 42194 | B13: E 68109 | C13: PRIMARK STORES LIMITED | E13: 7B (Boy) Core Hoody | F13: 600 CT | H13: 137692800 | M13: =G13+H13 -> 137692800
A14: 42194 | B14: E 68146 | C14: PRIMARK | E14: Men's Zip Thru Hoody | F14: 772 CT | H14: 199310328 | M14: =G14+H14 -> 199310328
A15: 42195 | B15: E 69396 | C15: LPP S.A | E15: Men's Knit Sweater + Jogging Top | F15: 1133 CT | H15: 222232983 | M15: =G15+H15 -> 222232983
A16: 42195 | B16: E 69396 | C16: LPP S.A | E16: Men's Knit Trousers | F16: 39 CT | H16: 15787217 | M16: =G16+H16 -> 15787217
A17: 42195 | B17: E 69549 | C17: PRIMARK STORES LIMITED | E17: Men + Boy Hoodies | F17: 638 CT | H17: 147298512 | M17: =G17+H17 -> 147298512
A18: 42196 | B18: E 70637 | C18: LPP S.A | E18: Ladies Jogging Top | F18: 490 CT | H18: 108300780 | M18: =G18+H18 -> 108300780
A19: 42196 | B19: E 70637 | C19: LPP S.A | E19: Men's Knit Trousers | F19: 99 CT | H19: 39649873 | M19: =G19+H19 -> 39649873
A20: 42196 | B20: E 70627 | C20: Primark Tiendas Slu | E20: Men's Zip Thru Hoody | F20: 2066 CT | H20: 532736694 | M20: =G20+H20 -> 532736694
... A29: 42203 | B29: E 73524 | C29: VDR FASHION GROUP BV | E29: Ladies Knitted Blazer | F29: 191 CT | H29: 114575606 | M29: =G29+H29 -> 114575606
A30: =L4 -> 4099 | E30: Riel | F30: =SUM(F9:F29) -> 0 | H30: =SUM(H9:H29) -> 3379679902 | M30: =SUM(M9:M29) -> 3379679902
A31: Total USD | E31: USD | G31: =G30/L4 -> 0 | H31: =H30/L4 -> 824513.27 | I31: =I30*4034 -> 0 | J31: =J30*4034 -> 0 | K31: =K30*4034 -> 0 | L31: =L30*4034 -> 0 | M31: =M30/L4 -> 824513.27
G32: Box 12 | H32: Box 13 | I32: Box 14 | J32: Box 15 | K32: Box 14 | L32: Box 15
H33: Approved By :
H35: =H31*1% -> 8245.1327
H44: =H31*1% -> 8245.1327

Sheet Sale - Aug
A1: សៀវភៅទិនានុប្បវត្តិលក់- នាំចេញ
A2: ខែ​​ សីហា ឆ្នាំ ២០១៥
A3: ជី អេវើរហ្រ្គីន( ខេមបូឌា​ ) នីតធីង | L3: Vat:100193102
A4: ភូមិជ្រៃកោង សង្កាត់ចោមចៅ ខណ្ឌ ពោធិសែនជ័យ ក្រុង ភ្នំពេញ | L4: Average: | M4: 4095
A5: វិក្ក័យប័ត្រ | J5: ការផ្គត់ផ្គង់
A6: កាលបរិចេ្ឆទ | B6: វិក្ក័យប័ត្រ | C6: អ្នកទិញ | D6: លេខ អតប | E6: បរិយាយ | F6: បរិមាណ | J6: karlk;Cab;Gakr | N6: សរុបថ្លៃទិញ
D7: TIN | F7: ការផ្គត់ផ្គង់ | I7: ការនាំចេញ | J7: lk;;»übuKþlCab;Gakr | L7: lk;;»üGñkeRbIR)as; | N7: រួមទាំអាករ
F8: មិនជាប់អាករ | I8: អត្រា​​ 0 % | J8: តំលៃជាប់អាករ | K8: អាករ | L8: តំលៃជាប់អាករ | M8: អាករ
A9: 42202 | B9: E 72202 | C9: Primark Us Corp | E9: Men Zip Thru Hoody | F9: 65 | G9: CT | I9: 16764930 | N9: =H9+I9 -> 16764930
A10: 42203 | B10: E 13027 | C10: LPP S.A | E10: Ladies Knit Jogging Top | F10: 64 | G10: CT | I10: 26424115 | N10: =H10+I10 -> 26424115
A11: 42208 | B11: E 13359 | C11: VDR Fashion Group BV | E11: Ladies Knit Shirt | F11: 36 | G11: CT | I11: 29192000 | N11: =H11+I11 -> 29192000
A12: 42209 | B12: E 74804 | C12: Primark Us Corp | E12: Boy Hoody | F12: 305 | G12: CT | I12: 70028000 | N12: =H12+I12 -> 70028000
A13: 42209 | B13: E 74578 | C13: LPP S.A | E13: Men's Jogging Top | F13: 904 | G13: CT | I13: 242980473 | N13: =H13+I13 -> 242980473
A14: 42210 | B14: E 76431 | C14: Primark | E14: Men Zip Thru Hoody | F14: 700 | G14: CT | I14: 180986400 | N14: =H14+I14 -> 180986400
A15: 42210 | B15: E 76547 | C15: Primark Stores Limited | E15: 7/2Boy Core Hoody | F15: 800 | G15: CT | I15: 174420000 | N15: =H15+I15 -> 174420000
A16: 42210 | B16: E 65557 | C16: LPP S.A | E16: Ladies Jogging Top | F16: 680 | G16: CT | I16: 178829338 | N16: =H16+I16 -> 178829338
A17: 42210 | B17: E 65557 | C17: LPP S.A | E17: Men's Knit Trousers | F17: 93 | G17: CT | I17: 36022203 | N17: =H17+I17 -> 36022203
A18: 42215 | B18: E 76966 | C18: Primark | E18: See Val Note | F18: 355 | G18: CT | I18: 89531330 | N18: =H18+I18 -> 89531330
A19: 42215 | B19: E 76966 | C19: Primark | E19: Ladies Nylon Zip Back Fl Legging | F19: 267 | G19: CT | I19: 191743220 | N19: =H19+I19 -> 191743220
A20: 42216 | B20: E 78298 | C20: Primark Us Corp | E20: Mens Hoody | F20: 70 | G20: CT | I20: 18116280 | N20: =H20+I20 -> 18116280
... A41: 42237 | B41: E 87246 | C41: Primark Stores Limited | E41: Boy's Hoody | F41: 200 | G41: CT | I41: 41197900 | N41: =H41+I41 -> 41197900
A42: 42237 | B42: E 87199 | C42: Primakr Tiendas S.l.u. | E42: Men's Knit Chest Print Zip Thru | F42: 250 | G42: CT | I42: =15750*4079 -> 64244250 | N42: =H42+I42 -> 64244250
A43: 42237 | B43: E 87074 | C43: Primark 47 Mary Street Dublin1. | E43: Men's Knit Chest Print Zip Thru | F43: 192 | G43: CT | I43: 49339584 | N43: =H43+I43 -> 49339584
A44: 42237 | B44: E 86097 | C44: Primark Stores Limited | E44: See Val Note | F44: 756 | G44: CT | I44: 178378749 | N44: =H44+I44 -> 178378749
A45: 42237 | B45: E 86347 | C45: LPP S.A | E45: Men's Jogging Top | F45: 725 | G45: CT | I45: 162100480 | N45: =H45+I45 -> 162100480
A46: 42237 | B46: E 86347 | C46: LPP S.A | E46: Men's Knit Trousers | F46: 531 | G46: CT | I46: 203679970 | N46: =H46+I46 -> 203679970
A47: =M4 -> 4095 | E47: Riel | I47: =SUM(I9:I46) -> 5225078447 | N47: =SUM(N9:N46) -> 5225078447
A48: Total USD | E48: USD | H48: =H47/M4 -> 0 | I48: =I47/M4 -> 1275965.4 | J48: =J47*4034 -> 0 | K48: =K47*4034 -> 0 | L48: =L47*4034 -> 0 | M48: =M47*4034 -> 0 | N48: =N47/M4 -> 1275965.4
H49: Box 12 | J49: Box 14 | K49: Box 15 | L49: Box 14 | M49: Box 15
I50: Approved By :
I52: =I48*1% -> 12759.654
I61: =I48*1% -> 12759.654
